Workbook

Sheet 1. RG-RQ
B1: Research Goal
B2: Purpose | C2: Collection and comparison of studies on
B3: Issue | C3: model-driven approaches that explicitly address the software architecture of
B4: Object | C4: artificial intelligence applications (machine learning, deep learning)
B5: Viewpoint | C5: from the point of view of researchers
B7: Based on:
B8: Caldiera, V. R. B. G., & Rombach, H. D. (1994). The goal question metric approach. Encyclopedia of software engineering, 528-532.
A13: ID | B13: Research Question | C13: Motivation
A14: RQ1 | B14: What language aspects of MDE are addressed in the approaches, e.g., abstract syntax, concrete syntax, metamodel, etc.? | C14: This RQ aims to assess the pillar concepts of MDE languages concerning comprehensiveness (of modeling) and applicability (maturity).
A15: RQ2 | B15: Which phases of AI development aligned with the CRISP-DM methodology are covered by the approaches? | C15: This RQ assesses the extent to which the development phases of CRISP-DM are covered. As a result, implications can be made about the extent of support.
A16: RQ3 | B16: Which industrial domains are supported by MDE for AI approaches? | C16: This RQ enables finding industries that are using MDE in the context of AI and thus driving the development of MDE for AI using domain-specific tools and methodologies towards the needs of the (specific) industry.
A17: RQ4 | B17: What are the used methods and MDE tools the proposed approaches~rely on? | C17: This RQ allows assessing the underlying principles of methods used, e.g. SysML or MDE methods and the related toolchain such as WebGME. Consequently, further development can rely on these technologies to gain maturity instead of reinventing the wheel.
A18: RQ5 | B18: To what extent is communication between different stakeholders supported by MDE? | C18: Communication and business knowledge elaboration are one of the core pitfalls in the development of AI solutions \cite{piorkowski_how_2021}. Therefore, this question aims to assess the contribution to support fostering AI in the industry.
A19: RQ6 | B19: Which challenges and research directions are still open? | C19: This RQ will lead to future research directions and challenges for the model-based engineering of artificial intelligence applications due to a collection of limitations in the proposed approaches based on respective authors or our obtainment.

Sheet 2. Search Queries
E1: Databases Nr. of results
A2: ID | B2: Part 1 | D2: Part 2 | E2: IEEExplore | F2: ACM | G2: Springer | H2: DBLP | I2: Google Scholar
A3: SS1 | B3: MDE | C3: AND | D3: AI | E3: 5 | F3: 4 | G3: 6 | H3: 8 | I3: 0
A4: SS2 | B4: Model-Driven Engineering | C4: AND | D4: AI | E4: 8 | F4: 5 | G4: 15 | H4: 9 | I4: 6
A5: SS3 | B5: DSL | C5: AND | D5: AI | E5: 5 | F5: 4 | G5: 17 | H5: 1 | I5: 3
A6: SS4 | B6: Domain Specific Language | C6: AND | D6: AI | E6: 4 | F6: 3 | G6: 5 | H6: 6 | I6: 1
A7: SS5 | B7: Metamodeling | C7: AND | D7: AI | E7: 2 | F7: 1 | G7: 16 | H7: 3 | I7: 1
A8: SS6 | B8: Domain Modeling | C8: AND | D8: AI | E8: 1 | F8: 3 | G8: 12 | H8: 7 | I8: 2
A9: SS7 | B9: MDE | C9: AND | D9: Artificial Intelligence | E9: 5 | F9: 3 | G9: 31 | H9: 2 | I9: 2
A10: SS8 | B10: Model-Driven Engineering | C10: AND | D10: Artificial Intelligence | E10: 10 | F10: 9 | G10: 65 | H10: 4 | I10: 4
A11: SS9 | B11: DSL | C11: AND | D11: Artificial Intelligence | E11: 6 | F11: 2 | G11: 56 | H11: 1 | I11: 1
A12: SS10 | B12: Domain Specific Language | C12: AND | D12: Artificial Intelligence | E12: 8 | F12: 3 | G12: 45 | H12: 0 | I12: 2
A13: SS11 | B13: Metamodeling | C13: AND | D13: Artificial Intelligence | E13: 1 | F13: 1 | G13: 55 | H13: 0 | I13: 1
A14: SS12 | B14: Domain Modeling | C14: AND | D14: Artificial Intelligence | E14: 2 | F14: 2 | G14: 28 | H14: 2 | I14: 1
... A38: SS36 | B38: Domain Modeling | C38: AND | D38: Intelligence | E38: 3 | F38: 2 | G38: 31 | H38: 3 | I38: 1
E39: =SUM(E3:E38) -> 252 | F39: =SUM(F3:F38) -> 155 | G39: =SUM(G3:G38) -> 827 | H39: =SUM(H3:H38) -> 102 | I39: =SUM(I3:I38) -> 92
D40: Unique: | E40: 137 | F40: 83 | G40: 408 | H40: 81 | I40: 74

Sheet 3. Unique Results
A1: Key | B1: Item Type | C1: Publication Year | D1: Author | E1: Title | F1: Publication Title | G1: ISBN | H1: ISSN | I1: DOI | J1: Url | K1: Date | L1: Date Added | M1: Date Modified | N1: Access Date | O1: Pages | P1: Issue | Q1: Volume | R1: Journal Abbreviation | S1: Short Title | T1: Publisher | U1: Place | V1: Language | W1: Library Catalog | X1: Extra | Y1: Editor | Z1: Series Editor
A2: NGEXAYY3 | B2: journalArticle | C2: 2018 | D2: Zheng, Jun | E2: An output mapping variable fidelity metamodeling approach based on nested Latin hypercube design for complex engineering design optimization | F2: Applied Intelligence | H2: 0924-669X, 1573-7497 | I2: 10.1007/s10489-018-1164-8 | J2: http://link.springer.com/10.1007/s10489-018-1164-8 | K2: 2018-10 | L2: 44887.364 | M2: 44887.364 | N2: 44886.598 | O2: 3591-3611 | P2: 10 | Q2: 48 | R2: Appl Intell | V2: en | W2: DOI.org (Crossref)
A3: W3X5ABDE | B3: bookSection | C3: 2018 | D3: Swacha, Jakub | E3: SIPE: A Domain-Specific Language for Specifying Interactive Programming Exercises | F3: Towards a Synergistic Combination of Research and Practice in Software Engineering | G3: 978-3-319-65207-8 978-3-319-65208-5 | J3: http://link.springer.com/10.1007/978-3-319-65208-5_2 | K3: 2018 | L3: 44887.364 | M3: 44887.364 | N3: 44886.598 | O3: 15-29 | Q3: 733 | S3: SIPE | T3: Springer International Publishing | U3: Cham | W3: DOI.org (Crossref) | X3: Series Title: Studies in Computational Intelligence DOI: 10.1007/978-3-319-65208-5_2 | Y3: Kosiuczenko, Piotr; Madeyski, Lech
A4: 6BTFNFLU | B4: journalArticle | C4: 2018 | D4: Yang, Bin; Qiao, Lihong; Cai, Na; Zhu, Zuowei; Wulan, Muqi | E4: Manufacturing process information modeling using a metamodeling approach | F4: The International Journal of Advanced Manufacturing Technology | H4: 0268-3768, 1433-3015 | I4: 10.1007/s00170-016-9979-0 | J4: http://link.springer.com/10.1007/s00170-016-9979-0 | K4: 2018-02 | L4: 44887.364 | M4: 44887.364 | N4: 44886.598 | O4: 1579-1596 | P4: 5-8 | Q4: 94 | R4: Int J Adv Manuf Technol | V4: en | W4: DOI.org (Crossref)
A5: 7VKPKRGN | B5: bookSection | C5: 2010 | D5: Schlegel, Christian; Steck, Andreas; Brugali, Davide; Knoll, Alois | E5: Design Abstraction and Processes in Robotics: From Code-Driven to Model-Driven Engineering | F5: Simulation, Modeling, and Programming for Autonomous Robots | G5: 978-3-642-17318-9 978-3-642-17319-6 | J5: http://link.springer.com/10.1007/978-3-642-17319-6_31 | K5: 2010 | L5: 44887.364 | M5: 44887.364 | N5: 44886.598 | O5: 324-335 | Q5: 6472 | S5: Design Abstraction and Processes in Robotics | T5: Springer Berlin Heidelberg | U5: Berlin, Heidelberg | W5: DOI.org (Crossref) | X5: Series Title: Lecture Notes in Computer Science DOI: 10.1007/978-3-642-17319-6_31 | Y5: Ando, Noriaki; Balakirsky, Stephen; Hemker, Thomas; Reggiani, Monica; von Stryk, Oskar
A6: Q42UQ55J | B6: journalArticle | C6: 2019 | D6: Chen, Liming; Wang, Hu; Ye, Fan; Hu, Wei | E6: Comparative study of HDMRs and other popular metamodeling techniques for high dimensional problems | F6: Structural and Multidisciplinary Optimization | H6: 1615-147X, 1615-1488 | I6: 10.1007/s00158-018-2046-8 | J6: http://link.springer.com/10.1007/s00158-018-2046-8 | K6: 2019-01 | L6: 44887.364 | M6: 44887.364 | N6: 44886.598 | O6: 21-42 | P6: 1 | Q6: 59 | R6: Struct Multidisc Optim | V6: en | W6: DOI.org (Crossref)
A7: ZYBDV3MN | B7: journalArticle | C7: 2022 | D7: Di Ruscio, Davide; Kolovos, Dimitris; de Lara, Juan; Pierantonio, Alfonso; Tisi, Massimo; Wimmer, Manuel | E7: Low-code development and model-driven engineering: Two sides of the same coin? | F7: Software and Systems Modeling | H7: 1619-1366, 1619-1374 | I7: 10.1007/s10270-021-00970-2 | J7: https://link.springer.com/10.1007/s10270-021-00970-2 | K7: 2022-04 | L7: 44887.364 | M7: 44887.364 | N7: 44886.598 | O7: 437-446 | P7: 2 | Q7: 21 | R7: Softw Syst Model | S7: Low-code development and model-driven engineering | V7: en | W7: DOI.org (Crossref)
A8: 72LMJHKT | B8: bookSection | C8: 2016 | D8: Dingel, Juergen | E8: Complexity is the Only Constant: Trends in Computing and Their Relevance to Model Driven Engineering | F8: Graph Transformation | G8: 978-3-319-40529-2 978-3-319-40530-8 | J8: http://link.springer.com/10.1007/978-3-319-40530-8_1 | K8: 2016 | L8: 44887.364 | M8: 44887.364 | N8: 44886.598 | O8: 3-18 | Q8: 9761 | S8: Complexity is the Only Constant | T8: Springer International Publishing | U8: Cham | W8: DOI.org (Crossref) | X8: Series Title: Lecture Notes in Computer Science DOI: 10.1007/978-3-319-40530-8_1 | Y8: Echahed, Rachid; Minas, Mark
A9: JNMMFHBV | B9: journalArticle | C9: 2008 | D9: Hu, Wang; Enying, Li; Li, G. Y.; Zhong, Z. H. | E9: Optimization of sheet metal forming processes by the use of space mapping based metamodeling method | F9: The International Journal of Advanced Manufacturing Technology | H9: 0268-3768, 1433-3015 | I9: 10.1007/s00170-007-1253-z | J9: http://link.springer.com/10.1007/s00170-007-1253-z | K9: 2008-11 | L9: 44887.364 | M9: 44887.364 | N9: 44886.598 | O9: 642-655 | P9: 7-8 | Q9: 39 | R9: Int J Adv Manuf Technol | V9: en | W9: DOI.org (Crossref)
A10: NUQXM7FE | B10: journalArticle | C10: 2019 | D10: Coelho, Luis Pedro; Alves, Renato; Monteiro, Paulo; Huerta-Cepas, Jaime; Freitas, Ana Teresa; Bork, Peer | E10: NG-meta-profiler: fast processing of metagenomes using NGLess, a domain-specific language | F10: Microbiome | H10: 2049-2618 | I10: 10.1186/s40168-019-0684-8 | J10: https://microbiomejournal.biomedcentral.com/articles/10.1186/s40168-019-0684-8 | K10: 2019-12 | L10: 44887.364 | M10: 44887.364 | N10: 44886.598 | O10: 84 | P10: 1 | Q10: 7 | R10: Microbiome | S10: NG-meta-profiler | V10: en | W10: DOI.org (Crossref)
A11: JNNBIKDB | B11: bookSection | C11: 2003 | D11: Wu, Wenming; Dong, Yisheng | E11: Metamodeling-Based Semantic Web Languages | F11: E-Commerce and Web Technologies | G11: 978-3-540-40808-6 978-3-540-45229-4 | J11: http://link.springer.com/10.1007/978-3-540-45229-4_33 | K11: 2003 | L11: 44887.364 | M11: 44887.364 | N11: 44886.598 | O11: 339-347 | Q11: 2738 | T11: Springer Berlin Heidelberg | U11: Berlin, Heidelberg | W11: DOI.org (Crossref) | X11: Series Title: Lecture Notes in Computer Science DOI: 10.1007/978-3-540-45229-4_33 | Y11: Bauknecht, Kurt; Tjoa, A Min; Quirchmayr, Gerald | Z11: Goos, Gerhard; Hartmanis, Juris; van Leeuwen, Jan
A12: A89323UM | B12: bookSection | C12: 2010 | D12: Abramov, Jenny; Sturm, Arnon | E12: Supporting Layered Architecture Specifications: A Domain Modeling Approach | F12: Enterprise, Business-Process and Information Systems Modeling | G12: 978-3-642-13050-2 978-3-642-13051-9 | J12: http://link.springer.com/10.1007/978-3-642-13051-9_17 | K12: 2010 | L12: 44887.364 | M12: 44887.364 | N12: 44886.598 | O12: 195-207 | Q12: 50 | S12: Supporting Layered Architecture Specifications | T12: Springer Berlin Heidelberg | U12: Berlin, Heidelberg | V12: en | W12: DOI.org (Crossref) | X12: Series Title: Lecture Notes in Business Information Processing DOI: 10.1007/978-3-642-13051-9_17 | Y12: Bider, Ilia; Halpin, Terry; Krogstie, John; Nurcan, Selmin; Proper, Erik; Schmidt, Rainer; Ukor, Roland | Z12: van der Aalst, Will; Mylopoulos, John; Sadeh, Norman M.; Shaw, Michael J.; Szyperski, Clemens
A13: W5698GQL | B13: bookSection | C13: 2013 | D13: Grossmann, Georg; Jordan, Andreas; Muruganandha, Rishi; Selway, Matt; Stumptner, Markus | E13: Enabling Information Interoperability through Multi-domain Modeling | F13: Practice-Driven Research on Enterprise Transformation | G13: 978-3-642-38773-9 978-3-642-38774-6 | J13: http://link.springer.com/10.1007/978-3-642-38774-6_2 | K13: 2013 | L13: 44887.364 | M13: 44887.364 | N13: 44886.598 | O13: 16-33 | Q13: 151 | T13: Springer Berlin Heidelberg | U13: Berlin, Heidelberg | V13: en | W13: DOI.org (Crossref) | X13: Series Title: Lecture Notes in Business Information Processing DOI: 10.1007/978-3-642-38774-6_2 | Y13: Harmsen, Frank; Proper, Henderik A. | Z13: van der Aalst, Wil; Mylopoulos, John; Rosemann, Michael; Shaw, Michael J.; Szyperski, Clemens
A14: 6D2F4NLY | B14: journalArticle | C14: 2013 | D14: Mulo, Emmanuel; Zdun, Uwe; Dustdar, Schahram | E14: Domain-specific language for event-based compliance monitoring in process-driven SOAs | F14: Service Oriented Computing and Applications | H14: 1863-2386, 1863-2394 | I14: 10.1007/s11761-012-0121-3 | J14: http://link.springer.com/10.1007/s11761-012-0121-3 | K14: 2013-03 | L14: 44887.364 | M14: 44887.364 | N14: 44886.598 | O14: 59-73 | P14: 1 | Q14: 7 | R14: SOCA | V14: en | W14: DOI.org (Crossref)
A15: UQ2VR6UN | B15: bookSection | C15: 1991 | D15: van Gigch, John P. | E15: Diagnosis and Metamodeling of System Failures | F15: System Design Modeling and Metamodeling | G15: 978-1-4899-0678-6 978-1-4899-0676-2 | J15: http://link.springer.com/10.1007/978-1-4899-0676-2_14 | K15: 1991 | L15: 44887.364 | M15: 44887.364 | N15: 44886.598 | O15: 297-310 | T15: Springer US | U15: Boston, MA | V15: en | W15: DOI.org (Crossref) | X15: DOI: 10.1007/978-1-4899-0676-2_14
A16: UHWHUK72 | B16: journalArticle | C16: 2022 | D16: Kushari, Subrata; Gupta, Kritesh Kumar; Vaishali; Dey, Sudip | E16: Metamodeling-assisted probabilistic first ply failure analysis of laminated composite plates—RS-HDMR- and GPR-based approach | F16: Journal of the Brazilian Society of Mechanical Sciences and Engineering | H16: 1678-5878, 1806-3691 | I16: 10.1007/s40430-022-03674-w | J16: https://link.springer.com/10.1007/s40430-022-03674-w | K16: 2022-08 | L16: 44887.364 | M16: 44887.364 | N16: 44886.598 | O16: 374 | P16: 8 | Q16: 44 | R16: J Braz. Soc. Mech. Sci. Eng. | V16: en | W16: DOI.org (Crossref)
A17: PYVP2CUA | B17: bookSection | C17: 2011 | D17: Saleem, Muhammad Qaiser; Jaafar, Jafreezal; Hassan, Mohd Fadzil | E17: Security Modeling of SOA System Using Security Intent DSL | F17: Software Engineering and Computer Systems | G17: 978-3-642-22202-3 978-3-642-22203-0 | J17: http://link.springer.com/10.1007/978-3-642-22203-0_16 | K17: 2011 | L17: 44887.364 | M17: 44887.364 | N17: 44886.598 | O17: 176-190 | Q17: 181 | T17: Springer Berlin Heidelberg | U17: Berlin, Heidelberg | W17: DOI.org (Crossref) | X17: Series Title: Communications in Computer and Information Science DOI: 10.1007/978-3-642-22203-0_16 | Y17: Zain, Jasni Mohamad; Wan Mohd, Wan Maseri bt; El-Qawasmeh, Eyas
A18: R57L47XX | B18: bookSection | C18: 2019 | D18: Fickenscher, Jörg; Hannig, Frank; Teich, Jürgen | E18: DSL-Based Acceleration of Automotive Environment Perception and Mapping Algorithms for Embedded CPUs, GPUs, and FPGAs | F18: Architecture of Computing Systems – ARCS 2019 | G18: 978-3-030-18655-5 978-3-030-18656-2 | J18: http://link.springer.com/10.1007/978-3-030-18656-2_6 | K18: 2019 | L18: 44887.364 | M18: 44887.364 | N18: 44886.598 | O18: 71-86 | Q18: 11479 | T18: Springer International Publishing | U18: Cham | V18: en | W18: DOI.org (Crossref) | X18: Series Title: Lecture Notes in Computer Science DOI: 10.1007/978-3-030-18656-2_6 | Y18: Schoeberl, Martin; Hochberger, Christian; Uhrig, Sascha; Brehm, Jürgen; Pionteck, Thilo
A19: SGYHCIG2 | B19: journalArticle | C19: 2020 | D19: Iung, Aníbal; Carbonell, João; Marchezan, Luciano; Rodrigues, Elder; Bernardino, Maicon; Basso, Fabio Paulo; Medeiros, Bruno | E19: Systematic mapping study on domain-specific language development tools | F19: Empirical Software Engineering | H19: 1382-3256, 1573-7616 | I19: 10.1007/s10664-020-09872-1 | J19: https://link.springer.com/10.1007/s10664-020-09872-1 | K19: 2020-09 | L19: 44887.364 | M19: 44887.364 | N19: 44886.598 | O19: 4205-4249 | P19: 5 | Q19: 25 | R19: Empir Software Eng | V19: en | W19: DOI.org (Crossref)
A20: UVS2JJGV | B20: journalArticle | C20: 2022 | D20: Hoffmann, Benjamin; Urquhart, Neil; Chalmers, Kevin; Guckert, Michael | E20: An empirical evaluation of a novel domain-specific language – modelling vehicle routing problems with Athos | F20: Empirical Software Engineering | H20: 1382-3256, 1573-7616 | I20: 10.1007/s10664-022-10210-w | J20: https://link.springer.com/10.1007/s10664-022-10210-w | K20: 2022-12 | L20: 44887.364 | M20: 44887.364 | N20: 44886.598 | O20: 180 | P20: 7 | Q20: 27 | R20: Empir Software Eng | V20: en | W20: DOI.org (Crossref)
A21: VB46JCXX | B21: bookSection | C21: 2006 | D21: Sottet, Jean-Sébastien; Calvary, Gaëlle; Favre, Jean-Marie; Coutaz, Joëlle; Demeure, Alexandre; Balme, Lionel | E21: Towards Model Driven Engineering of Plastic User Interfaces | F21: Satellite Events at the MoDELS 2005 Conference | G21: 978-3-540-31780-7 978-3-540-31781-4 | J21: http://link.springer.com/10.1007/11663430_20 | K21: 2006 | L21: 44887.364 | M21: 44887.364 | N21: 44886.598 | O21: 191-200 | Q21: 3844 | T21: Springer Berlin Heidelberg | U21: Berlin, Heidelberg | W21: DOI.org (Crossref) | X21: Series Title: Lecture Notes in Computer Science DOI: 10.1007/11663430_20 | Y21: Bruel, Jean-Michel | Z21: Hutchison, David; Kanade, Takeo; Kittler, Josef; Kleinberg, Jon M.; Mattern, Friedemann; Mitchell, John C.; Naor, Moni; Nierstrasz, Oscar; Pandu Rangan, C.; Steffen, Bernhard; Sudan, Madhu; Terzopoulos, Demetri; Tygar, Dough; Vardi, Moshe Y.; Weikum, Gerhard
A22: AQ93UTSA | B22: journalArticle | C22: 2018 | D22: Chen, Liming; Qiu, Haobo; Jiang, Chen; Xiao, Mi; Gao, Liang | E22: Support Vector enhanced Kriging for metamodeling with noisy data | F22: Structural and Multidisciplinary Optimization | H22: 1615-147X, 1615-1488 | I22: 10.1007/s00158-017-1831-0 | J22: http://link.springer.com/10.1007/s00158-017-1831-0 | K22: 2018-04 | L22: 44887.364 | M22: 44887.364 | N22: 44886.598 | O22: 1611-1623 | P22: 4 | Q22: 57 | R22: Struct Multidisc Optim | V22: en | W22: DOI.org (Crossref)
A23: ID7RRDT3 | B23: bookSection | C23: 2008 | D23: Karagiannis, Dimitris; Höfferer, Peter | E23: Metamodeling as an Integration Concept | F23: Software and Data Technologies | G23: 978-3-540-70619-9 978-3-540-70621-2 | J23: http://link.springer.com/10.1007/978-3-540-70621-2_4 | K23: 2008 | L23: 44887.364 | M23: 44887.364 | N23: 44886.598 | O23: 37-50 | Q23: 10 | T23: Springer Berlin Heidelberg | U23: Berlin, Heidelberg | V23: en | W23: DOI.org (Crossref) | X23: ISSN: 1865-0929, 1865-0937 Series Title: Communications in Computer and Information Science DOI: 10.1007/978-3-540-70621-2_4 | Y23: Filipe, Joaquim; Shishkov, Boris; Helfert, Markus
A24: EYFZC2SV | B24: bookSection | C24: 2003 | D24: Hammond, Kevin; Michaelson, Greg | E24: Hume: A Domain-Specific Language for Real-Time Embedded Systems | F24: Generative Programming and Component Engineering | G24: 978-3-540-20102-1 978-3-540-39815-8 | J24: http://link.springer.com/10.1007/978-3-540-39815-8_3 | K24: 2003 | L24: 44887.364 | M24: 44887.364 | N24: 44886.598 | O24: 37-56 | Q24: 2830 | S24: Hume | T24: Springer Berlin Heidelberg | U24: Berlin, Heidelberg | W24: DOI.org (Crossref) | X24: Series Title: Lecture Notes in Computer Science DOI: 10.1007/978-3-540-39815-8_3 | Y24: Pfenning, Frank; Smaragdakis, Yannis | Z24: Goos, Gerhard; Hartmanis, Juris; van Leeuwen, Jan
A25: KRQA9EYE | B25: bookSection | C25: 2012 | D25: Kossakowski, Grzegorz; Amin, Nada; Rompf, Tiark; Odersky, Martin | E25: JavaScript as an Embedded DSL | F25: ECOOP 2012 – Object-Oriented Programming | G25: 978-3-642-31056-0 978-3-642-31057-7 | J25: http://link.springer.com/10.1007/978-3-642-31057-7_19 | K25: 2012 | L25: 44887.364 | M25: 44887.364 | N25: 44886.598 | O25: 409-434 | Q25: 7313 | T25: Springer Berlin Heidelberg | U25: Berlin, Heidelberg | W25: DOI.org (Crossref) | X25: Series Title: Lecture Notes in Computer Science DOI: 10.1007/978-3-642-31057-7_19 | Y25: Noble, James | Z25: Hutchison, David; Kanade, Takeo; Kittler, Josef; Kleinberg, Jon M.; Mattern, Friedemann; Mitchell, John C.; Naor, Moni; Nierstrasz, Oscar; Pandu Rangan, C.; Steffen, Bernhard; Sudan, Madhu; Terzopoulos, Demetri; Tygar, Doug; Vardi, Moshe Y.; Weikum, Gerhard
A26: 2G5FLEFB | B26: journalArticle | C26: 2013 | D26: Groenewegen, Danny M.; Visser, Eelco | E26: Integration of data validation and user interface concerns in a DSL for web applications | F26: Software & Systems Modeling | H26: 1619-1366, 1619-1374 | I26: 10.1007/s10270-010-0173-9 | J26: http://link.springer.com/10.1007/s10270-010-0173-9 | K26: 2013-02 | L26: 44887.364 | M26: 44887.364 | N26: 44886.598 | O26: 35-52 | P26: 1 | Q26: 12 | R26: Softw Syst Model | V26: en | W26: DOI.org (Crossref)
A27: K4YLN5WI | B27: journalArticle | C27: 1994 | D27: Zhang, Zhi; Jewett, Don L. | E27: DSL and MUSIC Under model misspecification and noise-conditions | F27: Brain Topography | H27: 0896-0267, 1573-6792 | I27: 10.1007/BF01186773 | J27: http://link.springer.com/10.1007/BF01186773 | K27: 1994-12 | L27: 44887.364 | M27: 44887.364 | N27: 44886.598 | O27: 151-161 | P27: 2 | Q27: 7 | R27: Brain Topogr | V27: en | W27: DOI.org (Crossref)
A28: XKN8WT8E | B28: journalArticle | C28: 2020 | D28: Bargigli, Leonardo; Riccetti, Luca; Russo, Alberto; Gallegati, Mauro | E28: Network calibration and metamodeling of a financial accelerator agent based model | F28: Journal of Economic Interaction and Coordination | H28: 1860-711X, 1860-7128 | I28: 10.1007/s11403-018-0217-8 | J28: http://link.springer.com/10.1007/s11403-018-0217-8 | K28: 2020-04 | L28: 44887.364 | M28: 44887.364 | N28: 44886.598 | O28: 413-440 | P28: 2 | Q28: 15 | R28: J Econ Interact Coord | V28: en | W28: DOI.org (Crossref)
A29: W99X6BAS | B29: bookSection | C29: 2021 | D29: Otter, Martin | E29: Multi-domain Modeling and Simulation | F29: Encyclopedia of Systems and Control | G29: 978-3-030-44183-8 978-3-030-44184-5 | J29: https://link.springer.com/10.1007/978-3-030-44184-5_140 | K29: 2021 | L29: 44887.364 | M29: 44887.364 | N29: 44886.598 | O29: 1367-1379 | T29: Springer International Publishing | U29: Cham | V29: en | W29: DOI.org (Crossref) | X29: DOI: 10.1007/978-3-030-44184-5_140 | Y29: Baillieul, John; Samad, Tariq
A30: LM8B7RYV | B30: journalArticle | C30: 2018 | D30: Fernandez-Duarte, Karem Prunella; Olaya-Galán, Nury Nathalia; Salas-Cárdenas, Sandra Patricia; Lopez-Rozo, Jazmin; Gutierrez-Fernandez, Maria Fernanda | E30: Bifidobacterium adolescentis (DSM 20083) and Lactobacillus casei (Lafti L26-DSL): Probiotics Able to Block the In Vitro Adherence of Rotavirus in MA104 Cells | F30: Probiotics and Antimicrobial Proteins | H30: 1867-1306, 1867-1314 | I30: 10.1007/s12602-017-9277-7 | J30: http://link.springer.com/10.1007/s12602-017-9277-7 | K30: 2018-03 | L30: 44887.364 | M30: 44887.364 | N30: 44886.598 | O30: 56-63 | P30: 1 | Q30: 10 | R30: Probiotics & Antimicro. Prot. | S30: Bifidobacterium adolescentis (DSM 20083) and Lactobacillus casei (Lafti L26-DSL) | V30: en | W30: DOI.org (Crossref)
A31: BYFGLPEU | B31: journalArticle | C31: 2016 | D31: Amaral, Vasco; Mernik, Marjan | E31: Special issue on quality in model-driven engineering | F31: Software Quality Journal | H31: 0963-9314, 1573-1367 | I31: 10.1007/s11219-016-9327-5 | J31: http://link.springer.com/10.1007/s11219-016-9327-5 | K31: 2016-09 | L31: 44887.364 | M31: 44887.364 | N31: 44886.598 | O31: 597-599 | P31: 3 | Q31: 24 | R31: Software Qual J | V31: en | W31: DOI.org (Crossref)
A32: D5KCLPHS | B32: bookSection | C32: 2009 | D32: Toro, Carlos; Graña, Manuel; Posada, Jorge; Vaquero, Javier; Sanín, Cesar; Szczerbicki, Edward | E32: Domain Modeling Based on Engineering Standards | F32: Knowledge-Based and Intelligent Information and Engineering Systems | G32: 978-3-642-04594-3 978-3-642-04595-0 | J32: http://link.springer.com/10.1007/978-3-642-04595-0_12 | K32: 2009 | L32: 44887.364 | M32: 44887.364 | N32: 44886.598 | O32: 95-102 | Q32: 5711 | T32: Springer Berlin Heidelberg | U32: Berlin, Heidelberg | W32: DOI.org (Crossref) | X32: Series Title: Lecture Notes in Computer Science DOI: 10.1007/978-3-642-04595-0_12 | Y32: Velásquez, Juan D.; Ríos, Sebastián A.; Howlett, Robert J.; Jain, Lakhmi C.
A33: 3HLW2KTQ | B33: bookSection | C33: 2008 | D33: Morbach, J.; Theißen, M.; Marquardt, W. | E33: An Introduction to Application Domain Modeling | F33: Collaborative and Distributed Chemical Engineering. From Understanding to Substantial Design Process Support | G33: 978-3-540-70551-2 978-3-540-70552-9 | J33: http://link.springer.com/10.1007/978-3-540-70552-9_4 | K33: 2008 | L33: 44887.364 | M33: 44887.364 | N33: 44886.598 | O33: 83-92 | Q33: 4970 | T33: Springer Berlin Heidelberg | U33: Berlin, Heidelberg | V33: en | W33: DOI.org (Crossref) | X33: ISSN: 0302-9743, 1611-3349 Series Title: Lecture Notes in Computer Science DOI: 10.1007/978-3-540-70552-9_4 | Y33: Nagl, Manfred; Marquardt, Wolfgang
A34: 2R9W2CEC | B34: journalArticle | C34: 2016 | D34: Yang, Qian; Cai, Shu; Dong, Shaowei; Chen, Lulu; Chen, Jifei; Cai, Tianming | E34: Biodegradation of 3-methyldiphenylether (MDE) by Hydrogenophaga atypical strain QY7-2 and cloning of the methy-oxidation gene mdeABCD | F34: Scientific Reports | H34: 2045-2322 | I34: 10.1038/srep39270 | J34: http://www.nature.com/articles/srep39270 | K34: 2016-12 | L34: 44887.364 | M34: 44887.364 | N34: 44886.598 | O34: 39270 | P34: 1 | Q34: 6 | R34: Sci Rep | V34: en | W34: DOI.org (Crossref)
A35: 9YFCUB8K | B35: bookSection | C35: 2002 | D35: Zielenski, Julian; Aznarez, Isabel; Onay, Tuncer; Tzounzouris, John; Markiewicz, Danuta; Tsui, Lap-Chee | E35: CFTR Mutation Detection by Multiplex Heteroduplex (mHET) Analysis on MDE Gel | F35: Cystic Fibrosis Methods and Protocols | G35: 978-1-59259-187-9 | J35: http://link.springer.com/10.1385/1-59259-187-6:03 | K35: 2002-03-04 | L35: 44887.364 | M35: 44887.364 | N35: 44886.598 | O35: 03-20 | Q35: 70 | T35: Humana Press | U35: New Jersey | V35: en | W35: DOI.org (Crossref) | X35: DOI: 10.1385/1-59259-187-6:03 DOI: 10.1385/1-59259-187-6:03
A36: ZTIQ238S | B36: bookSection | C36: 2005 | D36: Steel, Jim; Jézéquel, Jean-Marc | E36: Model Typing for Improving Reuse in Model-Driven Engineering | F36: Model Driven Engineering Languages and Systems | G36: 978-3-540-29010-0 978-3-540-32057-9 | J36: http://link.springer.com/10.1007/11557432_7 | K36: 2005 | L36: 44887.364 | M36: 44887.364 | N36: 44886.598 | O36: 84-96 | Q36: 3713 | T36: Springer Berlin Heidelberg | U36: Berlin, Heidelberg | W36: DOI.org (Crossref) | X36: Series Title: Lecture Notes in Computer Science DOI: 10.1007/11557432_7 | Y36: Briand, Lionel; Williams, Clay | Z36: Hutchison, David; Kanade, Takeo; Kittler, Josef; Kleinberg, Jon M.; Mattern, Friedemann; Mitchell, John C.; Naor, Moni; Nierstrasz, Oscar; Pandu Rangan, C.; Steffen, Bernhard; Sudan, Madhu; Terzopoulos, Demetri; Tygar, Dough; Vardi, Moshe Y.; Weikum, Gerhard
A37: 3JUDNKK6 | B37: bookSection | C37: 2016 | D37: Rouquette, Nicolas F. | E37: Simplifying OMG MOF-Based Metamodeling | F37: Leveraging Applications of Formal Methods, Verification and Validation: Discussion, Dissemination, Applications | G37: 978-3-319-47168-6 978-3-319-47169-3 | J37: http://link.springer.com/10.1007/978-3-319-47169-3_8 | K37: 2016 | L37: 44887.364 | M37: 44887.364 | N37: 44886.598 | O37: 97-118 | Q37: 9953 | T37: Springer International Publishing | U37: Cham | W37: DOI.org (Crossref) | X37: Series Title: Lecture Notes in Computer Science DOI: 10.1007/978-3-319-47169-3_8 | Y37: Margaria, Tiziana; Steffen, Bernhard
A38: KY4RYNHG | B38: bookSection | C38: 2010 | D38: Farwick, Matthias; Agreiter, Berthold; White, Jules; Forster, Simon; Lanzanasto, Norbert; Breu, Ruth | E38: A Web-Based Collaborative Metamodeling Environment with Secure Remote Model Access | F38: Web Engineering | G38: 978-3-642-13910-9 978-3-642-13911-6 | J38: http://link.springer.com/10.1007/978-3-642-13911-6_19 | K38: 2010 | L38: 44887.364 | M38: 44887.364 | N38: 44886.598 | O38: 278-291 | Q38: 6189 | T38: Springer Berlin Heidelberg | U38: Berlin, Heidelberg | W38: DOI.org (Crossref) | X38: Series Title: Lecture Notes in Computer Science DOI: 10.1007/978-3-642-13911-6_19 | Y38: Benatallah, Boualem; Casati, Fabio; Kappel, Gerti; Rossi, Gustavo | Z38: Hutchison, David; Kanade, Takeo; Kittler, Josef; Kleinberg, Jon M.; Mattern, Friedemann; Mitchell, John C.; Naor, Moni; Nierstrasz, Oscar; Pandu Rangan, C.; Steffen, Bernhard; Sudan, Madhu; Terzopoulos, Demetri; Tygar, Doug; Vardi, Moshe Y.; Weikum, Gerhard
A39: 958KA64C | B39: bookSection | C39: 2020 | D39: Amaral de Sousa, Victor; Burnay, Corentin; Snoeck, Monique | E39: B-MERODE: A Model-Driven Engineering and Artifact-Centric Approach to Generate Blockchain-Based Information Systems | F39: Advanced Information Systems Engineering | G39: 978-3-030-49434-6 978-3-030-49435-3 | J39: http://link.springer.com/10.1007/978-3-030-49435-3_8 | K39: 2020 | L39: 44887.364 | M39: 44887.364 | N39: 44886.598 | O39: 117-133 | Q39: 12127 | S39: B-MERODE | T39: Springer International Publishing | U39: Cham | V39: en | W39: DOI.org (Crossref) | X39: Series Title: Lecture Notes in Computer Science DOI: 10.1007/978-3-030-49435-3_8 | Y39: Dustdar, Schahram; Yu, Eric; Salinesi, Camille; Rieu, Dominique; Pant, Vik
A40: RGCKL82B | B40: bookSection | C40: 2016 | D40: Aarab, Zineb; Saidi, Rajaa; Rahmani, Moulay Driss | E40: Context Modeling and Metamodeling: A State of the Art | F40: Proceedings of the Mediterranean Conference on Information & Communication Technologies 2015 | G40: 978-3-319-30296-6 978-3-319-30298-0 | J40: http://link.springer.com/10.1007/978-3-319-30298-0_30 | K40: 2016 | L40: 44887.364 | M40: 44887.364 | N40: 44886.598 | O40: 287-295 | Q40: 381 | S40: Context Modeling and Metamodeling | T40: Springer International Publishing | U40: Cham | W40: DOI.org (Crossref) | X40: Series Title: Lecture Notes in Electrical Engineering DOI: 10.1007/978-3-319-30298-0_30 | Y40: El Oualkadi, Ahmed; Choubani, Fethi; El Moussati, Ali
A41: RI7G54I5 | B41: bookSection | C41: 2019 | D41: Otter, Martin | E41: Multi-domain Modeling and Simulation | F41: Encyclopedia of Systems and Control | G41: 978-1-4471-5102-9 | J41: http://link.springer.com/10.1007/978-1-4471-5102-9_140-2 | K41: 2019 | L41: 44887.364 | M41: 44887.364 | N41: 44886.598 | O41: 1-13 | T41: Springer London | U41: London | V41: en | W41: DOI.org (Crossref) | X41: DOI: 10.1007/978-1-4471-5102-9_140-2 | Y41: Baillieul, John; Samad, Tariq
A42: CUBADJE8 | B42: bookSection | C42: 2017 | D42: Mainland, Geoffrey | E42: A Domain-Specific Language for Software-Defined Radio | F42: Practical Aspects of Declarative Languages | G42: 978-3-319-51675-2 978-3-319-51676-9 | J42: http://link.springer.com/10.1007/978-3-319-51676-9_12 | K42: 2017 | L42: 44887.364 | M42: 44887.364 | N42: 44886.598 | O42: 173-188 | Q42: 10137 | T42: Springer International Publishing | U42: Cham | W42: DOI.org (Crossref) | X42: Series Title: Lecture Notes in Computer Science DOI: 10.1007/978-3-319-51676-9_12 | Y42: Lierler, Yuliya; Taha, Walid
A43: MF8SBFK8 | B43: bookSection | C43: 2009 | D43: Kopernik, Magdalena; Stanisławczyk, Andrzej; Kusiak, Jan; Pietrzyk, Maciej | E43: Identification of Material Models of Nanocoatings System Using the Metamodeling Approach | F43: System Modeling and Optimization | G43: 978-3-642-04801-2 978-3-642-04802-9 | J43: http://link.springer.com/10.1007/978-3-642-04802-9_18 | K43: 2009 | L43: 44887.364 | M43: 44887.364 | N43: 44886.598 | O43: 319-330 | Q43: 312 | T43: Springer Berlin Heidelberg | U43: Berlin, Heidelberg | W43: DOI.org (Crossref) | X43: Series Title: IFIP Advances in Information and Communication Technology DOI: 10.1007/978-3-642-04802-9_18 | Y43: Korytowski, Adam; Malanowski, Kazimierz; Mitkowski, Wojciech; Szymkat, Maciej
A44: 84P2N68F | B44: bookSection | C44: 2017 | D44: Ciccozzi, Federico; Spalazzese, Romina | E44: MDE4IoT: Supporting the Internet of Things with Model-Driven Engineering | F44: Intelligent Distributed Computing X | G44: 978-3-319-48828-8 978-3-319-48829-5 | J44: http://link.springer.com/10.1007/978-3-319-48829-5_7 | K44: 2017 | L44: 44887.364 | M44: 44887.364 | N44: 44886.598 | O44: 67-76 | Q44: 678 | S44: MDE4IoT | T44: Springer International Publishing | U44: Cham | W44: DOI.org (Crossref) | X44: Series Title: Studies in Computational Intelligence DOI: 10.1007/978-3-319-48829-5_7 | Y44: Badica, Costin; El Fallah Seghrouchni, Amal; Beynier, Aurélie; Camacho, David; Herpson, Cédric; Hindriks, Koen; Novais, Paulo
A45: 3U96Q73U | B45: bookSection | C45: 2012 | D45: Mayrhofer, Dieter; Huemer, Christian | E45: Extending the REA-DSL by the Planning Layer of the REA Ontology | F45: Advanced Information Systems Engineering Workshops | G45: 978-3-642-31068-3 978-3-642-31069-0 | J45: http://link.springer.com/10.1007/978-3-642-31069-0_45 | K45: 2012 | L45: 44887.364 | M45: 44887.364 | N45: 44886.598 | O45: 543-554 | Q45: 112 | T45: Springer Berlin Heidelberg | U45: Berlin, Heidelberg | V45: en | W45: DOI.org (Crossref) | X45: Series Title: Lecture Notes in Business Information Processing DOI: 10.1007/978-3-642-31069-0_45 | Y45: Bajec, Marko; Eder, Johann | Z45: van der Aalst, Wil; Mylopoulos, John; Rosemann, Michael; Shaw, Michael J.; Szyperski, Clemens
A46: 2VURJDJL | B46: journalArticle | C46: 2022 | D46: Alhijazi, Mohamad; Safaei, Babak; Zeeshan, Qasim; Asmael, Mohammed; Harb, Mohammad; Qin, Zhaoye | E46: An Experimental and Metamodeling Approach to Tensile Properties of Natural Fibers Composites | F46: Journal of Polymers and the Environment | H46: 1566-2543, 1572-8919 | I46: 10.1007/s10924-022-02514-1 | J46: https://link.springer.com/10.1007/s10924-022-02514-1 | K46: 2022-10 | L46: 44887.364 | M46: 44887.364 | N46: 44886.598 | O46: 4377-4393 | P46: 10 | Q46: 30 | R46: J Polym Environ | V46: en | W46: DOI.org (Crossref)
A47: 57DQYNKV | B47: bookSection | C47: 2022 | D47: Heisler, Eric; Deshmukh, Aadesh; Sundar, Hari | E47: Finch: Domain Specific Language and Code Generation for Finite Element and Finite Volume in Julia | F47: Computational Science – ICCS 2022 | G47: 978-3-031-08750-9 978-3-031-08751-6 | J47: https://link.springer.com/10.1007/978-3-031-08751-6_9 | K47: 2022 | L47: 44887.364 | M47: 44887.364 | N47: 44886.598 | O47: 118-132 | Q47: 13350 | S47: Finch | T47: Springer International Publishing | U47: Cham | V47: en | W47: DOI.org (Crossref) | X47: Series Title: Lecture Notes in Computer Science DOI: 10.1007/978-3-031-08751-6_9 | Y47: Groen, Derek; de Mulatier, Clélia; Paszynski, Maciej; Krzhizhanovskaya, Valeria V.; Dongarra, Jack J.; Sloot, Peter M. A.
A48: A4KRXB2L | B48: journalArticle | C48: 2018 | D48: Rabiser, Rick; Thanhofer-Pilisch, Jürgen; Vierhauser, Michael; Grünbacher, Paul; Egyed, Alexander | E48: Developing and evolving a DSL-based approach for runtime monitoring of systems of systems | F48: Automated Software Engineering | H48: 0928-8910, 1573-7535 | I48: 10.1007/s10515-018-0241-x | J48: http://link.springer.com/10.1007/s10515-018-0241-x | K48: 2018-12 | L48: 44887.364 | M48: 44887.364 | N48: 44886.598 | O48: 875-915 | P48: 4 | Q48: 25 | R48: Autom Softw Eng | V48: en | W48: DOI.org (Crossref)
A49: 9PK9YLN9 | B49: bookSection | C49: 2012 | D49: Parfieniuk, Marek; Kazberuk, Marcin; Kowalewski, Kamil | E49: A Compiler for a Domain-Specific Language for Rapid Implementation of DSP Transforms and Filter Banks | F49: Towards Modern Collaborative Knowledge Sharing Systems | G49: 978-3-642-27445-9 978-3-642-27446-6 | J49: http://link.springer.com/10.1007/978-3-642-27446-6_8 | K49: 2012 | L49: 44887.364 | M49: 44887.364 | N49: 44886.598 | O49: 83-100 | Q49: 401 | T49: Springer Berlin Heidelberg | U49: Berlin, Heidelberg | W49: DOI.org (Crossref) | X49: Series Title: Studies in Computational Intelligence DOI: 10.1007/978-3-642-27446-6_8 | Y49: Lipiński, Piotr; Świrski, Konrad
A50: 5K7TPZXT | B50: bookSection | C50: 2020 | D50: Yar, Asfand; Idani, Akram; Collart-Dutilleul, Simon | E50: Merging Railway Standard Notations in a Formal DSL-Based Framework | F50: Software Architecture | G50: 978-3-030-59154-0 978-3-030-59155-7 | J50: http://link.springer.com/10.1007/978-3-030-59155-7_30 | K50: 2020 | L50: 44887.364 | M50: 44887.364 | N50: 44886.598 | O50: 411-419 | Q50: 1269 | T50: Springer International Publishing | U50: Cham | V50: en | W50: DOI.org (Crossref) | X50: Series Title: Communications in Computer and Information Science DOI: 10.1007/978-3-030-59155-7_30 | Y50: Muccini, Henry; Avgeriou, Paris; Buhnova, Barbora; Camara, Javier; Caporuscio, Mauro; Franzago, Mirco; Koziolek, Anne; Scandurra, Patrizia; Trubiani, Catia; Weyns, Danny; Zdun, Uwe
A51: YDIS59LC | B51: journalArticle | C51: 2022 | D51: Almonte, Lissette; Guerra, Esther; Cantador, Iván; de Lara, Juan | E51: Recommender systems in model-driven engineering: A systematic mapping review | F51: Software and Systems Modeling | H51: 1619-1366, 1619-1374 | I51: 10.1007/s10270-021-00905-x | J51: https://link.springer.com/10.1007/s10270-021-00905-x | K51: 2022-02 | L51: 44887.364 | M51: 44887.364 | N51: 44886.598 | O51: 249-280 | P51: 1 | Q51: 21 | R51: Softw Syst Model | S51: Recommender systems in model-driven engineering | V51: en | W51: DOI.org (Crossref)
A52: EWGAAE8Y | B52: bookSection | C52: 2011 | D52: He, Ruan; Lacoste, Marc; Pulou, Jacques; Leneutre, Jean | E52: A DSL for Specifying Autonomic Security Management Strategies | F52: Data Privacy Management and Autonomous Spontaneous Security | G52: 978-3-642-19347-7 978-3-642-19348-4 | J52: http://link.springer.com/10.1007/978-3-642-19348-4_16 | K52: 2011 | L52: 44887.364 | M52: 44887.364 | N52: 44886.598 | O52: 216-230 | Q52: 6514 | T52: Springer Berlin Heidelberg | U52: Berlin, Heidelberg | V52: en | W52: DOI.org (Crossref) | X52: Series Title: Lecture Notes in Computer Science DOI: 10.1007/978-3-642-19348-4_16 | Y52: Garcia-Alfaro, Joaquin; Navarro-Arribas, Guillermo; Cavalli, Ana; Leneutre, Jean
A53: GCT37YMD | B53: bookSection | C53: 2008 | D53: Rougemaille, Sylvain; Migeon, Frédéric; Maurel, Christine; Gleizes, Marie-Pierre | E53: Model Driven Engineering for Designing Adaptive Multi-Agents Systems | F53: Engineering Societies in the Agents World VIII | G53: 978-3-540-87653-3 978-3-540-87654-0 | J53: http://link.springer.com/10.1007/978-3-540-87654-0_18 | K53: 2008 | L53: 44887.364 | M53: 44887.364 | N53: 44886.598 | O53: 318-332 | Q53: 4995 | T53: Springer Berlin Heidelberg | U53: Berlin, Heidelberg | V53: en | W53: DOI.org (Crossref) | X53: ISSN: 0302-9743, 1611-3349 Series Title: Lecture Notes in Computer Science DOI: 10.1007/978-3-540-87654-0_18 | Y53: Artikis, Alexander; O’Hare, Gregory M. P.; Stathis, Kostas; Vouros, George
A54: 3D7ZYWDU | B54: bookSection | C54: 2013 | D54: Noël, Frédéric; Azli, Mohd Azwan | E54: Experimenting New Metaphors for PDM through a Model Driven Engineering Scheme | F54: Product Lifecycle Management for Society | G54: 978-3-642-41500-5 978-3-642-41501-2 | J54: http://link.springer.com/10.1007/978-3-642-41501-2_57 | K54: 2013 | L54: 44887.364 | M54: 44887.364 | N54: 44886.598 | O54: 570-583 | Q54: 409 | T54: Springer Berlin Heidelberg | U54: Berlin, Heidelberg | W54: DOI.org (Crossref) | X54: Series Title: IFIP Advances in Information and Communication Technology DOI: 10.1007/978-3-642-41501-2_57 | Y54: Bernard, Alain; Rivest, Louis; Dutta, Debasish
A55: Y6RXQCCL | B55: book | C55: 2017 | E55: Model-Driven Engineering and Software Development | G55: 978-3-319-66301-2 978-3-319-66302-9 | J55: http://link.springer.com/10.1007/978-3-319-66302-9 | K55: 2017 | L55: 44887.364 | M55: 44887.364 | N55: 44886.598 | Q55: 692 | T55: Springer International Publishing | U55: Cham | W55: DOI.org (Crossref) | X55: DOI: 10.1007/978-3-319-66302-9 | Y55: Hammoudi, Slimane; Pires, Luís Ferreira; Selic, Bran; Desfray, Philippe
A56: IR79P6CT | B56: bookSection | C56: 2018 | D56: Cosenza, Biagio; Popov, Nikita; Juurlink, Ben; Richmond, Paul; Chimeh, Mozhgan Kabiri; Spagnuolo, Carmine; Cordasco, Gennaro; Scarano, Vittorio | E56: OpenABL: A Domain-Specific Language for Parallel and Distributed Agent-Based Simulations | F56: Euro-Par 2018: Parallel Processing | G56: 978-3-319-96982-4 978-3-319-96983-1 | J56: https://link.springer.com/10.1007/978-3-319-96983-1_36 | K56: 2018 | L56: 44887.364 | M56: 44887.364 | N56: 44886.598 | O56: 505-518 | Q56: 11014 | S56: OpenABL | T56: Springer International Publishing | U56: Cham | V56: en | W56: DOI.org (Crossref) | X56: Series Title: Lecture Notes in Computer Science DOI: 10.1007/978-3-319-96983-1_36 | Y56: Aldinucci, Marco; Padovani, Luca; Torquati, Massimo
A57: JWW8CNN3 | B57: book | C57: 2021 | E57: Model-Driven Engineering and Software Development: 8th International Conference, MODELSWARD 2020, Valletta, Malta, February 25–27, 2020, Revised Selected Papers | G57: 978-3-030-67444-1 978-3-030-67445-8 | J57: http://link.springer.com/10.1007/978-3-030-67445-8 | K57: 2021 | L57: 44887.364 | M57: 44887.364 | N57: 44886.598 | Q57: 1361 | S57: Model-Driven Engineering and Software Development | T57: Springer International Publishing | U57: Cham | V57: en | W57: DOI.org (Crossref) | X57: DOI: 10.1007/978-3-030-67445-8 | Y57: Hammoudi, Slimane; Pires, Luís Ferreira; Selić, Bran
A58: G6RASARN | B58: bookSection | C58: 2015 | D58: Glöckner, Michael; Mutke, Stefan; Augenstein, Christoph; Ludwig, André | E58: Planning of Composite Logistics Services: Model-Driven Engineering and Evaluation | F58: Enterprise Information Systems | G58: 978-3-319-29132-1 978-3-319-29133-8 | J58: http://link.springer.com/10.1007/978-3-319-29133-8_18 | K58: 2015 | L58: 44887.364 | M58: 44887.364 | N58: 44886.598 | O58: 364-384 | Q58: 241 | S58: Planning of Composite Logistics Services | T58: Springer International Publishing | U58: Cham | W58: DOI.org (Crossref) | X58: Series Title: Lecture Notes in Business Information Processing DOI: 10.1007/978-3-319-29133-8_18 | Y58: Hammoudi, Slimane; Maciaszek, Leszek; Teniente, Ernest; Camp, Olivier; Cordeiro, José
A59: BXYGNWMG | B59: journalArticle | C59: 2018 | D59: Butakov, Nikolay; Petrov, Maxim; Mukhina, Ksenia; Nasonov, Denis; Kovalchuk, Sergey | E59: Unified domain-specific language for collecting and processing data of social media | F59: Journal of Intelligent Information Systems | H59: 0925-9902, 1573-7675 | I59: 10.1007/s10844-018-0508-5 | J59: http://link.springer.com/10.1007/s10844-018-0508-5 | K59: 2018-10 | L59: 44887.364 | M59: 44887.364 | N59: 44886.598 | O59: 389-414 | P59: 2 | Q59: 51 | R59: J Intell Inf Syst | V59: en | W59: DOI.org (Crossref)
A60: UMAM4JR5 | B60: bookSection | C60: 2019 | D60: Nguyen Phuoc Bao, Hoang; Clavel, Manuel | E60: OCL2PSQL: An OCL-to-SQL Code-Generator for Model-Driven Engineering | F60: Future Data and Security Engineering | G60: 978-3-030-35652-1 978-3-030-35653-8 | J60: http://link.springer.com/10.1007/978-3-030-35653-8_13 | K60: 2019 | L60: 44887.364 | M60: 44887.364 | N60: 44886.598 | O60: 185-203 | Q60: 11814 | S60: OCL2PSQL | T60: Springer International Publishing | U60: Cham | V60: en | W60: DOI.org (Crossref) | X60: Series Title: Lecture Notes in Computer Science DOI: 10.1007/978-3-030-35653-8_13 | Y60: Dang, Tran Khanh; Küng, Josef; Takizawa, Makoto; Bui, Son Ha
A61: BKZDLDLN | B61: bookSection | C61: 2013 | D61: Vacchi, Edoardo; Cazzola, Walter; Pillay, Suresh; Combemale, Benoît | E61: Variability Support in Domain-Specific Language Development | F61: Software Language Engineering | G61: 978-3-319-02653-4 978-3-319-02654-1 | J61: http://link.springer.com/10.1007/978-3-319-02654-1_5 | K61: 2013 | L61: 44887.364 | M61: 44887.364 | N61: 44886.598 | O61: 76-95 | Q61: 8225 | T61: Springer International Publishing | U61: Cham | W61: DOI.org (Crossref) | X61: Series Title: Lecture Notes in Computer Science DOI: 10.1007/978-3-319-02654-1_5 | Y61: Erwig, Martin; Paige, Richard F.; Van Wyk, Eric | Z61: Hutchison, David; Kanade, Takeo; Kittler, Josef; Kleinberg, Jon M.; Mattern, Friedemann; Mitchell, John C.; Naor, Moni; Nierstrasz, Oscar; Pandu Rangan, C.; Steffen, Bernhard; Sudan, Madhu; Terzopoulos, Demetri; Tygar, Doug; Vardi, Moshe Y.; Weikum, Gerhard
A62: PIR8G9GD | B62: journalArticle | C62: 2022 | D62: Süß, Jörn Guy; Swift, Samantha; Escott, Eban | E62: Using DevOps toolchains in Agile model-driven engineering | F62: Software and Systems Modeling | H62: 1619-1366, 1619-1374 | I62: 10.1007/s10270-022-01003-2 | J62: https://link.springer.com/10.1007/s10270-022-01003-2 | K62: 2022-08 | L62: 44887.364 | M62: 44887.364 | N62: 44886.598 | O62: 1495-1510 | P62: 4 | Q62: 21 | R62: Softw Syst Model | V62: en | W62: DOI.org (Crossref)
A63: Z7F6CH85 | B63: bookSection | C63: 2007 | D63: Pederiva, Inés; Vanderdonckt, Jean; España, Sergio; Panach, Ignacio; Pastor, Oscar | E63: The Beautification Process in Model-Driven Engineering of User Interfaces | F63: Human-Computer Interaction – INTERACT 2007 | G63: 978-3-540-74794-9 978-3-540-74796-3 | J63: http://link.springer.com/10.1007/978-3-540-74796-3_39 | K63: 2007 | L63: 44887.364 | M63: 44887.364 | N63: 44886.598 | O63: 411-425 | Q63: 4662 | T63: Springer Berlin Heidelberg | U63: Berlin, Heidelberg | W63: DOI.org (Crossref) | X63: Series Title: Lecture Notes in Computer Science DOI: 10.1007/978-3-540-74796-3_39 | Y63: Baranauskas, Cécilia; Palanque, Philippe; Abascal, Julio; Barbosa, Simone Diniz Junqueira
A64: 5LYRM3CK | B64: bookSection | C64: 2011 | D64: Kalgin, Konstantin | E64: Domain Specific Language and Translator for Cellular Automata Models of Physico-Chemical Processes | F64: Parallel Computing Technologies | G64: 978-3-642-23177-3 978-3-642-23178-0 | J64: http://link.springer.com/10.1007/978-3-642-23178-0_14 | K64: 2011 | L64: 44887.364 | M64: 44887.364 | N64: 44886.598 | O64: 166-174 | Q64: 6873 | T64: Springer Berlin Heidelberg | U64: Berlin, Heidelberg | W64: DOI.org (Crossref) | X64: Series Title: Lecture Notes in Computer Science DOI: 10.1007/978-3-642-23178-0_14 | Y64: Malyshkin, Victor
A65: J2Y9SQSU | B65: bookSection | C65: 2021 | D65: Giallorenzo, Saverio; Montesi, Fabrizio; Peressotti, Marco; Rademacher, Florian; Sachweh, Sabine | E65: Jolie and LEMMA: Model-Driven Engineering and Programming Languages Meet on Microservices | F65: Coordination Models and Languages | G65: 978-3-030-78141-5 978-3-030-78142-2 | J65: https://link.springer.com/10.1007/978-3-030-78142-2_17 | K65: 2021 | L65: 44887.364 | M65: 44887.364 | N65: 44886.598 | O65: 276-284 | Q65: 12717 | S65: Jolie and LEMMA | T65: Springer International Publishing | U65: Cham | V65: en | W65: DOI.org (Crossref) | X65: Series Title: Lecture Notes in Computer Science DOI: 10.1007/978-3-030-78142-2_17 | Y65: Damiani, Ferruccio; Dardha, Ornela
A66: 82VPR2ZM | B66: bookSection | C66: 2012 | D66: Sinlapalun, Sakon; Limpiyakorn, Yachai | E66: ARSL: A Domain Specific Language for Aircraft Separation Minima Determination | F66: Computer Applications for Software Engineering, Disaster Recovery, and Business Continuity | G66: 978-3-642-35266-9 978-3-642-35267-6 | J66: http://link.springer.com/10.1007/978-3-642-35267-6_11 | K66: 2012 | L66: 44887.364 | M66: 44887.364 | N66: 44886.598 | O66: 80-87 | Q66: 340 | S66: ARSL | T66: Springer Berlin Heidelberg | U66: Berlin, Heidelberg | W66: DOI.org (Crossref) | X66: Series Title: Communications in Computer and Information Science DOI: 10.1007/978-3-642-35267-6_11 | Y66: Kim, Tai-hoon; Ramos, Carlos; Kim, Haeng-kon; Kiumi, Akingbehin; Mohammed, Sabah; Ślęzak, Dominik
A67: 5U2FBCJM | B67: bookSection | C67: 1999 | D67: Kutter, Philipp W.; Schweizer, Daniel; Thiele, Lothar | E67: Integrating Domain Specific Language Design in the Software Life Cycle | F67: Applied Formal Methods — FM-Trends 98 | G67: 978-3-540-66462-8 978-3-540-48257-4 | J67: http://link.springer.com/10.1007/3-540-48257-1_12 | K67: 1999 | L67: 44887.364 | M67: 44887.364 | N67: 44886.598 | O67: 196-212 | Q67: 1641 | T67: Springer Berlin Heidelberg | U67: Berlin, Heidelberg | W67: DOI.org (Crossref) | X67: Series Title: Lecture Notes in Computer Science DOI: 10.1007/3-540-48257-1_12 | Y67: Hutter, Dieter; Stephan, Werner; Traverso, Paolo; Ullmann, Markus | Z67: Goos, Gerhard; Hartmanis, Juris; van Leeuwen, Jan
A68: E34EMY8U | B68: bookSection | C68: 2016 | D68: Derezińska, Anna; Redosz, Karol | E68: A Model-Driven Engineering Approach to the Evaluation of a Remote Controller of a Movement Assistant System | F68: Man–Machine Interactions 4 | G68: 978-3-319-23436-6 978-3-319-23437-3 | J68: http://link.springer.com/10.1007/978-3-319-23437-3_7 | K68: 2016 | L68: 44887.364 | M68: 44887.364 | N68: 44886.598 | O68: 93-102 | Q68: 391 | T68: Springer International Publishing | U68: Cham | W68: DOI.org (Crossref) | X68: Series Title: Advances in Intelligent Systems and Computing DOI: 10.1007/978-3-319-23437-3_7 | Y68: Gruca, Aleksandra; Brachman, Agnieszka; Kozielski, Stanisław; Czachórski, Tadeusz
A69: H4ZGD85H | B69: bookSection | C69: 2007 | D69: Mathaikutty, Deepak A.; Shukla, Sandeep K. | E69: MCF: A Metamodeling-based Visual Component Composition Framework | F69: Advances in Design and Specification Languages for Embedded Systems | G69: 978-1-4020-6147-9 | J69: http://link.springer.com/10.1007/978-1-4020-6149-3_19 | K69: 2007 | L69: 44887.364 | M69: 44887.364 | N69: 44886.598 | O69: 319-337 | S69: MCF | T69: Springer Netherlands | U69: Dordrecht | V69: en | W69: DOI.org (Crossref) | X69: DOI: 10.1007/978-1-4020-6149-3_19 | Y69: Huss, Sorin A.
A70: WNHJH85X | B70: bookSection | C70: 2019 | D70: Laforcade, Pierre; Laghouaouta, Youness | E70: Generation of Adapted Learning Game Scenarios: A Model-Driven Engineering Approach | F70: Computer Supported Education | G70: 978-3-030-21150-9 978-3-030-21151-6 | J70: http://link.springer.com/10.1007/978-3-030-21151-6_6 | K70: 2019 | L70: 44887.364 | M70: 44887.364 | N70: 44886.598 | O70: 95-116 | Q70: 1022 | S70: Generation of Adapted Learning Game Scenarios | T70: Springer International Publishing | U70: Cham | V70: en | W70: DOI.org (Crossref) | X70: Series Title: Communications in Computer and Information Science DOI: 10.1007/978-3-030-21151-6_6 | Y70: McLaren, Bruce M.; Reilly, Rob; Zvacek, Susan; Uhomoibhi, James
A71: NLVKKUHV | B71: bookSection | C71: 2008 | D71: Osis, Janis; Asnina, Erika; Grave, Andrejs | E71: Formal Problem Domain Modeling within MDA | F71: Software and Data Technologies | G71: 978-3-540-88654-9 978-3-540-88655-6 | J71: http://link.springer.com/10.1007/978-3-540-88655-6_29 | K71: 2008 | L71: 44887.364 | M71: 44887.364 | N71: 44886.598 | O71: 387-398 | Q71: 22 | T71: Springer Berlin Heidelberg | U71: Berlin, Heidelberg | W71: DOI.org (Crossref) | X71: Series Title: Communications in Computer and Information Science DOI: 10.1007/978-3-540-88655-6_29 | Y71: Filipe, Joaquim; Shishkov, Boris; Helfert, Markus; Maciaszek, Leszek A.
A72: J8Z2T3WP | B72: bookSection | C72: 2016 | D72: Bihlmaier, Andreas; Schreiter, Luzie; Raczkowsky, Jörg; Wörn, Heinz | E72: Hierarchical Task Networks as Domain-Specific Language for Planning Surgical Interventions | F72: Intelligent Autonomous Systems 13 | G72: 978-3-319-08337-7 978-3-319-08338-4 | J72: http://link.springer.com/10.1007/978-3-319-08338-4_79 | K72: 2016 | L72: 44887.364 | M72: 44887.364 | N72: 44886.598 | O72: 1095-1105 | Q72: 302 | T72: Springer International Publishing | U72: Cham | W72: DOI.org (Crossref) | X72: Series Title: Advances in Intelligent Systems and Computing DOI: 10.1007/978-3-319-08338-4_79 | Y72: Menegatti, Emanuele; Michael, Nathan; Berns, Karsten; Yamaguchi, Hiroaki
A73: HJW3YD93 | B73: bookSection | C73: 2017 | D73: Gamboa, Miguel Andrés; Syriani, Eugene | E73: Using Workflows to Automate Activities in MDE Tools | F73: Model-Driven Engineering and Software Development | G73: 978-3-319-66301-2 978-3-319-66302-9 | J73: http://link.springer.com/10.1007/978-3-319-66302-9_2 | K73: 2017 | L73: 44887.364 | M73: 44887.364 | N73: 44886.598 | O73: 25-45 | Q73: 692 | T73: Springer International Publishing | U73: Cham | W73: DOI.org (Crossref) | X73: Series Title: Communications in Computer and Information Science DOI: 10.1007/978-3-319-66302-9_2 | Y73: Hammoudi, Slimane; Pires, Luís Ferreira; Selic, Bran; Desfray, Philippe
A74: 9V35S882 | B74: bookSection | C74: 2015 | D74: Oliveira, Bruno; Belo, Orlando | E74: A Domain-Specific Language for ETL Patterns Specification in Data Warehousing Systems | F74: Progress in Artificial Intelligence | G74: 978-3-319-23484-7 978-3-319-23485-4 | J74: http://link.springer.com/10.1007/978-3-319-23485-4_60 | K74: 2015 | L74: 44887.364 | M74: 44887.364 | N74: 44886.598 | O74: 597-602 | Q74: 9273 | T74: Springer International Publishing | U74: Cham | W74: DOI.org (Crossref) | X74: Series Title: Lecture Notes in Computer Science DOI: 10.1007/978-3-319-23485-4_60 | Y74: Pereira, Francisco; Machado, Penousal; Costa, Ernesto; Cardoso, Amílcar
A75: JYA8X7S2 | B75: bookSection | C75: 2013 | D75: Havelund, Klaus | E75: A Scala DSL for Rete-Based Runtime Verification | F75: Runtime Verification | G75: 978-3-642-40786-4 978-3-642-40787-1 | J75: http://link.springer.com/10.1007/978-3-642-40787-1_19 | K75: 2013 | L75: 44887.364 | M75: 44887.364 | N75: 44886.598 | O75: 322-327 | Q75: 8174 | T75: Springer Berlin Heidelberg | U75: Berlin, Heidelberg | V75: en | W75: DOI.org (Crossref) | X75: Series Title: Lecture Notes in Computer Science DOI: 10.1007/978-3-642-40787-1_19 | Y75: Legay, Axel; Bensalem, Saddek | Z75: Hutchison, David; Kanade, Takeo; Kittler, Josef; Kleinberg, Jon M.; Mattern, Friedemann; Mitchell, John C.; Naor, Moni; Nierstrasz, Oscar; Pandu Rangan, C.; Steffen, Bernhard; Sudan, Madhu; Terzopoulos, Demetri; Tygar, Doug; Vardi, Moshe Y.; Weikum, Gerhard
A76: QZYCCHF3 | B76: bookSection | C76: 2020 | D76: Arronategui, Unai; Bañares, José Ángel; Colom, José Manuel | E76: A MDE Approach for Modelling and Distributed Simulation of Health Systems | F76: Economics of Grids, Clouds, Systems, and Services | G76: 978-3-030-63057-7 978-3-030-63058-4 | J76: https://link.springer.com/10.1007/978-3-030-63058-4_9 | K76: 2020 | L76: 44887.364 | M76: 44887.364 | N76: 44886.598 | O76: 89-103 | Q76: 12441 | T76: Springer International Publishing | U76: Cham | V76: en | W76: DOI.org (Crossref) | X76: Series Title: Lecture Notes in Computer Science DOI: 10.1007/978-3-030-63058-4_9 | Y76: Djemame, Karim; Altmann, Jörn; Bañares, José Ángel; Agmon Ben-Yehuda, Orna; Stankovski, Vlado; Tuffin, Bruno
A77: QSF2YMNB | B77: bookSection | C77: 2013 | D77: Sabbadini, Letizia; Michelazzo, Letizia | E77: Metodologia di intervento nelle diverse tipologie di DSL | F77: Disturbi specifici del linguaggio, disprassie e funzioni esecutive | G77: 978-88-470-5348-9 978-88-470-5349-6 | J77: http://link.springer.com/10.1007/978-88-470-5349-6_9 | K77: 2013 | L77: 44887.364 | M77: 44887.364 | N77: 44886.598 | O77: 135-142 | T77: Springer Milan | U77: Milano | V77: it | W77: DOI.org (Crossref) | X77: DOI: 10.1007/978-88-470-5349-6_9
A78: 5ZYLL726 | B78: bookSection | C78: 2018 | D78: Morgan, Rebecca; Grossmann, Georg; Schrefl, Michael; Stumptner, Markus; Payne, Timothy | E78: VizDSL: A Visual DSL for Interactive Information Visualization | F78: Advanced Information Systems Engineering | G78: 978-3-319-91562-3 978-3-319-91563-0 | J78: http://link.springer.com/10.1007/978-3-319-91563-0_27 | K78: 2018 | L78: 44887.364 | M78: 44887.364 | N78: 44886.598 | O78: 440-455 | Q78: 10816 | S78: VizDSL | T78: Springer International Publishing | U78: Cham | W78: DOI.org (Crossref) | X78: Series Title: Lecture Notes in Computer Science DOI: 10.1007/978-3-319-91563-0_27 | Y78: Krogstie, John; Reijers, Hajo A.
A79: 3Z2AXK9Q | B79: journalArticle | C79: 2017 | D79: Zolotas, Christoforos; Diamantopoulos, Themistoklis; Chatzidimitriou, Kyriakos C.; Symeonidis, Andreas L. | E79: From requirements to source code: a Model-Driven Engineering approach for RESTful web services | F79: Automated Software Engineering | H79: 0928-8910, 1573-7535 | I79: 10.1007/s10515-016-0206-x | J79: http://link.springer.com/10.1007/s10515-016-0206-x | K79: 2017-12 | L79: 44887.364 | M79: 44887.364 | N79: 44886.598 | O79: 791-838 | P79: 4 | Q79: 24 | R79: Autom Softw Eng | S79: From requirements to source code | V79: en | W79: DOI.org (Crossref)
A80: ZIBTRQ9J | B80: bookSection | C80: 2005 | E80: Componenti disprattiche nei DSL | F80: La disprassia in età evolutiva: criteri di valutazione ed intervento | G80: 978-88-470-0328-6 | J80: http://link.springer.com/10.1007/88-470-0398-9_7 | K80: 2005 | L80: 44887.364 | M80: 44887.364 | N80: 44886.598 | O80: 109-124 | T80: Springer-Verlag | U80: Milan | V80: it | W80: DOI.org (Crossref) | X80: DOI: 10.1007/88-470-0398-9_7
A81: I86F8EVY | B81: bookSection | C81: 2022 | D81: Evans, Riley; Frohlich, Samantha; Wang, Meng | E81: $$\textsf {CircuitFlow}$$: A Domain Specific Language for Dataflow Programming | F81: Practical Aspects of Declarative Languages | G81: 978-3-030-94478-0 978-3-030-94479-7 | J81: https://link.springer.com/10.1007/978-3-030-94479-7_6 | K81: 2022 | L81: 44887.364 | M81: 44887.364 | N81: 44886.598 | O81: 79-98 | Q81: 13165 | S81: $$\textsf {CircuitFlow}$$ | T81: Springer International Publishing | U81: Cham | V81: en | W81: DOI.org (Crossref) | X81: Series Title: Lecture Notes in Computer Science DOI: 10.1007/978-3-030-94479-7_6 | Y81: Cheney, James; Perri, Simona
A82: BWZQVHL4 | B82: journalArticle | C82: 2009 | D82: Truşcan, Dragoş; Lundkvist, Torbjörn; Alanen, Marcus; Sandström, Kim; Porres, Ivan; Lilius, Johan | E82: MDE for SoC design | F82: Innovations in Systems and Software Engineering | H82: 1614-5046, 1614-5054 | I82: 10.1007/s11334-009-0077-4 | J82: http://link.springer.com/10.1007/s11334-009-0077-4 | K82: 2009-03 | L82: 44887.364 | M82: 44887.364 | N82: 44886.598 | O82: 49-64 | P82: 1 | Q82: 5 | R82: Innovations Syst Softw Eng | V82: en | W82: DOI.org (Crossref)
A83: 4UFB8UL6 | B83: bookSection | C83: 2011 | D83: Wuille, Pieter; Schrijvers, Tom; Samulowitz, Horst; Tack, Guido; Stuckey, Peter | E83: Memoizing a Monadic Mixin DSL | F83: Functional and Constraint Logic Programming | G83: 978-3-642-22530-7 978-3-642-22531-4 | J83: http://link.springer.com/10.1007/978-3-642-22531-4_5 | K83: 2011 | L83: 44887.364 | M83: 44887.364 | N83: 44886.598 | O83: 68-85 | Q83: 6816 | T83: Springer Berlin Heidelberg | U83: Berlin, Heidelberg | V83: en | W83: DOI.org (Crossref) | X83: Series Title: Lecture Notes in Computer Science DOI: 10.1007/978-3-642-22531-4_5 | Y83: Kuchen, Herbert
A84: 5MTID9WL | B84: bookSection | C84: 2021 | D84: Liu, Ya; Xue, Jinyun; Zhang, Zhiheng; Liu, Yang; Hu, Hongwen | E84: Research on the Model Transformation Method and Application of Formal Model Driven Engineering (FMDE) | F84: Theoretical Computer Science | G84: 9789811674426 9789811674433 | J84: https://link.springer.com/10.1007/978-981-16-7443-3_14 | K84: 2021 | L84: 44887.364 | M84: 44887.364 | N84: 44886.598 | O84: 234-254 | Q84: 1494 | T84: Springer Singapore | U84: Singapore | V84: en | W84: DOI.org (Crossref) | X84: Series Title: Communications in Computer and Information Science DOI: 10.1007/978-981-16-7443-3_14 | Y84: Cai, Zhiping; Li, Jian; Zhang, Jialin
A85: 7WBIM5QL | B85: bookSection | C85: 2012 | D85: Arnold, Bob; Shadnam, Mohammad Reza | E85: Analysis of Industrial Challenges and Capabilities in Computer Science and Software Development Sector: Model Driven Engineering | F85: Recent Advances in Computer Science and Information Engineering | G85: 978-3-642-25777-3 978-3-642-25778-0 | J85: http://link.springer.com/10.1007/978-3-642-25778-0_69 | K85: 2012 | L85: 44887.364 | M85: 44887.364 | N85: 44886.598 | O85: 499-505 | Q85: 129 | S85: Analysis of Industrial Challenges and Capabilities in Computer Science and Software Development Sector | T85: Springer Berlin Heidelberg | U85: Berlin, Heidelberg | W85: DOI.org (Crossref) | X85: Series Title: Lecture Notes in Electrical Engineering DOI: 10.1007/978-3-642-25778-0_69 | Y85: Qian, Zhihong; Cao, Lei; Su, Weilian; Wang, Tingkai; Yang, Huamin
A86: 2XX86U5V | B86: journalArticle | C86: 2014 | D86: Bačíková, Michaela; Porubän, Jaroslav | E86: DSL-driven generation of Graphical User Interfaces | F86: Open Computer Science | H86: 2299-1093 | I86: 10.2478/s13537-014-0210-9 | J86: https://www.degruyter.com/document/doi/10.2478/s13537-014-0210-9/html | K86: 2014-01-01 | L86: 44887.364 | M86: 44887.364 | N86: 44886.598 | P86: 4 | Q86: 4 | W86: DOI.org (Crossref)
A87: JTMM5PYW | B87: journalArticle | C87: 2020 | D87: Emoto, Kento; Sadahira, Fumihisa | E87: A DSL for graph parallel programming with vertex subsets | F87: The Journal of Supercomputing | H87: 0920-8542, 1573-0484 | I87: 10.1007/s11227-019-02821-w | J87: http://link.springer.com/10.1007/s11227-019-02821-w | K87: 2020-07 | L87: 44887.364 | M87: 44887.364 | N87: 44886.598 | O87: 4998-5015 | P87: 7 | Q87: 76 | R87: J Supercomput | V87: en | W87: DOI.org (Crossref)
A88: L586B3MF | B88: bookSection | C88: 2013 | D88: Sabbadini, Letizia | E88: Valutazione e terapia di casi clinici nelle diverse tipologie dei DSL | F88: Disturbi specifici del linguaggio, disprassie e funzioni esecutive | G88: 978-88-470-5348-9 978-88-470-5349-6 | J88: http://link.springer.com/10.1007/978-88-470-5349-6_13 | K88: 2013 | L88: 44887.364 | M88: 44887.364 | N88: 44886.598 | O88: 169-194 | T88: Springer Milan | U88: Milano | V88: it | W88: DOI.org (Crossref) | X88: DOI: 10.1007/978-88-470-5349-6_13
A89: FR38P6L6 | B89: bookSection | C89: 2010 | D89: Menet, Ludovic; Lamolle, Myiam; Le Dc, Chan | E89: Incremental Validation of Models in a MDE Approach Applied to the Modeling of Complex Data Structures | F89: On the Move to Meaningful Internet Systems: OTM 2010 Workshops | G89: 978-3-642-16960-1 978-3-642-16961-8 | J89: http://link.springer.com/10.1007/978-3-642-16961-8_28 | K89: 2010 | L89: 44887.364 | M89: 44887.364 | N89: 44886.598 | O89: 120-129 | Q89: 6428 | T89: Springer Berlin Heidelberg | U89: Berlin, Heidelberg | W89: DOI.org (Crossref) | X89: Series Title: Lecture Notes in Computer Science DOI: 10.1007/978-3-642-16961-8_28 | Y89: Meersman, Robert; Dillon, Tharam; Herrero, Pilar
A90: R4TL5IYW | B90: bookSection | C90: 2017 | D90: Golasowski, Martin; Bispo, João; Martinovič, Jan; Slaninová, Kateřina; Cardoso, João M. P. | E90: Expressing and Applying C++ Code Transformations for the HDF5 API Through a DSL | F90: Computer Information Systems and Industrial Management | G90: 978-3-319-59104-9 978-3-319-59105-6 | J90: https://link.springer.com/10.1007/978-3-319-59105-6_26 | K90: 2017 | L90: 44887.364 | M90: 44887.364 | N90: 44886.598 | O90: 303-314 | Q90: 10244 | T90: Springer International Publishing | U90: Cham | V90: en | W90: DOI.org (Crossref) | X90: Series Title: Lecture Notes in Computer Science DOI: 10.1007/978-3-319-59105-6_26 | Y90: Saeed, Khalid; Homenda, Władysław; Chaki, Rituparna
A91: PW98CRPE | B91: book | C91: 2009 | D91: Deved¿ic, Vladan; Djuric, Dragan; Ga¿evic, Dragan | E91: Model Driven Engineering and Ontology Development | G91: 978-3-642-00281-6 978-3-642-00282-3 | J91: http://link.springer.com/10.1007/978-3-642-00282-3 | K91: 2009 | L91: 44887.364 | M91: 44887.364 | N91: 44886.598 | T91: Springer Berlin Heidelberg | U91: Berlin, Heidelberg | V91: en | W91: DOI.org (Crossref) | X91: DOI: 10.1007/978-3-642-00282-3
A92: LZV4GXMU | B92: journalArticle | C92: 2007 | D92: Forouzan, Amir R.; Garth, Lee M. | E92: Computationally Efficient Partial Crosstalk Cancellation in Fast Time-Varying DSL Crosstalk Environments | F92: EURASIP Journal on Advances in Signal Processing | H92: 1687-6180 | I92: 10.1155/2007/72041 | J92: https://asp-eurasipjournals.springeropen.com/articles/10.1155/2007/72041 | K92: 2007-12 | L92: 44887.364 | M92: 44887.364 | N92: 44886.598 | O92: 072041 | P92: 1 | Q92: 2007 | R92: EURASIP J. Adv. Signal Process. | V92: en | W92: DOI.org (Crossref)
A93: V46LYXHE | B93: journalArticle | C93: 2021 | D93: Özkan, M. Akif; Ok, Burak; Qiao, Bo; Teich, Jürgen; Hannig, Frank | E93: HipaccVX: wedding of OpenVX and DSL-based code generation | F93: Journal of Real-Time Image Processing | H93: 1861-8200, 1861-8219 | I93: 10.1007/s11554-020-01015-5 | J93: https://link.springer.com/10.1007/s11554-020-01015-5 | K93: 2021-06 | L93: 44887.364 | M93: 44887.364 | N93: 44886.598 | O93: 765-777 | P93: 3 | Q93: 18 | R93: J Real-Time Image Proc | S93: HipaccVX | V93: en | W93: DOI.org (Crossref)
A94: QGU3TFI3 | B94: bookSection | C94: 1995 | D94: Salon, S. J. | E94: Time Domain Modeling of Induction Machines | F94: Finite Element Analysis of Electrical Machines | G94: 978-1-4613-5996-8 978-1-4615-2349-9 | J94: http://link.springer.com/10.1007/978-1-4615-2349-9_9 | K94: 1995 | L94: 44887.364 | M94: 44887.364 | N94: 44886.598 | O94: 169-196 | T94: Springer US | U94: New York, NY | V94: en | W94: DOI.org (Crossref) | X94: Series Title: Power Electronics and Power Systems DOI: 10.1007/978-1-4615-2349-9_9
A95: 5Q8RNZW5 | B95: bookSection | C95: 2011 | D95: Sonnenberg, Christian; Huemer, Christian; Hofreiter, Birgit; Mayrhofer, Dieter; Braccini, Alessio | E95: The REA-DSL: A Domain Specific Modeling Language for Business Models | F95: Active Flow and Combustion Control 2018 | G95: 978-3-319-98176-5 978-3-319-98177-2 | J95: http://link.springer.com/10.1007/978-3-642-21640-4_20 | K95: 2011 | L95: 44887.364 | M95: 44887.364 | N95: 44886.598 | O95: 252-266 | Q95: 141 | S95: The REA-DSL | T95: Springer International Publishing | U95: Cham | W95: DOI.org (Crossref) | X95: Series Title: Notes on Numerical Fluid Mechanics and Multidisciplinary Design DOI: 10.1007/978-3-642-21640-4_20 | Y95: King, Rudibert
A96: T2CSTDAY | B96: bookSection | C96: 2008 | E96: Credit Risk Analysis with a SVM-based Metamodeling Ensemble Approach | F96: Bio-Inspired Credit Risk Analysis | G96: 978-3-540-77802-8 978-3-540-77803-5 | J96: http://link.springer.com/10.1007/978-3-540-77803-5_9 | K96: 2008 | L96: 44887.364 | M96: 44887.364 | N96: 44886.598 | O96: 157-177 | T96: Springer Berlin Heidelberg | U96: Berlin, Heidelberg | V96: en | W96: DOI.org (Crossref) | X96: DOI: 10.1007/978-3-540-77803-5_9
A97: JJVY7F7H | B97: journalArticle | C97: 2008 | D97: Zhang, Tian; Jouault, Frédéric; Bézivin, Jean; Li, Xuandong | E97: An MDE-based method for bridging different design notations | F97: Innovations in Systems and Software Engineering | H97: 1614-5046, 1614-5054 | I97: 10.1007/s11334-008-0052-5 | J97: http://link.springer.com/10.1007/s11334-008-0052-5 | K97: 2008-10 | L97: 44887.364 | M97: 44887.364 | N97: 44886.598 | O97: 203-213 | P97: 3 | Q97: 4 | R97: Innovations Syst Softw Eng | V97: en | W97: DOI.org (Crossref)
A98: 5PVML2XT | B98: bookSection | C98: 2018 | D98: van den Berg, Freek; Hooman, Jozef; Haverkort, Boudewijn R. | E98: A Domain-Specific Language and Toolchain for Performance Evaluation Based on Measurements | F98: Measurement, Modelling and Evaluation of Computing Systems | G98: 978-3-319-74946-4 978-3-319-74947-1 | J98: http://link.springer.com/10.1007/978-3-319-74947-1_21 | K98: 2018 | L98: 44887.364 | M98: 44887.364 | N98: 44886.598 | O98: 295-301 | Q98: 10740 | T98: Springer International Publishing | U98: Cham | W98: DOI.org (Crossref) | X98: Series Title: Lecture Notes in Computer Science DOI: 10.1007/978-3-319-74947-1_21 | Y98: German, Reinhard; Hielscher, Kai-Steffen; Krieger, Udo R.
A99: KLYD9XW7 | B99: bookSection | C99: 2018 | D99: Sanchez, Daniel; Florez, Hector | E99: Model Driven Engineering Approach to Manage Peripherals in Mobile Devices | F99: Computational Science and Its Applications – ICCSA 2018 | G99: 978-3-319-95170-6 978-3-319-95171-3 | J99: http://link.springer.com/10.1007/978-3-319-95171-3_28 | K99: 2018 | L99: 44887.364 | M99: 44887.364 | N99: 44886.598 | O99: 353-364 | Q99: 10963 | T99: Springer International Publishing | U99: Cham | W99: DOI.org (Crossref) | X99: Series Title: Lecture Notes in Computer Science DOI: 10.1007/978-3-319-95171-3_28 | Y99: Gervasi, Osvaldo; Murgante, Beniamino; Misra, Sanjay; Stankova, Elena; Torre, Carmelo M.; Rocha, Ana Maria A.C.; Taniar, David; Apduhan, Bernady O.; Tarantino, Eufemia; Ryu, Yeonseung
A100: 9YJS3YIA | B100: journalArticle | C100: 2007 | D100: White, Jules; Schmidt, Douglas C.; Gokhale, Aniruddha | E100: Simplifying autonomic enterprise Java Bean applications via model-driven engineering and simulation | F100: Software & Systems Modeling | H100: 1619-1366, 1619-1374 | I100: 10.1007/s10270-007-0057-9 | J100: http://link.springer.com/10.1007/s10270-007-0057-9 | K100: 2007-11-21 | L100: 44887.364 | M100: 44887.364 | N100: 44886.598 | O100: 3-23 | P100: 1 | Q100: 7 | R100: Softw Syst Model | V100: en | W100: DOI.org (Crossref)
...

Sheet 4. Selection Based on Title
A1: Key | B1: Item Type | C1: Publication Year | D1: Author | E1: Title | F1: Publication Title | G1: ISBN | H1: ISSN | I1: DOI | J1: Url | K1: Abstract Note | L1: Date | M1: Date Added | N1: Date Modified | O1: Access Date | P1: Pages | Q1: Num Pages | R1: Issue | S1: Volume | T1: Series | U1: Publisher | V1: Place | W1: Extra
A2: NDD6WRD9 | B2: =VLOOKUP(Tabelle4[[#This Row],[Key]],'3. Unique Results'!A:X,2,FALSE) -> conferencePaper | C2: =VLOOKUP(Tabelle4[[#This Row],[Key]],'3. Unique Results'!A:X,3,FALSE) -> 2022 | D2: =VLOOKUP(Tabelle4[[#This Row],[Key]],'3. Unique Results'!A:X,4,FALSE) -> d'Aloisio, Giordano | E2: =VLOOKUP(Tabelle4[[#This Row],[Key]],'3. Unique Results'!A:X,5,FALSE) -> Quality-Driven Machine Learning-Based Data Science Pipeline Realization: A Software Engineering Approach | F2: =VLOOKUP(Tabelle4[[#This Row],[Key]],'3. Unique Results'!A:X,6,FALSE) -> Proceedings of the ACM/IEEE 44th International Conference on Software Engineering: Companion Proceedings | G2: =VLOOKUP(Tabelle4[[#This Row],[Key]],'3. Unique Results'!A:X,7,FALSE) -> 978-1-4503-9223-5 | H2: =VLOOKUP(Tabelle4[[#This Row],[Key]],'3. Unique Results'!A:X,8,FALSE) | I2: =VLOOKUP(Tabelle4[[#This Row],[Key]],'3. Unique Results'!A:X,9,FALSE) -> 10.1145/3510454.3517067 | J2: =VLOOKUP(Tabelle4[[#This Row],[Key]],'3. Unique Results'!A:X,10,FALSE) -> https://doi.org/10.1145/3510454.3517067 | K2: =VLOOKUP(Tabelle4[[#This Row],[Key]],'3. Unique Results'!A:X,11,FALSE) -> 2022 | L2: =VLOOKUP(Tabelle4[[#This Row],[Key]],'3. Unique Results'!A:X,12,FALSE) -> 44887.364 | M2: =VLOOKUP(Tabelle4[[#This Row],[Key]],'3. Unique Results'!A:X,13,FALSE) -> 44887.412 | N2: =VLOOKUP(Tabelle4[[#This Row],[Key]],'3. Unique Results'!A:X,14,FALSE) -> 0 | O2: =VLOOKUP(Tabelle4[[#This Row],[Key]],'3. Unique Results'!A:X,15,FALSE) -> 291–293 | P2: =VLOOKUP(Tabelle4[[#This Row],[Key]],'3. Unique Results'!A:X,16,FALSE) | Q2: =VLOOKUP(Tabelle4[[#This Row],[Key]],'3. Unique Results'!A:X,17,FALSE) | R2: =VLOOKUP(Tabelle4[[#This Row],[Key]],'3. Unique Results'!A:X,18,FALSE) | S2: =VLOOKUP(Tabelle4[[#This Row],[Key]],'3. Unique Results'!A:X,19,FALSE) | T2: =VLOOKUP(Tabelle4[[#This Row],[Key]],'3. Unique Results'!A:X,20,FALSE) -> Association for Computing Machinery | U2: =VLOOKUP(Tabelle4[[#This Row],[Key]],'3. Unique Results'!A:X,21,FALSE) -> New York, NY, USA | V2: =VLOOKUP(Tabelle4[[#This Row],[Key]],'3. Unique Results'!A:X,22,FALSE) | W2: =VLOOKUP(Tabelle4[[#This Row],[Key]],'3. Unique Results'!A:X,23,FALSE)
A3: HMQVEDXS | B3: =VLOOKUP(Tabelle4[[#This Row],[Key]],'3. Unique Results'!A:X,2,FALSE) -> conferencePaper | C3: =VLOOKUP(Tabelle4[[#This Row],[Key]],'3. Unique Results'!A:X,3,FALSE) -> 2017 | D3: =VLOOKUP(Tabelle4[[#This Row],[Key]],'3. Unique Results'!A:X,4,FALSE) -> Dethlefs, Nina; Hawick, Ken | E3: =VLOOKUP(Tabelle4[[#This Row],[Key]],'3. Unique Results'!A:X,5,FALSE) -> DEFIne: A Fluent Interface DSL for Deep Learning Applications | F3: =VLOOKUP(Tabelle4[[#This Row],[Key]],'3. Unique Results'!A:X,6,FALSE) -> Proceedings of the 2nd International Workshop on Real World Domain Specific Languages | G3: =VLOOKUP(Tabelle4[[#This Row],[Key]],'3. Unique Results'!A:X,7,FALSE) -> 978-1-4503-4845-4 | H3: =VLOOKUP(Tabelle4[[#This Row],[Key]],'3. Unique Results'!A:X,8,FALSE) | I3: =VLOOKUP(Tabelle4[[#This Row],[Key]],'3. Unique Results'!A:X,9,FALSE) -> 10.1145/3039895.3039898 | J3: =VLOOKUP(Tabelle4[[#This Row],[Key]],'3. Unique Results'!A:X,10,FALSE) -> https://doi.org/10.1145/3039895.3039898 | K3: =VLOOKUP(Tabelle4[[#This Row],[Key]],'3. Unique Results'!A:X,11,FALSE) -> 2017 | L3: =VLOOKUP(Tabelle4[[#This Row],[Key]],'3. Unique Results'!A:X,12,FALSE) -> 44887.364 | M3: =VLOOKUP(Tabelle4[[#This Row],[Key]],'3. Unique Results'!A:X,13,FALSE) -> 44887.411 | N3: =VLOOKUP(Tabelle4[[#This Row],[Key]],'3. Unique Results'!A:X,14,FALSE) -> 0 | O3: =VLOOKUP(Tabelle4[[#This Row],[Key]],'3. Unique Results'!A:X,15,FALSE) | P3: =VLOOKUP(Tabelle4[[#This Row],[Key]],'3. Unique Results'!A:X,16,FALSE) | Q3: =VLOOKUP(Tabelle4[[#This Row],[Key]],'3. Unique Results'!A:X,17,FALSE) | R3: =VLOOKUP(Tabelle4[[#This Row],[Key]],'3. Unique Results'!A:X,18,FALSE) | S3: =VLOOKUP(Tabelle4[[#This Row],[Key]],'3. Unique Results'!A:X,19,FALSE) | T3: =VLOOKUP(Tabelle4[[#This Row],[Key]],'3. Unique Results'!A:X,20,FALSE) -> Association for Computing Machinery | U3: =VLOOKUP(Tabelle4[[#This Row],[Key]],'3. Unique Results'!A:X,21,FALSE) -> New York, NY, USA | V3: =VLOOKUP(Tabelle4[[#This Row],[Key]],'3. Unique Results'!A:X,22,FALSE) | W3: =VLOOKUP(Tabelle4[[#This Row],[Key]],'3. Unique Results'!A:X,23,FALSE)
A4: E77DCQEB | B4: =VLOOKUP(Tabelle4[[#This Row],[Key]],'3. Unique Results'!A:X,2,FALSE) -> conferencePaper | C4: =VLOOKUP(Tabelle4[[#This Row],[Key]],'3. Unique Results'!A:X,3,FALSE) -> 2021 | D4: =VLOOKUP(Tabelle4[[#This Row],[Key]],'3. Unique Results'!A:X,4,FALSE) -> Ries, Benoît; Guelfi, Nicolas; Jahic, Benjamin | E4: =VLOOKUP(Tabelle4[[#This Row],[Key]],'3. Unique Results'!A:X,5,FALSE) -> An MDE Method for Improving Deep Learning Dataset Requirements Engineering using Alloy and UML | F4: =VLOOKUP(Tabelle4[[#This Row],[Key]],'3. Unique Results'!A:X,6,FALSE) -> Proceedings of the 9th International Conference on Model-Driven Engineering and Software Development, MODELSWARD 2021, Online Streaming, February 8-10, 2021 | G4: =VLOOKUP(Tabelle4[[#This Row],[Key]],'3. Unique Results'!A:X,7,FALSE) | H4: =VLOOKUP(Tabelle4[[#This Row],[Key]],'3. Unique Results'!A:X,8,FALSE) | I4: =VLOOKUP(Tabelle4[[#This Row],[Key]],'3. Unique Results'!A:X,9,FALSE) -> 10.5220/0010216600410052 | J4: =VLOOKUP(Tabelle4[[#This Row],[Key]],'3. Unique Results'!A:X,10,FALSE) -> https://doi.org/10.5220/0010216600410052 | K4: =VLOOKUP(Tabelle4[[#This Row],[Key]],'3. Unique Results'!A:X,11,FALSE) -> 2021 | L4: =VLOOKUP(Tabelle4[[#This Row],[Key]],'3. Unique Results'!A:X,12,FALSE) -> 44887.364 | M4: =VLOOKUP(Tabelle4[[#This Row],[Key]],'3. Unique Results'!A:X,13,FALSE) -> 44887.364 | N4: =VLOOKUP(Tabelle4[[#This Row],[Key]],'3. Unique Results'!A:X,14,FALSE) -> 0 | O4: =VLOOKUP(Tabelle4[[#This Row],[Key]],'3. Unique Results'!A:X,15,FALSE) -> 41–52 | P4: =VLOOKUP(Tabelle4[[#This Row],[Key]],'3. Unique Results'!A:X,16,FALSE) | Q4: =VLOOKUP(Tabelle4[[#This Row],[Key]],'3. Unique Results'!A:X,17,FALSE) | R4: =VLOOKUP(Tabelle4[[#This Row],[Key]],'3. Unique Results'!A:X,18,FALSE) | S4: =VLOOKUP(Tabelle4[[#This Row],[Key]],'3. Unique Results'!A:X,19,FALSE) | T4: =VLOOKUP(Tabelle4[[#This Row],[Key]],'3. Unique Results'!A:X,20,FALSE) -> SCITEPRESS | U4: =VLOOKUP(Tabelle4[[#This Row],[Key]],'3. Unique Results'!A:X,21,FALSE) | V4: =VLOOKUP(Tabelle4[[#This Row],[Key]],'3. Unique Results'!A:X,22,FALSE) | W4: =VLOOKUP(Tabelle4[[#This Row],[Key]],'3. Unique Results'!A:X,23,FALSE)
A5: 9FSARRET | B5: =VLOOKUP(Tabelle4[[#This Row],[Key]],'3. Unique Results'!A:X,2,FALSE) -> book | C5: =VLOOKUP(Tabelle4[[#This Row],[Key]],'3. Unique Results'!A:X,3,FALSE) -> 2009 | D5: =VLOOKUP(Tabelle4[[#This Row],[Key]],'3. Unique Results'!A:X,4,FALSE) -> Calleja, A.; Pace, G. J. | E5: =VLOOKUP(Tabelle4[[#This Row],[Key]],'3. Unique Results'!A:X,5,FALSE) -> A domain-specific embedded language approach for the scripting of game artificial intelligence | F5: =VLOOKUP(Tabelle4[[#This Row],[Key]],'3. Unique Results'!A:X,6,FALSE) | G5: =VLOOKUP(Tabelle4[[#This Row],[Key]],'3. Unique Results'!A:X,7,FALSE) | H5: =VLOOKUP(Tabelle4[[#This Row],[Key]],'3. Unique Results'!A:X,8,FALSE) | I5: =VLOOKUP(Tabelle4[[#This Row],[Key]],'3. Unique Results'!A:X,9,FALSE) | J5: =VLOOKUP(Tabelle4[[#This Row],[Key]],'3. Unique Results'!A:X,10,FALSE) -> https://www.um.edu.mt/library/oar/handle/123456789/27604 | K5: =VLOOKUP(Tabelle4[[#This Row],[Key]],'3. Unique Results'!A:X,11,FALSE) -> 2009 | L5: =VLOOKUP(Tabelle4[[#This Row],[Key]],'3. Unique Results'!A:X,12,FALSE) -> 44887.364 | M5: =VLOOKUP(Tabelle4[[#This Row],[Key]],'3. Unique Results'!A:X,13,FALSE) -> 44887.364 | N5: =VLOOKUP(Tabelle4[[#This Row],[Key]],'3. Unique Results'!A:X,14,FALSE) -> 0 | O5: =VLOOKUP(Tabelle4[[#This Row],[Key]],'3. Unique Results'!A:X,15,FALSE) | P5: =VLOOKUP(Tabelle4[[#This Row],[Key]],'3. Unique Results'!A:X,16,FALSE) | Q5: =VLOOKUP(Tabelle4[[#This Row],[Key]],'3. Unique Results'!A:X,17,FALSE) | R5: =VLOOKUP(Tabelle4[[#This Row],[Key]],'3. Unique Results'!A:X,18,FALSE) | S5: =VLOOKUP(Tabelle4[[#This Row],[Key]],'3. Unique Results'!A:X,19,FALSE) | T5: =VLOOKUP(Tabelle4[[#This Row],[Key]],'3. Unique Results'!A:X,20,FALSE) -> um.edu.mt | U5: =VLOOKUP(Tabelle4[[#This Row],[Key]],'3. Unique Results'!A:X,21,FALSE) | V5: =VLOOKUP(Tabelle4[[#This Row],[Key]],'3. Unique Results'!A:X,22,FALSE) | W5: =VLOOKUP(Tabelle4[[#This Row],[Key]],'3. Unique Results'!A:X,23,FALSE)
A6: DFHPWT8X | B6: =VLOOKUP(Tabelle4[[#This Row],[Key]],'3. Unique Results'!A:X,2,FALSE) -> journalArticle | C6: =VLOOKUP(Tabelle4[[#This Row],[Key]],'3. Unique Results'!A:X,3,FALSE) -> 2018 | D6: =VLOOKUP(Tabelle4[[#This Row],[Key]],'3. Unique Results'!A:X,4,FALSE) -> Ghiasi, Ramin; Ghasemi, Mohammad Reza; Noori, Mohammad N. | E6: =VLOOKUP(Tabelle4[[#This Row],[Key]],'3. Unique Results'!A:X,5,FALSE) -> Comparative studies of metamodeling and AI-Based techniques in damage detection of structures | F6: =VLOOKUP(Tabelle4[[#This Row],[Key]],'3. Unique Results'!A:X,6,FALSE) -> Adv. Eng. Softw. | G6: =VLOOKUP(Tabelle4[[#This Row],[Key]],'3. Unique Results'!A:X,7,FALSE) | H6: =VLOOKUP(Tabelle4[[#This Row],[Key]],'3. Unique Results'!A:X,8,FALSE) | I6: =VLOOKUP(Tabelle4[[#This Row],[Key]],'3. Unique Results'!A:X,9,FALSE) -> 10.1016/j.advengsoft.2018.02.006 | J6: =VLOOKUP(Tabelle4[[#This Row],[Key]],'3. Unique Results'!A:X,10,FALSE) -> https://doi.org/10.1016/j.advengsoft.2018.02.006 | K6: =VLOOKUP(Tabelle4[[#This Row],[Key]],'3. Unique Results'!A:X,11,FALSE) -> 2018 | L6: =VLOOKUP(Tabelle4[[#This Row],[Key]],'3. Unique Results'!A:X,12,FALSE) -> 44887.364 | M6: =VLOOKUP(Tabelle4[[#This Row],[Key]],'3. Unique Results'!A:X,13,FALSE) -> 44887.364 | N6: =VLOOKUP(Tabelle4[[#This Row],[Key]],'3. Unique Results'!A:X,14,FALSE) -> 0 | O6: =VLOOKUP(Tabelle4[[#This Row],[Key]],'3. Unique Results'!A:X,15,FALSE) -> 101–112 | P6: =VLOOKUP(Tabelle4[[#This Row],[Key]],'3. Unique Results'!A:X,16,FALSE) | Q6: =VLOOKUP(Tabelle4[[#This Row],[Key]],'3. Unique Results'!A:X,17,FALSE) -> 125 | R6: =VLOOKUP(Tabelle4[[#This Row],[Key]],'3. Unique Results'!A:X,18,FALSE) | S6: =VLOOKUP(Tabelle4[[#This Row],[Key]],'3. Unique Results'!A:X,19,FALSE) | T6: =VLOOKUP(Tabelle4[[#This Row],[Key]],'3. Unique Results'!A:X,20,FALSE) | U6: =VLOOKUP(Tabelle4[[#This Row],[Key]],'3. Unique Results'!A:X,21,FALSE) | V6: =VLOOKUP(Tabelle4[[#This Row],[Key]],'3. Unique Results'!A:X,22,FALSE) | W6: =VLOOKUP(Tabelle4[[#This Row],[Key]],'3. Unique Results'!A:X,23,FALSE)
A7: QGZZF9WA | B7: =VLOOKUP(Tabelle4[[#This Row],[Key]],'3. Unique Results'!A:X,2,FALSE) -> conferencePaper | C7: =VLOOKUP(Tabelle4[[#This Row],[Key]],'3. Unique Results'!A:X,3,FALSE) -> 2017 | D7: =VLOOKUP(Tabelle4[[#This Row],[Key]],'3. Unique Results'!A:X,4,FALSE) -> Zhao, Tian; Huang, Xiaobing; Cao, Yu | E7: =VLOOKUP(Tabelle4[[#This Row],[Key]],'3. Unique Results'!A:X,5,FALSE) -> DeepDSL: A Compilation-based Domain-Specific Language for Deep Learning | F7: =VLOOKUP(Tabelle4[[#This Row],[Key]],'3. Unique Results'!A:X,6,FALSE) -> 5th International Conference on Learning Representations, ICLR 2017, Toulon, France, April 24-26, 2017, Conference Track Proceedings | G7: =VLOOKUP(Tabelle4[[#This Row],[Key]],'3. Unique Results'!A:X,7,FALSE) | H7: =VLOOKUP(Tabelle4[[#This Row],[Key]],'3. Unique Results'!A:X,8,FALSE) | I7: =VLOOKUP(Tabelle4[[#This Row],[Key]],'3. Unique Results'!A:X,9,FALSE) | J7: =VLOOKUP(Tabelle4[[#This Row],[Key]],'3. Unique Results'!A:X,10,FALSE) -> https://openreview.net/forum?id=Bks8cPcxe | K7: =VLOOKUP(Tabelle4[[#This Row],[Key]],'3. Unique Results'!A:X,11,FALSE) -> 2017 | L7: =VLOOKUP(Tabelle4[[#This Row],[Key]],'3. Unique Results'!A:X,12,FALSE) -> 44887.364 | M7: =VLOOKUP(Tabelle4[[#This Row],[Key]],'3. Unique Results'!A:X,13,FALSE) -> 44887.364 | N7: =VLOOKUP(Tabelle4[[#This Row],[Key]],'3. Unique Results'!A:X,14,FALSE) -> 0 | O7: =VLOOKUP(Tabelle4[[#This Row],[Key]],'3. Unique Results'!A:X,15,FALSE) | P7: =VLOOKUP(Tabelle4[[#This Row],[Key]],'3. Unique Results'!A:X,16,FALSE) | Q7: =VLOOKUP(Tabelle4[[#This Row],[Key]],'3. Unique Results'!A:X,17,FALSE) | R7: =VLOOKUP(Tabelle4[[#This Row],[Key]],'3. Unique Results'!A:X,18,FALSE) | S7: =VLOOKUP(Tabelle4[[#This Row],[Key]],'3. Unique Results'!A:X,19,FALSE) | T7: =VLOOKUP(Tabelle4[[#This Row],[Key]],'3. Unique Results'!A:X,20,FALSE) -> OpenReview.net | U7: =VLOOKUP(Tabelle4[[#This Row],[Key]],'3. Unique Results'!A:X,21,FALSE) | V7: =VLOOKUP(Tabelle4[[#This Row],[Key]],'3. Unique Results'!A:X,22,FALSE) | W7: =VLOOKUP(Tabelle4[[#This Row],[Key]],'3. Unique Results'!A:X,23,FALSE)
A8: YT9ZH6FN | B8: =VLOOKUP(Tabelle4[[#This Row],[Key]],'3. Unique Results'!A:X,2,FALSE) -> conferencePaper | C8: =VLOOKUP(Tabelle4[[#This Row],[Key]],'3. Unique Results'!A:X,3,FALSE) -> 2011 | D8: =VLOOKUP(Tabelle4[[#This Row],[Key]],'3. Unique Results'!A:X,4,FALSE) -> Chafi, Hassan; Sujeeth, Arvind K.; Brown, Kevin J.; Lee, HyoukJoong; Atreya, Anand R.; Olukotun, Kunle | E8: =VLOOKUP(Tabelle4[[#This Row],[Key]],'3. Unique Results'!A:X,5,FALSE) -> A Domain-Specific Approach to Heterogeneous Parallelism | F8: =VLOOKUP(Tabelle4[[#This Row],[Key]],'3. Unique Results'!A:X,6,FALSE) -> Proceedings of the 16th ACM Symposium on Principles and Practice of Parallel Programming | G8: =VLOOKUP(Tabelle4[[#This Row],[Key]],'3. Unique Results'!A:X,7,FALSE) -> 978-1-4503-0119-0 | H8: =VLOOKUP(Tabelle4[[#This Row],[Key]],'3. Unique Results'!A:X,8,FALSE) | I8: =VLOOKUP(Tabelle4[[#This Row],[Key]],'3. Unique Results'!A:X,9,FALSE) -> 10.1145/1941553.1941561 | J8: =VLOOKUP(Tabelle4[[#This Row],[Key]],'3. Unique Results'!A:X,10,FALSE) -> https://doi.org/10.1145/1941553.1941561 | K8: =VLOOKUP(Tabelle4[[#This Row],[Key]],'3. Unique Results'!A:X,11,FALSE) -> 2011 | L8: =VLOOKUP(Tabelle4[[#This Row],[Key]],'3. Unique Results'!A:X,12,FALSE) -> 44887.364 | M8: =VLOOKUP(Tabelle4[[#This Row],[Key]],'3. Unique Results'!A:X,13,FALSE) -> 44887.364 | N8: =VLOOKUP(Tabelle4[[#This Row],[Key]],'3. Unique Results'!A:X,14,FALSE) -> 0 | O8: =VLOOKUP(Tabelle4[[#This Row],[Key]],'3. Unique Results'!A:X,15,FALSE) -> 35–46 | P8: =VLOOKUP(Tabelle4[[#This Row],[Key]],'3. Unique Results'!A:X,16,FALSE) | Q8: =VLOOKUP(Tabelle4[[#This Row],[Key]],'3. Unique Results'!A:X,17,FALSE) | R8: =VLOOKUP(Tabelle4[[#This Row],[Key]],'3. Unique Results'!A:X,18,FALSE) | S8: =VLOOKUP(Tabelle4[[#This Row],[Key]],'3. Unique Results'!A:X,19,FALSE) | T8: =VLOOKUP(Tabelle4[[#This Row],[Key]],'3. Unique Results'!A:X,20,FALSE) -> Association for Computing Machinery | U8: =VLOOKUP(Tabelle4[[#This Row],[Key]],'3. Unique Results'!A:X,21,FALSE) -> New York, NY, USA | V8: =VLOOKUP(Tabelle4[[#This Row],[Key]],'3. Unique Results'!A:X,22,FALSE) | W8: =VLOOKUP(Tabelle4[[#This Row],[Key]],'3. Unique Results'!A:X,23,FALSE)
A9: E3RZ35LZ | B9: =VLOOKUP(Tabelle4[[#This Row],[Key]],'3. Unique Results'!A:X,2,FALSE) -> bookSection | C9: =VLOOKUP(Tabelle4[[#This Row],[Key]],'3. Unique Results'!A:X,3,FALSE) -> 2009 | D9: =VLOOKUP(Tabelle4[[#This Row],[Key]],'3. Unique Results'!A:X,4,FALSE) -> García-Díaz, Vicente; Tolosa, Jose Barranquero; G-Bustelo, B. Cristina Pelayo; Palacios-González, Elías; Sanjuan-Martínez, Óscar; Crespo, Rubén González | E9: =VLOOKUP(Tabelle4[[#This Row],[Key]],'3. Unique Results'!A:X,5,FALSE) -> TALISMAN MDE Framework: An Architecture for Intelligent Model-Driven Engineering | F9: =VLOOKUP(Tabelle4[[#This Row],[Key]],'3. Unique Results'!A:X,6,FALSE) -> Distributed Computing, Artificial Intelligence, Bioinformatics, Soft Computing, and Ambient Assisted Living | G9: =VLOOKUP(Tabelle4[[#This Row],[Key]],'3. Unique Results'!A:X,7,FALSE) -> 978-3-642-02480-1 978-3-642-02481-8 | H9: =VLOOKUP(Tabelle4[[#This Row],[Key]],'3. Unique Results'!A:X,8,FALSE) | I9: =VLOOKUP(Tabelle4[[#This Row],[Key]],'3. Unique Results'!A:X,9,FALSE) | J9: =VLOOKUP(Tabelle4[[#This Row],[Key]],'3. Unique Results'!A:X,10,FALSE) -> http://link.springer.com/10.1007/978-3-642-02481-8_43 | K9: =VLOOKUP(Tabelle4[[#This Row],[Key]],'3. Unique Results'!A:X,11,FALSE) -> 2009 | L9: =VLOOKUP(Tabelle4[[#This Row],[Key]],'3. Unique Results'!A:X,12,FALSE) -> 44887.364 | M9: =VLOOKUP(Tabelle4[[#This Row],[Key]],'3. Unique Results'!A:X,13,FALSE) -> 44887.364 | N9: =VLOOKUP(Tabelle4[[#This Row],[Key]],'3. Unique Results'!A:X,14,FALSE) -> 44886.598 | O9: =VLOOKUP(Tabelle4[[#This Row],[Key]],'3. Unique Results'!A:X,15,FALSE) -> 299-306 | P9: =VLOOKUP(Tabelle4[[#This Row],[Key]],'3. Unique Results'!A:X,16,FALSE) | Q9: =VLOOKUP(Tabelle4[[#This Row],[Key]],'3. Unique Results'!A:X,17,FALSE) -> 5518 | R9: =VLOOKUP(Tabelle4[[#This Row],[Key]],'3. Unique Results'!A:X,18,FALSE) | S9: =VLOOKUP(Tabelle4[[#This Row],[Key]],'3. Unique Results'!A:X,19,FALSE) -> TALISMAN MDE Framework | T9: =VLOOKUP(Tabelle4[[#This Row],[Key]],'3. Unique Results'!A:X,20,FALSE) -> Springer Berlin Heidelberg | U9: =VLOOKUP(Tabelle4[[#This Row],[Key]],'3. Unique Results'!A:X,21,FALSE) -> Berlin, Heidelberg | V9: =VLOOKUP(Tabelle4[[#This Row],[Key]],'3. Unique Results'!A:X,22,FALSE) | W9: =VLOOKUP(Tabelle4[[#This Row],[Key]],'3. Unique Results'!A:X,23,FALSE) -> DOI.org (Crossref)
A10: 8RC6BWB6 | B10: =VLOOKUP(Tabelle4[[#This Row],[Key]],'3. Unique Results'!A:X,2,FALSE) -> journalArticle | C10: =VLOOKUP(Tabelle4[[#This Row],[Key]],'3. Unique Results'!A:X,3,FALSE) -> 2020 | D10: =VLOOKUP(Tabelle4[[#This Row],[Key]],'3. Unique Results'!A:X,4,FALSE) -> Meacham, Sofia; Pech, Vaclav; Nauck, Detlef | E10: =VLOOKUP(Tabelle4[[#This Row],[Key]],'3. Unique Results'!A:X,5,FALSE) -> AdaptiveVLE: An Integrated Framework for Personalized Online Education Using MPS JetBrains Domain-Specific Modeling Environment | F10: =VLOOKUP(Tabelle4[[#This Row],[Key]],'3. Unique Results'!A:X,6,FALSE) -> IEEE Access | G10: =VLOOKUP(Tabelle4[[#This Row],[Key]],'3. Unique Results'!A:X,7,FALSE) | H10: =VLOOKUP(Tabelle4[[#This Row],[Key]],'3. Unique Results'!A:X,8,FALSE) | I10: =VLOOKUP(Tabelle4[[#This Row],[Key]],'3. Unique Results'!A:X,9,FALSE) -> 10.1109/ACCESS.2020.3029888 | J10: =VLOOKUP(Tabelle4[[#This Row],[Key]],'3. Unique Results'!A:X,10,FALSE) | K10: =VLOOKUP(Tabelle4[[#This Row],[Key]],'3. Unique Results'!A:X,11,FALSE) -> 2020 | L10: =VLOOKUP(Tabelle4[[#This Row],[Key]],'3. Unique Results'!A:X,12,FALSE) -> 44887.364 | M10: =VLOOKUP(Tabelle4[[#This Row],[Key]],'3. Unique Results'!A:X,13,FALSE) -> 44887.364 | N10: =VLOOKUP(Tabelle4[[#This Row],[Key]],'3. Unique Results'!A:X,14,FALSE) -> 0 | O10: =VLOOKUP(Tabelle4[[#This Row],[Key]],'3. Unique Results'!A:X,15,FALSE) -> 184621-184632 | P10: =VLOOKUP(Tabelle4[[#This Row],[Key]],'3. Unique Results'!A:X,16,FALSE) | Q10: =VLOOKUP(Tabelle4[[#This Row],[Key]],'3. Unique Results'!A:X,17,FALSE) -> 8 | R10: =VLOOKUP(Tabelle4[[#This Row],[Key]],'3. Unique Results'!A:X,18,FALSE) | S10: =VLOOKUP(Tabelle4[[#This Row],[Key]],'3. Unique Results'!A:X,19,FALSE) | T10: =VLOOKUP(Tabelle4[[#This Row],[Key]],'3. Unique Results'!A:X,20,FALSE) | U10: =VLOOKUP(Tabelle4[[#This Row],[Key]],'3. Unique Results'!A:X,21,FALSE) | V10: =VLOOKUP(Tabelle4[[#This Row],[Key]],'3. Unique Results'!A:X,22,FALSE) | W10: =VLOOKUP(Tabelle4[[#This Row],[Key]],'3. Unique Results'!A:X,23,FALSE)
A11: 4TJQZERC | B11: =VLOOKUP(Tabelle4[[#This Row],[Key]],'3. Unique Results'!A:X,2,FALSE) -> conferencePaper | C11: =VLOOKUP(Tabelle4[[#This Row],[Key]],'3. Unique Results'!A:X,3,FALSE) -> 2020 | D11: =VLOOKUP(Tabelle4[[#This Row],[Key]],'3. Unique Results'!A:X,4,FALSE) -> Ziaei, Mahdi; Zamani, Bahman; Bohlooli, Ali | E11: =VLOOKUP(Tabelle4[[#This Row],[Key]],'3. Unique Results'!A:X,5,FALSE) -> A Model-Driven Approach for IoT-Based Monitoring Systems in Industry 4.0 | F11: =VLOOKUP(Tabelle4[[#This Row],[Key]],'3. Unique Results'!A:X,6,FALSE) -> 2020 4th International Conference on Smart City, Internet of Things and Applications (SCIOT) | G11: =VLOOKUP(Tabelle4[[#This Row],[Key]],'3. Unique Results'!A:X,7,FALSE) | H11: =VLOOKUP(Tabelle4[[#This Row],[Key]],'3. Unique Results'!A:X,8,FALSE) | I11: =VLOOKUP(Tabelle4[[#This Row],[Key]],'3. Unique Results'!A:X,9,FALSE) -> 10.1109/SCIOT50840.2020.9250202 | J11: =VLOOKUP(Tabelle4[[#This Row],[Key]],'3. Unique Results'!A:X,10,FALSE) | K11: =VLOOKUP(Tabelle4[[#This Row],[Key]],'3. Unique Results'!A:X,11,FALSE) -> 2020 | L11: =VLOOKUP(Tabelle4[[#This Row],[Key]],'3. Unique Results'!A:X,12,FALSE) -> 44887.364 | M11: =VLOOKUP(Tabelle4[[#This Row],[Key]],'3. Unique Results'!A:X,13,FALSE) -> 44887.364 | N11: =VLOOKUP(Tabelle4[[#This Row],[Key]],'3. Unique Results'!A:X,14,FALSE) -> 0 | O11: =VLOOKUP(Tabelle4[[#This Row],[Key]],'3. Unique Results'!A:X,15,FALSE) -> 99-105 | P11: =VLOOKUP(Tabelle4[[#This Row],[Key]],'3. Unique Results'!A:X,16,FALSE) | Q11: =VLOOKUP(Tabelle4[[#This Row],[Key]],'3. Unique Results'!A:X,17,FALSE) | R11: =VLOOKUP(Tabelle4[[#This Row],[Key]],'3. Unique Results'!A:X,18,FALSE) | S11: =VLOOKUP(Tabelle4[[#This Row],[Key]],'3. Unique Results'!A:X,19,FALSE) | T11: =VLOOKUP(Tabelle4[[#This Row],[Key]],'3. Unique Results'!A:X,20,FALSE) | U11: =VLOOKUP(Tabelle4[[#This Row],[Key]],'3. Unique Results'!A:X,21,FALSE) | V11: =VLOOKUP(Tabelle4[[#This Row],[Key]],'3. Unique Results'!A:X,22,FALSE) | W11: =VLOOKUP(Tabelle4[[#This Row],[Key]],'3. Unique Results'!A:X,23,FALSE)
A12: AZ4AEJ6J | B12: =VLOOKUP(Tabelle4[[#This Row],[Key]],'3. Unique Results'!A:X,2,FALSE) -> conferencePaper | C12: =VLOOKUP(Tabelle4[[#This Row],[Key]],'3. Unique Results'!A:X,3,FALSE) -> 2019 | D12: =VLOOKUP(Tabelle4[[#This Row],[Key]],'3. Unique Results'!A:X,4,FALSE) -> Shokooh, Shervin; Nordvik, Geir | E12: =VLOOKUP(Tabelle4[[#This Row],[Key]],'3. Unique Results'!A:X,5,FALSE) -> A Model-Driven Approach for Situational Intelligence & Operational Awareness | F12: =VLOOKUP(Tabelle4[[#This Row],[Key]],'3. Unique Results'!A:X,6,FALSE) -> 2019 Petroleum and Chemical Industry Conference Europe (PCIC EUROPE) | G12: =VLOOKUP(Tabelle4[[#This Row],[Key]],'3. Unique Results'!A:X,7,FALSE) | H12: =VLOOKUP(Tabelle4[[#This Row],[Key]],'3. Unique Results'!A:X,8,FALSE) | I12: =VLOOKUP(Tabelle4[[#This Row],[Key]],'3. Unique Results'!A:X,9,FALSE) -> 10.23919/PCICEurope46863.2019.9011632 | J12: =VLOOKUP(Tabelle4[[#This Row],[Key]],'3. Unique Results'!A:X,10,FALSE) | K12: =VLOOKUP(Tabelle4[[#This Row],[Key]],'3. Unique Results'!A:X,11,FALSE) -> 2019 | L12: =VLOOKUP(Tabelle4[[#This Row],[Key]],'3. Unique Results'!A:X,12,FALSE) -> 44887.364 | M12: =VLOOKUP(Tabelle4[[#This Row],[Key]],'3. Unique Results'!A:X,13,FALSE) -> 44887.364 | N12: =VLOOKUP(Tabelle4[[#This Row],[Key]],'3. Unique Results'!A:X,14,FALSE) -> 0 | O12: =VLOOKUP(Tabelle4[[#This Row],[Key]],'3. Unique Results'!A:X,15,FALSE) -> 1-8 | P12: =VLOOKUP(Tabelle4[[#This Row],[Key]],'3. Unique Results'!A:X,16,FALSE) | Q12: =VLOOKUP(Tabelle4[[#This Row],[Key]],'3. Unique Results'!A:X,17,FALSE) | R12: =VLOOKUP(Tabelle4[[#This Row],[Key]],'3. Unique Results'!A:X,18,FALSE) | S12: =VLOOKUP(Tabelle4[[#This Row],[Key]],'3. Unique Results'!A:X,19,FALSE) | T12: =VLOOKUP(Tabelle4[[#This Row],[Key]],'3. Unique Results'!A:X,20,FALSE) | U12: =VLOOKUP(Tabelle4[[#This Row],[Key]],'3. Unique Results'!A:X,21,FALSE) | V12: =VLOOKUP(Tabelle4[[#This Row],[Key]],'3. Unique Results'!A:X,22,FALSE) | W12: =VLOOKUP(Tabelle4[[#This Row],[Key]],'3. Unique Results'!A:X,23,FALSE)
A13: DPT5MS8D | B13: =VLOOKUP(Tabelle4[[#This Row],[Key]],'3. Unique Results'!A:X,2,FALSE) -> conferencePaper | C13: =VLOOKUP(Tabelle4[[#This Row],[Key]],'3. Unique Results'!A:X,3,FALSE) -> 2021 | D13: =VLOOKUP(Tabelle4[[#This Row],[Key]],'3. Unique Results'!A:X,4,FALSE) -> Cong, Jason | E13: =VLOOKUP(Tabelle4[[#This Row],[Key]],'3. Unique Results'!A:X,5,FALSE) -> From Parallelization to Customization – Challenges and Opportunities | F13: =VLOOKUP(Tabelle4[[#This Row],[Key]],'3. Unique Results'!A:X,6,FALSE) -> 2021 IEEE International Parallel and Distributed Processing Symposium (IPDPS) | G13: =VLOOKUP(Tabelle4[[#This Row],[Key]],'3. Unique Results'!A:X,7,FALSE) | H13: =VLOOKUP(Tabelle4[[#This Row],[Key]],'3. Unique Results'!A:X,8,FALSE) | I13: =VLOOKUP(Tabelle4[[#This Row],[Key]],'3. Unique Results'!A:X,9,FALSE) -> 10.1109/IPDPS49936.2021.00077 | J13: =VLOOKUP(Tabelle4[[#This Row],[Key]],'3. Unique Results'!A:X,10,FALSE) | K13: =VLOOKUP(Tabelle4[[#This Row],[Key]],'3. Unique Results'!A:X,11,FALSE) -> 2021 | L13: =VLOOKUP(Tabelle4[[#This Row],[Key]],'3. Unique Results'!A:X,12,FALSE) -> 44887.364 | M13: =VLOOKUP(Tabelle4[[#This Row],[Key]],'3. Unique Results'!A:X,13,FALSE) -> 44887.364 | N13: =VLOOKUP(Tabelle4[[#This Row],[Key]],'3. Unique Results'!A:X,14,FALSE) -> 0 | O13: =VLOOKUP(Tabelle4[[#This Row],[Key]],'3. Unique Results'!A:X,15,FALSE) -> 682-682 | P13: =VLOOKUP(Tabelle4[[#This Row],[Key]],'3. Unique Results'!A:X,16,FALSE) | Q13: =VLOOKUP(Tabelle4[[#This Row],[Key]],'3. Unique Results'!A:X,17,FALSE) | R13: =VLOOKUP(Tabelle4[[#This Row],[Key]],'3. Unique Results'!A:X,18,FALSE) | S13: =VLOOKUP(Tabelle4[[#This Row],[Key]],'3. Unique Results'!A:X,19,FALSE) | T13: =VLOOKUP(Tabelle4[[#This Row],[Key]],'3. Unique Results'!A:X,20,FALSE) | U13: =VLOOKUP(Tabelle4[[#This Row],[Key]],'3. Unique Results'!A:X,21,FALSE) | V13: =VLOOKUP(Tabelle4[[#This Row],[Key]],'3. Unique Results'!A:X,22,FALSE) | W13: =VLOOKUP(Tabelle4[[#This Row],[Key]],'3. Unique Results'!A:X,23,FALSE)
... A92: 227PU6N9 | B92: =VLOOKUP(Tabelle4[[#This Row],[Key]],'3. Unique Results'!A:X,2,FALSE) -> #N/A | C92: =VLOOKUP(Tabelle4[[#This Row],[Key]],'3. Unique Results'!A:X,3,FALSE) -> #N/A | D92: =VLOOKUP(Tabelle4[[#This Row],[Key]],'3. Unique Results'!A:X,4,FALSE) -> #N/A | E92: =VLOOKUP(Tabelle4[[#This Row],[Key]],'3. Unique Results'!A:X,5,FALSE) -> #N/A | F92: =VLOOKUP(Tabelle4[[#This Row],[Key]],'3. Unique Results'!A:X,6,FALSE) -> #N/A | G92: =VLOOKUP(Tabelle4[[#This Row],[Key]],'3. Unique Results'!A:X,7,FALSE) -> #N/A | H92: =VLOOKUP(Tabelle4[[#This Row],[Key]],'3. Unique Results'!A:X,8,FALSE) -> #N/A | I92: =VLOOKUP(Tabelle4[[#This Row],[Key]],'3. Unique Results'!A:X,9,FALSE) -> #N/A | J92: =VLOOKUP(Tabelle4[[#This Row],[Key]],'3. Unique Results'!A:X,10,FALSE) -> #N/A | K92: =VLOOKUP(Tabelle4[[#This Row],[Key]],'3. Unique Results'!A:X,11,FALSE) -> #N/A | L92: =VLOOKUP(Tabelle4[[#This Row],[Key]],'3. Unique Results'!A:X,12,FALSE) -> #N/A | M92: =VLOOKUP(Tabelle4[[#This Row],[Key]],'3. Unique Results'!A:X,13,FALSE) -> #N/A | N92: =VLOOKUP(Tabelle4[[#This Row],[Key]],'3. Unique Results'!A:X,14,FALSE) -> #N/A | O92: =VLOOKUP(Tabelle4[[#This Row],[Key]],'3. Unique Results'!A:X,15,FALSE) -> #N/A | P92: =VLOOKUP(Tabelle4[[#This Row],[Key]],'3. Unique Results'!A:X,16,FALSE) -> #N/A | Q92: =VLOOKUP(Tabelle4[[#This Row],[Key]],'3. Unique Results'!A:X,17,FALSE) -> #N/A | R92: =VLOOKUP(Tabelle4[[#This Row],[Key]],'3. Unique Results'!A:X,18,FALSE) -> #N/A | S92: =VLOOKUP(Tabelle4[[#This Row],[Key]],'3. Unique Results'!A:X,19,FALSE) -> #N/A | T92: =VLOOKUP(Tabelle4[[#This Row],[Key]],'3. Unique Results'!A:X,20,FALSE) -> #N/A | U92: =VLOOKUP(Tabelle4[[#This Row],[Key]],'3. Unique Results'!A:X,21,FALSE) -> #N/A | V92: =VLOOKUP(Tabelle4[[#This Row],[Key]],'3. Unique Results'!A:X,22,FALSE) -> #N/A | W92: =VLOOKUP(Tabelle4[[#This Row],[Key]],'3. Unique Results'!A:X,23,FALSE) -> #N/A

Sheet 5. Selection Based on Abstract
A1: Key | B1: Item Type | C1: Publication Year | D1: Author | E1: Title | F1: Publication Title | G1: ISBN | H1: ISSN | I1: DOI | J1: Url | K1: Abstract Note | L1: Date | M1: Date Added | N1: Date Modified | O1: Access Date | P1: Pages | Q1: Num Pages | R1: Issue | S1: Volume | T1: Series | U1: Publisher | V1: Place | W1: Extra
A2: UCWWRPIQ | B2: =VLOOKUP(Tabelle43[[#This Row],[Key]],'3. Unique Results'!A:X,2,FALSE) -> conferencePaper | C2: =VLOOKUP(Tabelle43[[#This Row],[Key]],'3. Unique Results'!A:X,3,FALSE) -> 2020 | D2: =VLOOKUP(Tabelle43[[#This Row],[Key]],'3. Unique Results'!A:X,4,FALSE) -> Al-Azzoni, Issam | E2: =VLOOKUP(Tabelle43[[#This Row],[Key]],'3. Unique Results'!A:X,5,FALSE) -> Model Driven Approach for Neural Networks | F2: =VLOOKUP(Tabelle43[[#This Row],[Key]],'3. Unique Results'!A:X,6,FALSE) -> 2020 International Conference on Intelligent Data Science Technologies and Applications (IDSTA) | G2: =VLOOKUP(Tabelle43[[#This Row],[Key]],'3. Unique Results'!A:X,7,FALSE) | H2: =VLOOKUP(Tabelle43[[#This Row],[Key]],'3. Unique Results'!A:X,8,FALSE) | I2: =VLOOKUP(Tabelle43[[#This Row],[Key]],'3. Unique Results'!A:X,9,FALSE) -> 10.1109/IDSTA50958.2020.9264067 | J2: =VLOOKUP(Tabelle43[[#This Row],[Key]],'3. Unique Results'!A:X,10,FALSE) | K2: =VLOOKUP(Tabelle43[[#This Row],[Key]],'3. Unique Results'!A:X,11,FALSE) -> 2020 | L2: =VLOOKUP(Tabelle43[[#This Row],[Key]],'3. Unique Results'!A:X,12,FALSE) -> 44887.364 | M2: =VLOOKUP(Tabelle43[[#This Row],[Key]],'3. Unique Results'!A:X,13,FALSE) -> 44887.364 | N2: =VLOOKUP(Tabelle43[[#This Row],[Key]],'3. Unique Results'!A:X,14,FALSE) -> 0 | O2: =VLOOKUP(Tabelle43[[#This Row],[Key]],'3. Unique Results'!A:X,15,FALSE) -> 87-94 | P2: =VLOOKUP(Tabelle43[[#This Row],[Key]],'3. Unique Results'!A:X,16,FALSE) | Q2: =VLOOKUP(Tabelle43[[#This Row],[Key]],'3. Unique Results'!A:X,17,FALSE) | R2: =VLOOKUP(Tabelle43[[#This Row],[Key]],'3. Unique Results'!A:X,18,FALSE) | S2: =VLOOKUP(Tabelle43[[#This Row],[Key]],'3. Unique Results'!A:X,19,FALSE) | T2: =VLOOKUP(Tabelle43[[#This Row],[Key]],'3. Unique Results'!A:X,20,FALSE) | U2: =VLOOKUP(Tabelle43[[#This Row],[Key]],'3. Unique Results'!A:X,21,FALSE) | V2: =VLOOKUP(Tabelle43[[#This Row],[Key]],'3. Unique Results'!A:X,22,FALSE) | W2: =VLOOKUP(Tabelle43[[#This Row],[Key]],'3. Unique Results'!A:X,23,FALSE)
A3: KGVRCW7T | B3: =VLOOKUP(Tabelle43[[#This Row],[Key]],'3. Unique Results'!A:X,2,FALSE) -> conferencePaper | C3: =VLOOKUP(Tabelle43[[#This Row],[Key]],'3. Unique Results'!A:X,3,FALSE) -> 2020 | D3: =VLOOKUP(Tabelle43[[#This Row],[Key]],'3. Unique Results'!A:X,4,FALSE) -> Benaben, Frederick; Lauras, Matthieu; Fertier, Audrey; Salatgé, Nicolas | E3: =VLOOKUP(Tabelle43[[#This Row],[Key]],'3. Unique Results'!A:X,5,FALSE) -> Integrating Model-Driven Engineering as the next Challenge for Artificial Intelligence: Application to Risk and Crisis Management | F3: =VLOOKUP(Tabelle43[[#This Row],[Key]],'3. Unique Results'!A:X,6,FALSE) -> Proceedings of the Winter Simulation Conference | G3: =VLOOKUP(Tabelle43[[#This Row],[Key]],'3. Unique Results'!A:X,7,FALSE) -> 978-1-72813-283-9 | H3: =VLOOKUP(Tabelle43[[#This Row],[Key]],'3. Unique Results'!A:X,8,FALSE) | I3: =VLOOKUP(Tabelle43[[#This Row],[Key]],'3. Unique Results'!A:X,9,FALSE) | J3: =VLOOKUP(Tabelle43[[#This Row],[Key]],'3. Unique Results'!A:X,10,FALSE) | K3: =VLOOKUP(Tabelle43[[#This Row],[Key]],'3. Unique Results'!A:X,11,FALSE) -> 2020 | L3: =VLOOKUP(Tabelle43[[#This Row],[Key]],'3. Unique Results'!A:X,12,FALSE) -> 44887.364 | M3: =VLOOKUP(Tabelle43[[#This Row],[Key]],'3. Unique Results'!A:X,13,FALSE) -> 44887.492 | N3: =VLOOKUP(Tabelle43[[#This Row],[Key]],'3. Unique Results'!A:X,14,FALSE) -> 0 | O3: =VLOOKUP(Tabelle43[[#This Row],[Key]],'3. Unique Results'!A:X,15,FALSE) -> 1549–1563 | P3: =VLOOKUP(Tabelle43[[#This Row],[Key]],'3. Unique Results'!A:X,16,FALSE) | Q3: =VLOOKUP(Tabelle43[[#This Row],[Key]],'3. Unique Results'!A:X,17,FALSE) | R3: =VLOOKUP(Tabelle43[[#This Row],[Key]],'3. Unique Results'!A:X,18,FALSE) | S3: =VLOOKUP(Tabelle43[[#This Row],[Key]],'3. Unique Results'!A:X,19,FALSE) | T3: =VLOOKUP(Tabelle43[[#This Row],[Key]],'3. Unique Results'!A:X,20,FALSE) -> IEEE Press | U3: =VLOOKUP(Tabelle43[[#This Row],[Key]],'3. Unique Results'!A:X,21,FALSE) | V3: =VLOOKUP(Tabelle43[[#This Row],[Key]],'3. Unique Results'!A:X,22,FALSE) | W3: =VLOOKUP(Tabelle43[[#This Row],[Key]],'3. Unique Results'!A:X,23,FALSE)
A4: BQTIAXTW | B4: =VLOOKUP(Tabelle43[[#This Row],[Key]],'3. Unique Results'!A:X,2,FALSE) -> conferencePaper | C4: =VLOOKUP(Tabelle43[[#This Row],[Key]],'3. Unique Results'!A:X,3,FALSE) -> 2019 | D4: =VLOOKUP(Tabelle43[[#This Row],[Key]],'3. Unique Results'!A:X,4,FALSE) -> Bhattacharjee, Anirban; Barve, Yogesh; Khare, Shweta; Bao, Shunxing; Kang, Zhuangwei; Gokhale, Aniruddha; Damiano, Thomas | E4: =VLOOKUP(Tabelle43[[#This Row],[Key]],'3. Unique Results'!A:X,5,FALSE) -> STRATUM: A BigData-as-a-Service for Lifecycle Management of IoT Analytics Applications | F4: =VLOOKUP(Tabelle43[[#This Row],[Key]],'3. Unique Results'!A:X,6,FALSE) -> 2019 IEEE International Conference on Big Data (Big Data) | G4: =VLOOKUP(Tabelle43[[#This Row],[Key]],'3. Unique Results'!A:X,7,FALSE) | H4: =VLOOKUP(Tabelle43[[#This Row],[Key]],'3. Unique Results'!A:X,8,FALSE) | I4: =VLOOKUP(Tabelle43[[#This Row],[Key]],'3. Unique Results'!A:X,9,FALSE) -> 10.1109/BigData47090.2019.9006518 | J4: =VLOOKUP(Tabelle43[[#This Row],[Key]],'3. Unique Results'!A:X,10,FALSE) | K4: =VLOOKUP(Tabelle43[[#This Row],[Key]],'3. Unique Results'!A:X,11,FALSE) -> 2019 | L4: =VLOOKUP(Tabelle43[[#This Row],[Key]],'3. Unique Results'!A:X,12,FALSE) -> 44887.364 | M4: =VLOOKUP(Tabelle43[[#This Row],[Key]],'3. Unique Results'!A:X,13,FALSE) -> 44887.364 | N4: =VLOOKUP(Tabelle43[[#This Row],[Key]],'3. Unique Results'!A:X,14,FALSE) -> 0 | O4: =VLOOKUP(Tabelle43[[#This Row],[Key]],'3. Unique Results'!A:X,15,FALSE) -> 1607-1612 | P4: =VLOOKUP(Tabelle43[[#This Row],[Key]],'3. Unique Results'!A:X,16,FALSE) | Q4: =VLOOKUP(Tabelle43[[#This Row],[Key]],'3. Unique Results'!A:X,17,FALSE) | R4: =VLOOKUP(Tabelle43[[#This Row],[Key]],'3. Unique Results'!A:X,18,FALSE) | S4: =VLOOKUP(Tabelle43[[#This Row],[Key]],'3. Unique Results'!A:X,19,FALSE) | T4: =VLOOKUP(Tabelle43[[#This Row],[Key]],'3. Unique Results'!A:X,20,FALSE) | U4: =VLOOKUP(Tabelle43[[#This Row],[Key]],'3. Unique Results'!A:X,21,FALSE) | V4: =VLOOKUP(Tabelle43[[#This Row],[Key]],'3. Unique Results'!A:X,22,FALSE) | W4: =VLOOKUP(Tabelle43[[#This Row],[Key]],'3. Unique Results'!A:X,23,FALSE)
A5: UJPER7V8 | B5: =VLOOKUP(Tabelle43[[#This Row],[Key]],'3. Unique Results'!A:X,2,FALSE) -> journalArticle | C5: =VLOOKUP(Tabelle43[[#This Row],[Key]],'3. Unique Results'!A:X,3,FALSE) -> 2014 | D5: =VLOOKUP(Tabelle43[[#This Row],[Key]],'3. Unique Results'!A:X,4,FALSE) -> Breuker, D. | E5: =VLOOKUP(Tabelle43[[#This Row],[Key]],'3. Unique Results'!A:X,5,FALSE) -> Towards Model-Driven Engineering for Big Data Analytics–An Exploratory Analysis of Domain-Specific Languages for Machine Learning | F5: =VLOOKUP(Tabelle43[[#This Row],[Key]],'3. Unique Results'!A:X,6,FALSE) -> 2014 47th Hawaii International Conference on … | G5: =VLOOKUP(Tabelle43[[#This Row],[Key]],'3. Unique Results'!A:X,7,FALSE) | H5: =VLOOKUP(Tabelle43[[#This Row],[Key]],'3. Unique Results'!A:X,8,FALSE) | I5: =VLOOKUP(Tabelle43[[#This Row],[Key]],'3. Unique Results'!A:X,9,FALSE) | J5: =VLOOKUP(Tabelle43[[#This Row],[Key]],'3. Unique Results'!A:X,10,FALSE) -> https://ieeexplore.ieee.org/abstract/document/6758697/ | K5: =VLOOKUP(Tabelle43[[#This Row],[Key]],'3. Unique Results'!A:X,11,FALSE) -> 2014 | L5: =VLOOKUP(Tabelle43[[#This Row],[Key]],'3. Unique Results'!A:X,12,FALSE) -> 44887.364 | M5: =VLOOKUP(Tabelle43[[#This Row],[Key]],'3. Unique Results'!A:X,13,FALSE) -> 44887.364 | N5: =VLOOKUP(Tabelle43[[#This Row],[Key]],'3. Unique Results'!A:X,14,FALSE) -> 0 | O5: =VLOOKUP(Tabelle43[[#This Row],[Key]],'3. Unique Results'!A:X,15,FALSE) | P5: =VLOOKUP(Tabelle43[[#This Row],[Key]],'3. Unique Results'!A:X,16,FALSE) | Q5: =VLOOKUP(Tabelle43[[#This Row],[Key]],'3. Unique Results'!A:X,17,FALSE) | R5: =VLOOKUP(Tabelle43[[#This Row],[Key]],'3. Unique Results'!A:X,18,FALSE) | S5: =VLOOKUP(Tabelle43[[#This Row],[Key]],'3. Unique Results'!A:X,19,FALSE) | T5: =VLOOKUP(Tabelle43[[#This Row],[Key]],'3. Unique Results'!A:X,20,FALSE) | U5: =VLOOKUP(Tabelle43[[#This Row],[Key]],'3. Unique Results'!A:X,21,FALSE) | V5: =VLOOKUP(Tabelle43[[#This Row],[Key]],'3. Unique Results'!A:X,22,FALSE) | W5: =VLOOKUP(Tabelle43[[#This Row],[Key]],'3. Unique Results'!A:X,23,FALSE)
A6: TQWM56I7 | B6: =VLOOKUP(Tabelle43[[#This Row],[Key]],'3. Unique Results'!A:X,2,FALSE) -> journalArticle | C6: =VLOOKUP(Tabelle43[[#This Row],[Key]],'3. Unique Results'!A:X,3,FALSE) -> 2022 | D6: =VLOOKUP(Tabelle43[[#This Row],[Key]],'3. Unique Results'!A:X,4,FALSE) -> Burgueño, Lola; Cabot, Jordi; Wimmer, Manuel; Zschaler, Steffen | E6: =VLOOKUP(Tabelle43[[#This Row],[Key]],'3. Unique Results'!A:X,5,FALSE) -> Guest editorial to the theme section on AI-enhanced model-driven engineering | F6: =VLOOKUP(Tabelle43[[#This Row],[Key]],'3. Unique Results'!A:X,6,FALSE) -> Software and Systems Modeling | G6: =VLOOKUP(Tabelle43[[#This Row],[Key]],'3. Unique Results'!A:X,7,FALSE) | H6: =VLOOKUP(Tabelle43[[#This Row],[Key]],'3. Unique Results'!A:X,8,FALSE) -> 1619-1366, 1619-1374 | I6: =VLOOKUP(Tabelle43[[#This Row],[Key]],'3. Unique Results'!A:X,9,FALSE) -> 10.1007/s10270-022-00988-0 | J6: =VLOOKUP(Tabelle43[[#This Row],[Key]],'3. Unique Results'!A:X,10,FALSE) -> https://link.springer.com/10.1007/s10270-022-00988-0 | K6: =VLOOKUP(Tabelle43[[#This Row],[Key]],'3. Unique Results'!A:X,11,FALSE) -> 2022-06 | L6: =VLOOKUP(Tabelle43[[#This Row],[Key]],'3. Unique Results'!A:X,12,FALSE) -> 44887.364 | M6: =VLOOKUP(Tabelle43[[#This Row],[Key]],'3. Unique Results'!A:X,13,FALSE) -> 44887.364 | N6: =VLOOKUP(Tabelle43[[#This Row],[Key]],'3. Unique Results'!A:X,14,FALSE) -> 44886.598 | O6: =VLOOKUP(Tabelle43[[#This Row],[Key]],'3. Unique Results'!A:X,15,FALSE) -> 963-965 | P6: =VLOOKUP(Tabelle43[[#This Row],[Key]],'3. Unique Results'!A:X,16,FALSE) -> 3 | Q6: =VLOOKUP(Tabelle43[[#This Row],[Key]],'3. Unique Results'!A:X,17,FALSE) -> 21 | R6: =VLOOKUP(Tabelle43[[#This Row],[Key]],'3. Unique Results'!A:X,18,FALSE) -> Softw Syst Model | S6: =VLOOKUP(Tabelle43[[#This Row],[Key]],'3. Unique Results'!A:X,19,FALSE) | T6: =VLOOKUP(Tabelle43[[#This Row],[Key]],'3. Unique Results'!A:X,20,FALSE) | U6: =VLOOKUP(Tabelle43[[#This Row],[Key]],'3. Unique Results'!A:X,21,FALSE) | V6: =VLOOKUP(Tabelle43[[#This Row],[Key]],'3. Unique Results'!A:X,22,FALSE) -> en | W6: =VLOOKUP(Tabelle43[[#This Row],[Key]],'3. Unique Results'!A:X,23,FALSE) -> DOI.org (Crossref)
A7: MPTKPIZW | B7: =VLOOKUP(Tabelle43[[#This Row],[Key]],'3. Unique Results'!A:X,2,FALSE) -> conferencePaper | C7: =VLOOKUP(Tabelle43[[#This Row],[Key]],'3. Unique Results'!A:X,3,FALSE) -> 2021 | D7: =VLOOKUP(Tabelle43[[#This Row],[Key]],'3. Unique Results'!A:X,4,FALSE) -> Burgueño, Loli; Burdusel, Alexandru; Gérard, Sébastien; Wimmer, Manuel | E7: =VLOOKUP(Tabelle43[[#This Row],[Key]],'3. Unique Results'!A:X,5,FALSE) -> MDE Intelligence 2019: 1st Workshop on Artificial Intelligence and Model-Driven Engineering | F7: =VLOOKUP(Tabelle43[[#This Row],[Key]],'3. Unique Results'!A:X,6,FALSE) -> Proceedings of the 22nd International Conference on Model Driven Engineering Languages and Systems | G7: =VLOOKUP(Tabelle43[[#This Row],[Key]],'3. Unique Results'!A:X,7,FALSE) -> 978-1-72815-125-0 | H7: =VLOOKUP(Tabelle43[[#This Row],[Key]],'3. Unique Results'!A:X,8,FALSE) | I7: =VLOOKUP(Tabelle43[[#This Row],[Key]],'3. Unique Results'!A:X,9,FALSE) -> 10.1109/MODELS-C.2019.00028 | J7: =VLOOKUP(Tabelle43[[#This Row],[Key]],'3. Unique Results'!A:X,10,FALSE) -> https://doi.org/10.1109/MODELS-C.2019.00028 | K7: =VLOOKUP(Tabelle43[[#This Row],[Key]],'3. Unique Results'!A:X,11,FALSE) -> 2021 | L7: =VLOOKUP(Tabelle43[[#This Row],[Key]],'3. Unique Results'!A:X,12,FALSE) -> 44887.364 | M7: =VLOOKUP(Tabelle43[[#This Row],[Key]],'3. Unique Results'!A:X,13,FALSE) -> 44887.364 | N7: =VLOOKUP(Tabelle43[[#This Row],[Key]],'3. Unique Results'!A:X,14,FALSE) -> 0 | O7: =VLOOKUP(Tabelle43[[#This Row],[Key]],'3. Unique Results'!A:X,15,FALSE) -> 168–169 | P7: =VLOOKUP(Tabelle43[[#This Row],[Key]],'3. Unique Results'!A:X,16,FALSE) | Q7: =VLOOKUP(Tabelle43[[#This Row],[Key]],'3. Unique Results'!A:X,17,FALSE) | R7: =VLOOKUP(Tabelle43[[#This Row],[Key]],'3. Unique Results'!A:X,18,FALSE) | S7: =VLOOKUP(Tabelle43[[#This Row],[Key]],'3. Unique Results'!A:X,19,FALSE) | T7: =VLOOKUP(Tabelle43[[#This Row],[Key]],'3. Unique Results'!A:X,20,FALSE) -> IEEE Press | U7: =VLOOKUP(Tabelle43[[#This Row],[Key]],'3. Unique Results'!A:X,21,FALSE) | V7: =VLOOKUP(Tabelle43[[#This Row],[Key]],'3. Unique Results'!A:X,22,FALSE) | W7: =VLOOKUP(Tabelle43[[#This Row],[Key]],'3. Unique Results'!A:X,23,FALSE)
A8: LD7J8SB2 | B8: =VLOOKUP(Tabelle43[[#This Row],[Key]],'3. Unique Results'!A:X,2,FALSE) -> journalArticle | C8: =VLOOKUP(Tabelle43[[#This Row],[Key]],'3. Unique Results'!A:X,3,FALSE) -> 2021 | D8: =VLOOKUP(Tabelle43[[#This Row],[Key]],'3. Unique Results'!A:X,4,FALSE) -> Burgueño, Loli; Kessentini, Marouane; Wimmer, Manuel; Zschaler, Steffen | E8: =VLOOKUP(Tabelle43[[#This Row],[Key]],'3. Unique Results'!A:X,5,FALSE) -> MDE Intelligence 2021: 3rd Workshop on Artificial Intelligence and Model-Driven Engineering | F8: =VLOOKUP(Tabelle43[[#This Row],[Key]],'3. Unique Results'!A:X,6,FALSE) -> 2021 ACM/IEEE International Conference on Model Driven Engineering Languages and Systems Companion (MODELS-C) | G8: =VLOOKUP(Tabelle43[[#This Row],[Key]],'3. Unique Results'!A:X,7,FALSE) | H8: =VLOOKUP(Tabelle43[[#This Row],[Key]],'3. Unique Results'!A:X,8,FALSE) | I8: =VLOOKUP(Tabelle43[[#This Row],[Key]],'3. Unique Results'!A:X,9,FALSE) -> 10.1109/MODELS-C53483.2021.00026 | J8: =VLOOKUP(Tabelle43[[#This Row],[Key]],'3. Unique Results'!A:X,10,FALSE) | K8: =VLOOKUP(Tabelle43[[#This Row],[Key]],'3. Unique Results'!A:X,11,FALSE) -> 2021 | L8: =VLOOKUP(Tabelle43[[#This Row],[Key]],'3. Unique Results'!A:X,12,FALSE) -> 44887.364 | M8: =VLOOKUP(Tabelle43[[#This Row],[Key]],'3. Unique Results'!A:X,13,FALSE) -> 44887.364 | N8: =VLOOKUP(Tabelle43[[#This Row],[Key]],'3. Unique Results'!A:X,14,FALSE) -> 0 | O8: =VLOOKUP(Tabelle43[[#This Row],[Key]],'3. Unique Results'!A:X,15,FALSE) -> 148-149 | P8: =VLOOKUP(Tabelle43[[#This Row],[Key]],'3. Unique Results'!A:X,16,FALSE) | Q8: =VLOOKUP(Tabelle43[[#This Row],[Key]],'3. Unique Results'!A:X,17,FALSE) | R8: =VLOOKUP(Tabelle43[[#This Row],[Key]],'3. Unique Results'!A:X,18,FALSE) | S8: =VLOOKUP(Tabelle43[[#This Row],[Key]],'3. Unique Results'!A:X,19,FALSE) | T8: =VLOOKUP(Tabelle43[[#This Row],[Key]],'3. Unique Results'!A:X,20,FALSE) | U8: =VLOOKUP(Tabelle43[[#This Row],[Key]],'3. Unique Results'!A:X,21,FALSE) | V8: =VLOOKUP(Tabelle43[[#This Row],[Key]],'3. Unique Results'!A:X,22,FALSE) | W8: =VLOOKUP(Tabelle43[[#This Row],[Key]],'3. Unique Results'!A:X,23,FALSE)
A9: 3QB88ANK | B9: =VLOOKUP(Tabelle43[[#This Row],[Key]],'3. Unique Results'!A:X,2,FALSE) -> conferencePaper | C9: =VLOOKUP(Tabelle43[[#This Row],[Key]],'3. Unique Results'!A:X,3,FALSE) -> 2022 | D9: =VLOOKUP(Tabelle43[[#This Row],[Key]],'3. Unique Results'!A:X,4,FALSE) -> Burnay, Corentin; Giunta, Benito | E9: =VLOOKUP(Tabelle43[[#This Row],[Key]],'3. Unique Results'!A:X,5,FALSE) -> Towards Integrated Model-Driven Engineering Approach to Business Intelligence | F9: =VLOOKUP(Tabelle43[[#This Row],[Key]],'3. Unique Results'!A:X,6,FALSE) -> Research Challenges in Information Science | G9: =VLOOKUP(Tabelle43[[#This Row],[Key]],'3. Unique Results'!A:X,7,FALSE) -> 978-3-031-05759-5 978-3-031-05760-1 | H9: =VLOOKUP(Tabelle43[[#This Row],[Key]],'3. Unique Results'!A:X,8,FALSE) | I9: =VLOOKUP(Tabelle43[[#This Row],[Key]],'3. Unique Results'!A:X,9,FALSE) | J9: =VLOOKUP(Tabelle43[[#This Row],[Key]],'3. Unique Results'!A:X,10,FALSE) -> https://link.springer.com/10.1007/978-3-031-05760-1_38 | K9: =VLOOKUP(Tabelle43[[#This Row],[Key]],'3. Unique Results'!A:X,11,FALSE) -> 2022 | L9: =VLOOKUP(Tabelle43[[#This Row],[Key]],'3. Unique Results'!A:X,12,FALSE) -> 44887.364 | M9: =VLOOKUP(Tabelle43[[#This Row],[Key]],'3. Unique Results'!A:X,13,FALSE) -> 44887.364 | N9: =VLOOKUP(Tabelle43[[#This Row],[Key]],'3. Unique Results'!A:X,14,FALSE) -> 44886.598 | O9: =VLOOKUP(Tabelle43[[#This Row],[Key]],'3. Unique Results'!A:X,15,FALSE) -> 635-643 | P9: =VLOOKUP(Tabelle43[[#This Row],[Key]],'3. Unique Results'!A:X,16,FALSE) | Q9: =VLOOKUP(Tabelle43[[#This Row],[Key]],'3. Unique Results'!A:X,17,FALSE) -> 446 | R9: =VLOOKUP(Tabelle43[[#This Row],[Key]],'3. Unique Results'!A:X,18,FALSE) | S9: =VLOOKUP(Tabelle43[[#This Row],[Key]],'3. Unique Results'!A:X,19,FALSE) | T9: =VLOOKUP(Tabelle43[[#This Row],[Key]],'3. Unique Results'!A:X,20,FALSE) -> Springer International Publishing | U9: =VLOOKUP(Tabelle43[[#This Row],[Key]],'3. Unique Results'!A:X,21,FALSE) -> Cham | V9: =VLOOKUP(Tabelle43[[#This Row],[Key]],'3. Unique Results'!A:X,22,FALSE) -> en | W9: =VLOOKUP(Tabelle43[[#This Row],[Key]],'3. Unique Results'!A:X,23,FALSE) -> DOI.org (Crossref)
A10: YT9ZH6FN | B10: =VLOOKUP(Tabelle43[[#This Row],[Key]],'3. Unique Results'!A:X,2,FALSE) -> conferencePaper | C10: =VLOOKUP(Tabelle43[[#This Row],[Key]],'3. Unique Results'!A:X,3,FALSE) -> 2011 | D10: =VLOOKUP(Tabelle43[[#This Row],[Key]],'3. Unique Results'!A:X,4,FALSE) -> Chafi, Hassan; Sujeeth, Arvind K.; Brown, Kevin J.; Lee, HyoukJoong; Atreya, Anand R.; Olukotun, Kunle | E10: =VLOOKUP(Tabelle43[[#This Row],[Key]],'3. Unique Results'!A:X,5,FALSE) -> A Domain-Specific Approach to Heterogeneous Parallelism | F10: =VLOOKUP(Tabelle43[[#This Row],[Key]],'3. Unique Results'!A:X,6,FALSE) -> Proceedings of the 16th ACM Symposium on Principles and Practice of Parallel Programming | G10: =VLOOKUP(Tabelle43[[#This Row],[Key]],'3. Unique Results'!A:X,7,FALSE) -> 978-1-4503-0119-0 | H10: =VLOOKUP(Tabelle43[[#This Row],[Key]],'3. Unique Results'!A:X,8,FALSE) | I10: =VLOOKUP(Tabelle43[[#This Row],[Key]],'3. Unique Results'!A:X,9,FALSE) -> 10.1145/1941553.1941561 | J10: =VLOOKUP(Tabelle43[[#This Row],[Key]],'3. Unique Results'!A:X,10,FALSE) -> https://doi.org/10.1145/1941553.1941561 | K10: =VLOOKUP(Tabelle43[[#This Row],[Key]],'3. Unique Results'!A:X,11,FALSE) -> 2011 | L10: =VLOOKUP(Tabelle43[[#This Row],[Key]],'3. Unique Results'!A:X,12,FALSE) -> 44887.364 | M10: =VLOOKUP(Tabelle43[[#This Row],[Key]],'3. Unique Results'!A:X,13,FALSE) -> 44887.364 | N10: =VLOOKUP(Tabelle43[[#This Row],[Key]],'3. Unique Results'!A:X,14,FALSE) -> 0 | O10: =VLOOKUP(Tabelle43[[#This Row],[Key]],'3. Unique Results'!A:X,15,FALSE) -> 35–46 | P10: =VLOOKUP(Tabelle43[[#This Row],[Key]],'3. Unique Results'!A:X,16,FALSE) | Q10: =VLOOKUP(Tabelle43[[#This Row],[Key]],'3. Unique Results'!A:X,17,FALSE) | R10: =VLOOKUP(Tabelle43[[#This Row],[Key]],'3. Unique Results'!A:X,18,FALSE) | S10: =VLOOKUP(Tabelle43[[#This Row],[Key]],'3. Unique Results'!A:X,19,FALSE) | T10: =VLOOKUP(Tabelle43[[#This Row],[Key]],'3. Unique Results'!A:X,20,FALSE) -> Association for Computing Machinery | U10: =VLOOKUP(Tabelle43[[#This Row],[Key]],'3. Unique Results'!A:X,21,FALSE) -> New York, NY, USA | V10: =VLOOKUP(Tabelle43[[#This Row],[Key]],'3. Unique Results'!A:X,22,FALSE) | W10: =VLOOKUP(Tabelle43[[#This Row],[Key]],'3. Unique Results'!A:X,23,FALSE)
A11: HMQVEDXS | B11: =VLOOKUP(Tabelle43[[#This Row],[Key]],'3. Unique Results'!A:X,2,FALSE) -> conferencePaper | C11: =VLOOKUP(Tabelle43[[#This Row],[Key]],'3. Unique Results'!A:X,3,FALSE) -> 2017 | D11: =VLOOKUP(Tabelle43[[#This Row],[Key]],'3. Unique Results'!A:X,4,FALSE) -> Dethlefs, Nina; Hawick, Ken | E11: =VLOOKUP(Tabelle43[[#This Row],[Key]],'3. Unique Results'!A:X,5,FALSE) -> DEFIne: A Fluent Interface DSL for Deep Learning Applications | F11: =VLOOKUP(Tabelle43[[#This Row],[Key]],'3. Unique Results'!A:X,6,FALSE) -> Proceedings of the 2nd International Workshop on Real World Domain Specific Languages | G11: =VLOOKUP(Tabelle43[[#This Row],[Key]],'3. Unique Results'!A:X,7,FALSE) -> 978-1-4503-4845-4 | H11: =VLOOKUP(Tabelle43[[#This Row],[Key]],'3. Unique Results'!A:X,8,FALSE) | I11: =VLOOKUP(Tabelle43[[#This Row],[Key]],'3. Unique Results'!A:X,9,FALSE) -> 10.1145/3039895.3039898 | J11: =VLOOKUP(Tabelle43[[#This Row],[Key]],'3. Unique Results'!A:X,10,FALSE) -> https://doi.org/10.1145/3039895.3039898 | K11: =VLOOKUP(Tabelle43[[#This Row],[Key]],'3. Unique Results'!A:X,11,FALSE) -> 2017 | L11: =VLOOKUP(Tabelle43[[#This Row],[Key]],'3. Unique Results'!A:X,12,FALSE) -> 44887.364 | M11: =VLOOKUP(Tabelle43[[#This Row],[Key]],'3. Unique Results'!A:X,13,FALSE) -> 44887.411 | N11: =VLOOKUP(Tabelle43[[#This Row],[Key]],'3. Unique Results'!A:X,14,FALSE) -> 0 | O11: =VLOOKUP(Tabelle43[[#This Row],[Key]],'3. Unique Results'!A:X,15,FALSE) | P11: =VLOOKUP(Tabelle43[[#This Row],[Key]],'3. Unique Results'!A:X,16,FALSE) | Q11: =VLOOKUP(Tabelle43[[#This Row],[Key]],'3. Unique Results'!A:X,17,FALSE) | R11: =VLOOKUP(Tabelle43[[#This Row],[Key]],'3. Unique Results'!A:X,18,FALSE) | S11: =VLOOKUP(Tabelle43[[#This Row],[Key]],'3. Unique Results'!A:X,19,FALSE) | T11: =VLOOKUP(Tabelle43[[#This Row],[Key]],'3. Unique Results'!A:X,20,FALSE) -> Association for Computing Machinery | U11: =VLOOKUP(Tabelle43[[#This Row],[Key]],'3. Unique Results'!A:X,21,FALSE) -> New York, NY, USA | V11: =VLOOKUP(Tabelle43[[#This Row],[Key]],'3. Unique Results'!A:X,22,FALSE) | W11: =VLOOKUP(Tabelle43[[#This Row],[Key]],'3. Unique Results'!A:X,23,FALSE)
A12: 8JWXJ9MR | B12: =VLOOKUP(Tabelle43[[#This Row],[Key]],'3. Unique Results'!A:X,2,FALSE) -> conferencePaper | C12: =VLOOKUP(Tabelle43[[#This Row],[Key]],'3. Unique Results'!A:X,3,FALSE) -> 2021 | D12: =VLOOKUP(Tabelle43[[#This Row],[Key]],'3. Unique Results'!A:X,4,FALSE) -> Eramo, Romina; Muttillo, Vittoriano; Berardinelli, Luca; Bruneliere, Hugo; Gomez, Abel; Bagnato, Alessandra; Sadovykh, Andrey; Cicchetti, Antonio | E12: =VLOOKUP(Tabelle43[[#This Row],[Key]],'3. Unique Results'!A:X,5,FALSE) -> AIDOaRt: AI-augmented Automation for DevOps, a Model-based Framework for Continuous Development in Cyber-Physical Systems | F12: =VLOOKUP(Tabelle43[[#This Row],[Key]],'3. Unique Results'!A:X,6,FALSE) -> 2021 24th Euromicro Conference on Digital System Design (DSD) | G12: =VLOOKUP(Tabelle43[[#This Row],[Key]],'3. Unique Results'!A:X,7,FALSE) | H12: =VLOOKUP(Tabelle43[[#This Row],[Key]],'3. Unique Results'!A:X,8,FALSE) | I12: =VLOOKUP(Tabelle43[[#This Row],[Key]],'3. Unique Results'!A:X,9,FALSE) -> 10.1109/DSD53832.2021.00053 | J12: =VLOOKUP(Tabelle43[[#This Row],[Key]],'3. Unique Results'!A:X,10,FALSE) | K12: =VLOOKUP(Tabelle43[[#This Row],[Key]],'3. Unique Results'!A:X,11,FALSE) -> 2021 | L12: =VLOOKUP(Tabelle43[[#This Row],[Key]],'3. Unique Results'!A:X,12,FALSE) -> 44887.364 | M12: =VLOOKUP(Tabelle43[[#This Row],[Key]],'3. Unique Results'!A:X,13,FALSE) -> 44887.364 | N12: =VLOOKUP(Tabelle43[[#This Row],[Key]],'3. Unique Results'!A:X,14,FALSE) -> 0 | O12: =VLOOKUP(Tabelle43[[#This Row],[Key]],'3. Unique Results'!A:X,15,FALSE) -> 303-310 | P12: =VLOOKUP(Tabelle43[[#This Row],[Key]],'3. Unique Results'!A:X,16,FALSE) | Q12: =VLOOKUP(Tabelle43[[#This Row],[Key]],'3. Unique Results'!A:X,17,FALSE) | R12: =VLOOKUP(Tabelle43[[#This Row],[Key]],'3. Unique Results'!A:X,18,FALSE) | S12: =VLOOKUP(Tabelle43[[#This Row],[Key]],'3. Unique Results'!A:X,19,FALSE) | T12: =VLOOKUP(Tabelle43[[#This Row],[Key]],'3. Unique Results'!A:X,20,FALSE) | U12: =VLOOKUP(Tabelle43[[#This Row],[Key]],'3. Unique Results'!A:X,21,FALSE) | V12: =VLOOKUP(Tabelle43[[#This Row],[Key]],'3. Unique Results'!A:X,22,FALSE) | W12: =VLOOKUP(Tabelle43[[#This Row],[Key]],'3. Unique Results'!A:X,23,FALSE)
A13: SLULQZRF | B13: =VLOOKUP(Tabelle43[[#This Row],[Key]],'3. Unique Results'!A:X,2,FALSE) -> journalArticle | C13: =VLOOKUP(Tabelle43[[#This Row],[Key]],'3. Unique Results'!A:X,3,FALSE) -> 2022 | D13: =VLOOKUP(Tabelle43[[#This Row],[Key]],'3. Unique Results'!A:X,4,FALSE) -> Giner-Miguelez, J.; Gómez, A.; Cabot, J. | E13: =VLOOKUP(Tabelle43[[#This Row],[Key]],'3. Unique Results'!A:X,5,FALSE) -> A domain-specific language for describing machine learning dataset | F13: =VLOOKUP(Tabelle43[[#This Row],[Key]],'3. Unique Results'!A:X,6,FALSE) -> arXiv preprint arXiv:2207.02848 | G13: =VLOOKUP(Tabelle43[[#This Row],[Key]],'3. Unique Results'!A:X,7,FALSE) | H13: =VLOOKUP(Tabelle43[[#This Row],[Key]],'3. Unique Results'!A:X,8,FALSE) | I13: =VLOOKUP(Tabelle43[[#This Row],[Key]],'3. Unique Results'!A:X,9,FALSE) | J13: =VLOOKUP(Tabelle43[[#This Row],[Key]],'3. Unique Results'!A:X,10,FALSE) -> https://arxiv.org/abs/2207.02848 | K13: =VLOOKUP(Tabelle43[[#This Row],[Key]],'3. Unique Results'!A:X,11,FALSE) -> 2022 | L13: =VLOOKUP(Tabelle43[[#This Row],[Key]],'3. Unique Results'!A:X,12,FALSE) -> 44887.364 | M13: =VLOOKUP(Tabelle43[[#This Row],[Key]],'3. Unique Results'!A:X,13,FALSE) -> 44887.364 | N13: =VLOOKUP(Tabelle43[[#This Row],[Key]],'3. Unique Results'!A:X,14,FALSE) -> 0 | O13: =VLOOKUP(Tabelle43[[#This Row],[Key]],'3. Unique Results'!A:X,15,FALSE) | P13: =VLOOKUP(Tabelle43[[#This Row],[Key]],'3. Unique Results'!A:X,16,FALSE) | Q13: =VLOOKUP(Tabelle43[[#This Row],[Key]],'3. Unique Results'!A:X,17,FALSE) | R13: =VLOOKUP(Tabelle43[[#This Row],[Key]],'3. Unique Results'!A:X,18,FALSE) | S13: =VLOOKUP(Tabelle43[[#This Row],[Key]],'3. Unique Results'!A:X,19,FALSE) | T13: =VLOOKUP(Tabelle43[[#This Row],[Key]],'3. Unique Results'!A:X,20,FALSE) | U13: =VLOOKUP(Tabelle43[[#This Row],[Key]],'3. Unique Results'!A:X,21,FALSE) | V13: =VLOOKUP(Tabelle43[[#This Row],[Key]],'3. Unique Results'!A:X,22,FALSE) | W13: =VLOOKUP(Tabelle43[[#This Row],[Key]],'3. Unique Results'!A:X,23,FALSE)
... A38: KP52PSST | B38: =VLOOKUP(Tabelle43[[#This Row],[Key]],'3. Unique Results'!A:X,2,FALSE) -> conferencePaper | C38: =VLOOKUP(Tabelle43[[#This Row],[Key]],'3. Unique Results'!A:X,3,FALSE) -> 2020 | D38: =VLOOKUP(Tabelle43[[#This Row],[Key]],'3. Unique Results'!A:X,4,FALSE) -> Zucker, Julian; d'Leeuwen, Myraeka | E38: =VLOOKUP(Tabelle43[[#This Row],[Key]],'3. Unique Results'!A:X,5,FALSE) -> Arbiter: A Domain-Specific Language for Ethical Machine Learning | F38: =VLOOKUP(Tabelle43[[#This Row],[Key]],'3. Unique Results'!A:X,6,FALSE) -> AIES '20: AAAI/ACM Conference on AI, Ethics, and Society, New York, NY, USA, February 7-8, 2020 | G38: =VLOOKUP(Tabelle43[[#This Row],[Key]],'3. Unique Results'!A:X,7,FALSE) | H38: =VLOOKUP(Tabelle43[[#This Row],[Key]],'3. Unique Results'!A:X,8,FALSE) | I38: =VLOOKUP(Tabelle43[[#This Row],[Key]],'3. Unique Results'!A:X,9,FALSE) -> 10.1145/3375627.3375858 | J38: =VLOOKUP(Tabelle43[[#This Row],[Key]],'3. Unique Results'!A:X,10,FALSE) -> https://doi.org/10.1145/3375627.3375858 | K38: =VLOOKUP(Tabelle43[[#This Row],[Key]],'3. Unique Results'!A:X,11,FALSE) -> 2020 | L38: =VLOOKUP(Tabelle43[[#This Row],[Key]],'3. Unique Results'!A:X,12,FALSE) -> 44887.364 | M38: =VLOOKUP(Tabelle43[[#This Row],[Key]],'3. Unique Results'!A:X,13,FALSE) -> 44887.364 | N38: =VLOOKUP(Tabelle43[[#This Row],[Key]],'3. Unique Results'!A:X,14,FALSE) -> 0 | O38: =VLOOKUP(Tabelle43[[#This Row],[Key]],'3. Unique Results'!A:X,15,FALSE) -> 421–425 | P38: =VLOOKUP(Tabelle43[[#This Row],[Key]],'3. Unique Results'!A:X,16,FALSE) | Q38: =VLOOKUP(Tabelle43[[#This Row],[Key]],'3. Unique Results'!A:X,17,FALSE) | R38: =VLOOKUP(Tabelle43[[#This Row],[Key]],'3. Unique Results'!A:X,18,FALSE) | S38: =VLOOKUP(Tabelle43[[#This Row],[Key]],'3. Unique Results'!A:X,19,FALSE) | T38: =VLOOKUP(Tabelle43[[#This Row],[Key]],'3. Unique Results'!A:X,20,FALSE) -> ACM | U38: =VLOOKUP(Tabelle43[[#This Row],[Key]],'3. Unique Results'!A:X,21,FALSE) | V38: =VLOOKUP(Tabelle43[[#This Row],[Key]],'3. Unique Results'!A:X,22,FALSE) | W38: =VLOOKUP(Tabelle43[[#This Row],[Key]],'3. Unique Results'!A:X,23,FALSE)

Sheet 6. Selection Based on Full-Text
A1: Key | B1: Item Type | C1: Publication Year | D1: Author | E1: Title | F1: Publication Title | G1: ISBN | H1: ISSN | I1: DOI | J1: Url | K1: Abstract Note | L1: Date | M1: Date Added | N1: Date Modified | O1: Access Date | P1: Pages | Q1: Num Pages | R1: Issue | S1: Volume | T1: Series | U1: Publisher | V1: Place | W1: Extra
A2: UCWWRPIQ | B2: =VLOOKUP(Tabelle434[[#This Row],[Key]],'3. Unique Results'!A:X,2,FALSE) -> conferencePaper | C2: =VLOOKUP(Tabelle434[[#This Row],[Key]],'3. Unique Results'!A:X,3,FALSE) -> 2020 | D2: =VLOOKUP(Tabelle434[[#This Row],[Key]],'3. Unique Results'!A:X,4,FALSE) -> Al-Azzoni, Issam | E2: =VLOOKUP(Tabelle434[[#This Row],[Key]],'3. Unique Results'!A:X,5,FALSE) -> Model Driven Approach for Neural Networks | F2: =VLOOKUP(Tabelle434[[#This Row],[Key]],'3. Unique Results'!A:X,6,FALSE) -> 2020 International Conference on Intelligent Data Science Technologies and Applications (IDSTA) | G2: =VLOOKUP(Tabelle434[[#This Row],[Key]],'3. Unique Results'!A:X,7,FALSE) | H2: =VLOOKUP(Tabelle434[[#This Row],[Key]],'3. Unique Results'!A:X,8,FALSE) | I2: =VLOOKUP(Tabelle434[[#This Row],[Key]],'3. Unique Results'!A:X,9,FALSE) -> 10.1109/IDSTA50958.2020.9264067 | J2: =VLOOKUP(Tabelle434[[#This Row],[Key]],'3. Unique Results'!A:X,10,FALSE) | K2: =VLOOKUP(Tabelle434[[#This Row],[Key]],'3. Unique Results'!A:X,11,FALSE) -> 2020 | L2: =VLOOKUP(Tabelle434[[#This Row],[Key]],'3. Unique Results'!A:X,12,FALSE) -> 44887.364 | M2: =VLOOKUP(Tabelle434[[#This Row],[Key]],'3. Unique Results'!A:X,13,FALSE) -> 44887.364 | N2: =VLOOKUP(Tabelle434[[#This Row],[Key]],'3. Unique Results'!A:X,14,FALSE) -> 0 | O2: =VLOOKUP(Tabelle434[[#This Row],[Key]],'3. Unique Results'!A:X,15,FALSE) -> 87-94 | P2: =VLOOKUP(Tabelle434[[#This Row],[Key]],'3. Unique Results'!A:X,16,FALSE) | Q2: =VLOOKUP(Tabelle434[[#This Row],[Key]],'3. Unique Results'!A:X,17,FALSE) | R2: =VLOOKUP(Tabelle434[[#This Row],[Key]],'3. Unique Results'!A:X,18,FALSE) | S2: =VLOOKUP(Tabelle434[[#This Row],[Key]],'3. Unique Results'!A:X,19,FALSE) | T2: =VLOOKUP(Tabelle434[[#This Row],[Key]],'3. Unique Results'!A:X,20,FALSE) | U2: =VLOOKUP(Tabelle434[[#This Row],[Key]],'3. Unique Results'!A:X,21,FALSE) | V2: =VLOOKUP(Tabelle434[[#This Row],[Key]],'3. Unique Results'!A:X,22,FALSE) | W2: =VLOOKUP(Tabelle434[[#This Row],[Key]],'3. Unique Results'!A:X,23,FALSE)
A3: BQTIAXTW | B3: =VLOOKUP(Tabelle434[[#This Row],[Key]],'3. Unique Results'!A:X,2,FALSE) -> conferencePaper | C3: =VLOOKUP(Tabelle434[[#This Row],[Key]],'3. Unique Results'!A:X,3,FALSE) -> 2019 | D3: =VLOOKUP(Tabelle434[[#This Row],[Key]],'3. Unique Results'!A:X,4,FALSE) -> Bhattacharjee, Anirban; Barve, Yogesh; Khare, Shweta; Bao, Shunxing; Kang, Zhuangwei; Gokhale, Aniruddha; Damiano, Thomas | E3: =VLOOKUP(Tabelle434[[#This Row],[Key]],'3. Unique Results'!A:X,5,FALSE) -> STRATUM: A BigData-as-a-Service for Lifecycle Management of IoT Analytics Applications | F3: =VLOOKUP(Tabelle434[[#This Row],[Key]],'3. Unique Results'!A:X,6,FALSE) -> 2019 IEEE International Conference on Big Data (Big Data) | G3: =VLOOKUP(Tabelle434[[#This Row],[Key]],'3. Unique Results'!A:X,7,FALSE) | H3: =VLOOKUP(Tabelle434[[#This Row],[Key]],'3. Unique Results'!A:X,8,FALSE) | I3: =VLOOKUP(Tabelle434[[#This Row],[Key]],'3. Unique Results'!A:X,9,FALSE) -> 10.1109/BigData47090.2019.9006518 | J3: =VLOOKUP(Tabelle434[[#This Row],[Key]],'3. Unique Results'!A:X,10,FALSE) | K3: =VLOOKUP(Tabelle434[[#This Row],[Key]],'3. Unique Results'!A:X,11,FALSE) -> 2019 | L3: =VLOOKUP(Tabelle434[[#This Row],[Key]],'3. Unique Results'!A:X,12,FALSE) -> 44887.364 | M3: =VLOOKUP(Tabelle434[[#This Row],[Key]],'3. Unique Results'!A:X,13,FALSE) -> 44887.364 | N3: =VLOOKUP(Tabelle434[[#This Row],[Key]],'3. Unique Results'!A:X,14,FALSE) -> 0 | O3: =VLOOKUP(Tabelle434[[#This Row],[Key]],'3. Unique Results'!A:X,15,FALSE) -> 1607-1612 | P3: =VLOOKUP(Tabelle434[[#This Row],[Key]],'3. Unique Results'!A:X,16,FALSE) | Q3: =VLOOKUP(Tabelle434[[#This Row],[Key]],'3. Unique Results'!A:X,17,FALSE) | R3: =VLOOKUP(Tabelle434[[#This Row],[Key]],'3. Unique Results'!A:X,18,FALSE) | S3: =VLOOKUP(Tabelle434[[#This Row],[Key]],'3. Unique Results'!A:X,19,FALSE) | T3: =VLOOKUP(Tabelle434[[#This Row],[Key]],'3. Unique Results'!A:X,20,FALSE) | U3: =VLOOKUP(Tabelle434[[#This Row],[Key]],'3. Unique Results'!A:X,21,FALSE) | V3: =VLOOKUP(Tabelle434[[#This Row],[Key]],'3. Unique Results'!A:X,22,FALSE) | W3: =VLOOKUP(Tabelle434[[#This Row],[Key]],'3. Unique Results'!A:X,23,FALSE)
A4: UJPER7V8 | B4: =VLOOKUP(Tabelle434[[#This Row],[Key]],'3. Unique Results'!A:X,2,FALSE) -> journalArticle | C4: =VLOOKUP(Tabelle434[[#This Row],[Key]],'3. Unique Results'!A:X,3,FALSE) -> 2014 | D4: =VLOOKUP(Tabelle434[[#This Row],[Key]],'3. Unique Results'!A:X,4,FALSE) -> Breuker, D. | E4: =VLOOKUP(Tabelle434[[#This Row],[Key]],'3. Unique Results'!A:X,5,FALSE) -> Towards Model-Driven Engineering for Big Data Analytics–An Exploratory Analysis of Domain-Specific Languages for Machine Learning | F4: =VLOOKUP(Tabelle434[[#This Row],[Key]],'3. Unique Results'!A:X,6,FALSE) -> 2014 47th Hawaii International Conference on … | G4: =VLOOKUP(Tabelle434[[#This Row],[Key]],'3. Unique Results'!A:X,7,FALSE) | H4: =VLOOKUP(Tabelle434[[#This Row],[Key]],'3. Unique Results'!A:X,8,FALSE) | I4: =VLOOKUP(Tabelle434[[#This Row],[Key]],'3. Unique Results'!A:X,9,FALSE) | J4: =VLOOKUP(Tabelle434[[#This Row],[Key]],'3. Unique Results'!A:X,10,FALSE) -> https://ieeexplore.ieee.org/abstract/document/6758697/ | K4: =VLOOKUP(Tabelle434[[#This Row],[Key]],'3. Unique Results'!A:X,11,FALSE) -> 2014 | L4: =VLOOKUP(Tabelle434[[#This Row],[Key]],'3. Unique Results'!A:X,12,FALSE) -> 44887.364 | M4: =VLOOKUP(Tabelle434[[#This Row],[Key]],'3. Unique Results'!A:X,13,FALSE) -> 44887.364 | N4: =VLOOKUP(Tabelle434[[#This Row],[Key]],'3. Unique Results'!A:X,14,FALSE) -> 0 | O4: =VLOOKUP(Tabelle434[[#This Row],[Key]],'3. Unique Results'!A:X,15,FALSE) | P4: =VLOOKUP(Tabelle434[[#This Row],[Key]],'3. Unique Results'!A:X,16,FALSE) | Q4: =VLOOKUP(Tabelle434[[#This Row],[Key]],'3. Unique Results'!A:X,17,FALSE) | R4: =VLOOKUP(Tabelle434[[#This Row],[Key]],'3. Unique Results'!A:X,18,FALSE) | S4: =VLOOKUP(Tabelle434[[#This Row],[Key]],'3. Unique Results'!A:X,19,FALSE) | T4: =VLOOKUP(Tabelle434[[#This Row],[Key]],'3. Unique Results'!A:X,20,FALSE) | U4: =VLOOKUP(Tabelle434[[#This Row],[Key]],'3. Unique Results'!A:X,21,FALSE) | V4: =VLOOKUP(Tabelle434[[#This Row],[Key]],'3. Unique Results'!A:X,22,FALSE) | W4: =VLOOKUP(Tabelle434[[#This Row],[Key]],'3. Unique Results'!A:X,23,FALSE)
A5: 3QB88ANK | B5: =VLOOKUP(Tabelle434[[#This Row],[Key]],'3. Unique Results'!A:X,2,FALSE) -> conferencePaper | C5: =VLOOKUP(Tabelle434[[#This Row],[Key]],'3. Unique Results'!A:X,3,FALSE) -> 2022 | D5: =VLOOKUP(Tabelle434[[#This Row],[Key]],'3. Unique Results'!A:X,4,FALSE) -> Burnay, Corentin; Giunta, Benito | E5: =VLOOKUP(Tabelle434[[#This Row],[Key]],'3. Unique Results'!A:X,5,FALSE) -> Towards Integrated Model-Driven Engineering Approach to Business Intelligence | F5: =VLOOKUP(Tabelle434[[#This Row],[Key]],'3. Unique Results'!A:X,6,FALSE) -> Research Challenges in Information Science | G5: =VLOOKUP(Tabelle434[[#This Row],[Key]],'3. Unique Results'!A:X,7,FALSE) -> 978-3-031-05759-5 978-3-031-05760-1 | H5: =VLOOKUP(Tabelle434[[#This Row],[Key]],'3. Unique Results'!A:X,8,FALSE) | I5: =VLOOKUP(Tabelle434[[#This Row],[Key]],'3. Unique Results'!A:X,9,FALSE) | J5: =VLOOKUP(Tabelle434[[#This Row],[Key]],'3. Unique Results'!A:X,10,FALSE) -> https://link.springer.com/10.1007/978-3-031-05760-1_38 | K5: =VLOOKUP(Tabelle434[[#This Row],[Key]],'3. Unique Results'!A:X,11,FALSE) -> 2022 | L5: =VLOOKUP(Tabelle434[[#This Row],[Key]],'3. Unique Results'!A:X,12,FALSE) -> 44887.364 | M5: =VLOOKUP(Tabelle434[[#This Row],[Key]],'3. Unique Results'!A:X,13,FALSE) -> 44887.364 | N5: =VLOOKUP(Tabelle434[[#This Row],[Key]],'3. Unique Results'!A:X,14,FALSE) -> 44886.598 | O5: =VLOOKUP(Tabelle434[[#This Row],[Key]],'3. Unique Results'!A:X,15,FALSE) -> 635-643 | P5: =VLOOKUP(Tabelle434[[#This Row],[Key]],'3. Unique Results'!A:X,16,FALSE) | Q5: =VLOOKUP(Tabelle434[[#This Row],[Key]],'3. Unique Results'!A:X,17,FALSE) -> 446 | R5: =VLOOKUP(Tabelle434[[#This Row],[Key]],'3. Unique Results'!A:X,18,FALSE) | S5: =VLOOKUP(Tabelle434[[#This Row],[Key]],'3. Unique Results'!A:X,19,FALSE) | T5: =VLOOKUP(Tabelle434[[#This Row],[Key]],'3. Unique Results'!A:X,20,FALSE) -> Springer International Publishing | U5: =VLOOKUP(Tabelle434[[#This Row],[Key]],'3. Unique Results'!A:X,21,FALSE) -> Cham | V5: =VLOOKUP(Tabelle434[[#This Row],[Key]],'3. Unique Results'!A:X,22,FALSE) -> en | W5: =VLOOKUP(Tabelle434[[#This Row],[Key]],'3. Unique Results'!A:X,23,FALSE) -> DOI.org (Crossref)
A6: HMQVEDXS | B6: =VLOOKUP(Tabelle434[[#This Row],[Key]],'3. Unique Results'!A:X,2,FALSE) -> conferencePaper | C6: =VLOOKUP(Tabelle434[[#This Row],[Key]],'3. Unique Results'!A:X,3,FALSE) -> 2017 | D6: =VLOOKUP(Tabelle434[[#This Row],[Key]],'3. Unique Results'!A:X,4,FALSE) -> Dethlefs, Nina; Hawick, Ken | E6: =VLOOKUP(Tabelle434[[#This Row],[Key]],'3. Unique Results'!A:X,5,FALSE) -> DEFIne: A Fluent Interface DSL for Deep Learning Applications | F6: =VLOOKUP(Tabelle434[[#This Row],[Key]],'3. Unique Results'!A:X,6,FALSE) -> Proceedings of the 2nd International Workshop on Real World Domain Specific Languages | G6: =VLOOKUP(Tabelle434[[#This Row],[Key]],'3. Unique Results'!A:X,7,FALSE) -> 978-1-4503-4845-4 | H6: =VLOOKUP(Tabelle434[[#This Row],[Key]],'3. Unique Results'!A:X,8,FALSE) | I6: =VLOOKUP(Tabelle434[[#This Row],[Key]],'3. Unique Results'!A:X,9,FALSE) -> 10.1145/3039895.3039898 | J6: =VLOOKUP(Tabelle434[[#This Row],[Key]],'3. Unique Results'!A:X,10,FALSE) -> https://doi.org/10.1145/3039895.3039898 | K6: =VLOOKUP(Tabelle434[[#This Row],[Key]],'3. Unique Results'!A:X,11,FALSE) -> 2017 | L6: =VLOOKUP(Tabelle434[[#This Row],[Key]],'3. Unique Results'!A:X,12,FALSE) -> 44887.364 | M6: =VLOOKUP(Tabelle434[[#This Row],[Key]],'3. Unique Results'!A:X,13,FALSE) -> 44887.411 | N6: =VLOOKUP(Tabelle434[[#This Row],[Key]],'3. Unique Results'!A:X,14,FALSE) -> 0 | O6: =VLOOKUP(Tabelle434[[#This Row],[Key]],'3. Unique Results'!A:X,15,FALSE) | P6: =VLOOKUP(Tabelle434[[#This Row],[Key]],'3. Unique Results'!A:X,16,FALSE) | Q6: =VLOOKUP(Tabelle434[[#This Row],[Key]],'3. Unique Results'!A:X,17,FALSE) | R6: =VLOOKUP(Tabelle434[[#This Row],[Key]],'3. Unique Results'!A:X,18,FALSE) | S6: =VLOOKUP(Tabelle434[[#This Row],[Key]],'3. Unique Results'!A:X,19,FALSE) | T6: =VLOOKUP(Tabelle434[[#This Row],[Key]],'3. Unique Results'!A:X,20,FALSE) -> Association for Computing Machinery | U6: =VLOOKUP(Tabelle434[[#This Row],[Key]],'3. Unique Results'!A:X,21,FALSE) -> New York, NY, USA | V6: =VLOOKUP(Tabelle434[[#This Row],[Key]],'3. Unique Results'!A:X,22,FALSE) | W6: =VLOOKUP(Tabelle434[[#This Row],[Key]],'3. Unique Results'!A:X,23,FALSE)
A7: SLULQZRF | B7: =VLOOKUP(Tabelle434[[#This Row],[Key]],'3. Unique Results'!A:X,2,FALSE) -> journalArticle | C7: =VLOOKUP(Tabelle434[[#This Row],[Key]],'3. Unique Results'!A:X,3,FALSE) -> 2022 | D7: =VLOOKUP(Tabelle434[[#This Row],[Key]],'3. Unique Results'!A:X,4,FALSE) -> Giner-Miguelez, J.; Gómez, A.; Cabot, J. | E7: =VLOOKUP(Tabelle434[[#This Row],[Key]],'3. Unique Results'!A:X,5,FALSE) -> A domain-specific language for describing machine learning dataset | F7: =VLOOKUP(Tabelle434[[#This Row],[Key]],'3. Unique Results'!A:X,6,FALSE) -> arXiv preprint arXiv:2207.02848 | G7: =VLOOKUP(Tabelle434[[#This Row],[Key]],'3. Unique Results'!A:X,7,FALSE) | H7: =VLOOKUP(Tabelle434[[#This Row],[Key]],'3. Unique Results'!A:X,8,FALSE) | I7: =VLOOKUP(Tabelle434[[#This Row],[Key]],'3. Unique Results'!A:X,9,FALSE) | J7: =VLOOKUP(Tabelle434[[#This Row],[Key]],'3. Unique Results'!A:X,10,FALSE) -> https://arxiv.org/abs/2207.02848 | K7: =VLOOKUP(Tabelle434[[#This Row],[Key]],'3. Unique Results'!A:X,11,FALSE) -> 2022 | L7: =VLOOKUP(Tabelle434[[#This Row],[Key]],'3. Unique Results'!A:X,12,FALSE) -> 44887.364 | M7: =VLOOKUP(Tabelle434[[#This Row],[Key]],'3. Unique Results'!A:X,13,FALSE) -> 44887.364 | N7: =VLOOKUP(Tabelle434[[#This Row],[Key]],'3. Unique Results'!A:X,14,FALSE) -> 0 | O7: =VLOOKUP(Tabelle434[[#This Row],[Key]],'3. Unique Results'!A:X,15,FALSE) | P7: =VLOOKUP(Tabelle434[[#This Row],[Key]],'3. Unique Results'!A:X,16,FALSE) | Q7: =VLOOKUP(Tabelle434[[#This Row],[Key]],'3. Unique Results'!A:X,17,FALSE) | R7: =VLOOKUP(Tabelle434[[#This Row],[Key]],'3. Unique Results'!A:X,18,FALSE) | S7: =VLOOKUP(Tabelle434[[#This Row],[Key]],'3. Unique Results'!A:X,19,FALSE) | T7: =VLOOKUP(Tabelle434[[#This Row],[Key]],'3. Unique Results'!A:X,20,FALSE) | U7: =VLOOKUP(Tabelle434[[#This Row],[Key]],'3. Unique Results'!A:X,21,FALSE) | V7: =VLOOKUP(Tabelle434[[#This Row],[Key]],'3. Unique Results'!A:X,22,FALSE) | W7: =VLOOKUP(Tabelle434[[#This Row],[Key]],'3. Unique Results'!A:X,23,FALSE)
A8: HNLKTP5J | B8: =VLOOKUP(Tabelle434[[#This Row],[Key]],'3. Unique Results'!A:X,2,FALSE) -> conferencePaper | C8: =VLOOKUP(Tabelle434[[#This Row],[Key]],'3. Unique Results'!A:X,3,FALSE) -> 2017 | D8: =VLOOKUP(Tabelle434[[#This Row],[Key]],'3. Unique Results'!A:X,4,FALSE) -> Hartmann, Thomas; Moawad, Assaad; Fouquet, Francois; Traon, Yves Le | E8: =VLOOKUP(Tabelle434[[#This Row],[Key]],'3. Unique Results'!A:X,5,FALSE) -> The next Evolution of MDE: A Seamless Integration of Machine Learning into Domain Modeling | F8: =VLOOKUP(Tabelle434[[#This Row],[Key]],'3. Unique Results'!A:X,6,FALSE) -> Proceedings of the ACM/IEEE 20th International Conference on Model Driven Engineering Languages and Systems | G8: =VLOOKUP(Tabelle434[[#This Row],[Key]],'3. Unique Results'!A:X,7,FALSE) -> 978-1-5386-3492-9 | H8: =VLOOKUP(Tabelle434[[#This Row],[Key]],'3. Unique Results'!A:X,8,FALSE) | I8: =VLOOKUP(Tabelle434[[#This Row],[Key]],'3. Unique Results'!A:X,9,FALSE) -> 10.1109/MODELS.2017.32 | J8: =VLOOKUP(Tabelle434[[#This Row],[Key]],'3. Unique Results'!A:X,10,FALSE) -> https://doi.org/10.1109/MODELS.2017.32 | K8: =VLOOKUP(Tabelle434[[#This Row],[Key]],'3. Unique Results'!A:X,11,FALSE) -> 2017 | L8: =VLOOKUP(Tabelle434[[#This Row],[Key]],'3. Unique Results'!A:X,12,FALSE) -> 44887.364 | M8: =VLOOKUP(Tabelle434[[#This Row],[Key]],'3. Unique Results'!A:X,13,FALSE) -> 44887.492 | N8: =VLOOKUP(Tabelle434[[#This Row],[Key]],'3. Unique Results'!A:X,14,FALSE) -> 0 | O8: =VLOOKUP(Tabelle434[[#This Row],[Key]],'3. Unique Results'!A:X,15,FALSE) -> 180 | P8: =VLOOKUP(Tabelle434[[#This Row],[Key]],'3. Unique Results'!A:X,16,FALSE) | Q8: =VLOOKUP(Tabelle434[[#This Row],[Key]],'3. Unique Results'!A:X,17,FALSE) | R8: =VLOOKUP(Tabelle434[[#This Row],[Key]],'3. Unique Results'!A:X,18,FALSE) | S8: =VLOOKUP(Tabelle434[[#This Row],[Key]],'3. Unique Results'!A:X,19,FALSE) | T8: =VLOOKUP(Tabelle434[[#This Row],[Key]],'3. Unique Results'!A:X,20,FALSE) -> IEEE Press | U8: =VLOOKUP(Tabelle434[[#This Row],[Key]],'3. Unique Results'!A:X,21,FALSE) | V8: =VLOOKUP(Tabelle434[[#This Row],[Key]],'3. Unique Results'!A:X,22,FALSE) | W8: =VLOOKUP(Tabelle434[[#This Row],[Key]],'3. Unique Results'!A:X,23,FALSE)
A9: AVGA8TJW | B9: =VLOOKUP(Tabelle434[[#This Row],[Key]],'3. Unique Results'!A:X,2,FALSE) -> conferencePaper | C9: =VLOOKUP(Tabelle434[[#This Row],[Key]],'3. Unique Results'!A:X,3,FALSE) -> 2019 | D9: =VLOOKUP(Tabelle434[[#This Row],[Key]],'3. Unique Results'!A:X,4,FALSE) -> Hartmann, Thomas; Moawad, Assaad; Schockaert, Cedric; Fouquet, Francois; Le Traon, Yves | E9: =VLOOKUP(Tabelle434[[#This Row],[Key]],'3. Unique Results'!A:X,5,FALSE) -> Meta-Modelling Meta-Learning | F9: =VLOOKUP(Tabelle434[[#This Row],[Key]],'3. Unique Results'!A:X,6,FALSE) -> 2019 ACM/IEEE 22nd International Conference on Model Driven Engineering Languages and Systems (MODELS) | G9: =VLOOKUP(Tabelle434[[#This Row],[Key]],'3. Unique Results'!A:X,7,FALSE) | H9: =VLOOKUP(Tabelle434[[#This Row],[Key]],'3. Unique Results'!A:X,8,FALSE) | I9: =VLOOKUP(Tabelle434[[#This Row],[Key]],'3. Unique Results'!A:X,9,FALSE) -> 10.1109/MODELS.2019.00014 | J9: =VLOOKUP(Tabelle434[[#This Row],[Key]],'3. Unique Results'!A:X,10,FALSE) | K9: =VLOOKUP(Tabelle434[[#This Row],[Key]],'3. Unique Results'!A:X,11,FALSE) -> 2019 | L9: =VLOOKUP(Tabelle434[[#This Row],[Key]],'3. Unique Results'!A:X,12,FALSE) -> 44887.364 | M9: =VLOOKUP(Tabelle434[[#This Row],[Key]],'3. Unique Results'!A:X,13,FALSE) -> 44887.364 | N9: =VLOOKUP(Tabelle434[[#This Row],[Key]],'3. Unique Results'!A:X,14,FALSE) -> 0 | O9: =VLOOKUP(Tabelle434[[#This Row],[Key]],'3. Unique Results'!A:X,15,FALSE) -> 300-305 | P9: =VLOOKUP(Tabelle434[[#This Row],[Key]],'3. Unique Results'!A:X,16,FALSE) | Q9: =VLOOKUP(Tabelle434[[#This Row],[Key]],'3. Unique Results'!A:X,17,FALSE) | R9: =VLOOKUP(Tabelle434[[#This Row],[Key]],'3. Unique Results'!A:X,18,FALSE) | S9: =VLOOKUP(Tabelle434[[#This Row],[Key]],'3. Unique Results'!A:X,19,FALSE) | T9: =VLOOKUP(Tabelle434[[#This Row],[Key]],'3. Unique Results'!A:X,20,FALSE) | U9: =VLOOKUP(Tabelle434[[#This Row],[Key]],'3. Unique Results'!A:X,21,FALSE) | V9: =VLOOKUP(Tabelle434[[#This Row],[Key]],'3. Unique Results'!A:X,22,FALSE) | W9: =VLOOKUP(Tabelle434[[#This Row],[Key]],'3. Unique Results'!A:X,23,FALSE)
A10: 7SMEDRAN | B10: =VLOOKUP(Tabelle434[[#This Row],[Key]],'3. Unique Results'!A:X,2,FALSE) -> conferencePaper | C10: =VLOOKUP(Tabelle434[[#This Row],[Key]],'3. Unique Results'!A:X,3,FALSE) -> 2019 | D10: =VLOOKUP(Tabelle434[[#This Row],[Key]],'3. Unique Results'!A:X,4,FALSE) -> Koseler, Kaan; McGraw, Kelsea; Stephan, Matthew | E10: =VLOOKUP(Tabelle434[[#This Row],[Key]],'3. Unique Results'!A:X,5,FALSE) -> Realization of a Machine Learning Domain Specific Modeling Language: A Baseball Analytics Case Study | F10: =VLOOKUP(Tabelle434[[#This Row],[Key]],'3. Unique Results'!A:X,6,FALSE) -> Proceedings of the 7th International Conference on Model-Driven Engineering and Software Development, MODELSWARD 2019, Prague, Czech Republic, February 20-22, 2019 | G10: =VLOOKUP(Tabelle434[[#This Row],[Key]],'3. Unique Results'!A:X,7,FALSE) | H10: =VLOOKUP(Tabelle434[[#This Row],[Key]],'3. Unique Results'!A:X,8,FALSE) | I10: =VLOOKUP(Tabelle434[[#This Row],[Key]],'3. Unique Results'!A:X,9,FALSE) -> 10.5220/0007245800150026 | J10: =VLOOKUP(Tabelle434[[#This Row],[Key]],'3. Unique Results'!A:X,10,FALSE) -> https://doi.org/10.5220/0007245800150026 | K10: =VLOOKUP(Tabelle434[[#This Row],[Key]],'3. Unique Results'!A:X,11,FALSE) -> 2019 | L10: =VLOOKUP(Tabelle434[[#This Row],[Key]],'3. Unique Results'!A:X,12,FALSE) -> 44887.364 | M10: =VLOOKUP(Tabelle434[[#This Row],[Key]],'3. Unique Results'!A:X,13,FALSE) -> 44887.364 | N10: =VLOOKUP(Tabelle434[[#This Row],[Key]],'3. Unique Results'!A:X,14,FALSE) -> 0 | O10: =VLOOKUP(Tabelle434[[#This Row],[Key]],'3. Unique Results'!A:X,15,FALSE) -> 13–24 | P10: =VLOOKUP(Tabelle434[[#This Row],[Key]],'3. Unique Results'!A:X,16,FALSE) | Q10: =VLOOKUP(Tabelle434[[#This Row],[Key]],'3. Unique Results'!A:X,17,FALSE) | R10: =VLOOKUP(Tabelle434[[#This Row],[Key]],'3. Unique Results'!A:X,18,FALSE) | S10: =VLOOKUP(Tabelle434[[#This Row],[Key]],'3. Unique Results'!A:X,19,FALSE) | T10: =VLOOKUP(Tabelle434[[#This Row],[Key]],'3. Unique Results'!A:X,20,FALSE) -> SciTePress | U10: =VLOOKUP(Tabelle434[[#This Row],[Key]],'3. Unique Results'!A:X,21,FALSE) | V10: =VLOOKUP(Tabelle434[[#This Row],[Key]],'3. Unique Results'!A:X,22,FALSE) | W10: =VLOOKUP(Tabelle434[[#This Row],[Key]],'3. Unique Results'!A:X,23,FALSE)
A11: R9ALKAH3 | B11: =VLOOKUP(Tabelle434[[#This Row],[Key]],'3. Unique Results'!A:X,2,FALSE) -> journalArticle | C11: =VLOOKUP(Tabelle434[[#This Row],[Key]],'3. Unique Results'!A:X,3,FALSE) -> 2021 | D11: =VLOOKUP(Tabelle434[[#This Row],[Key]],'3. Unique Results'!A:X,4,FALSE) -> Meacham, Sofia; Pech, Vaclav; Nauck, Detlef | E11: =VLOOKUP(Tabelle434[[#This Row],[Key]],'3. Unique Results'!A:X,5,FALSE) -> AdaptiveSystems: An Integrated Framework for Adaptive Systems Design and Development Using MPS JetBrains Domain-Specific Modeling Environment | F11: =VLOOKUP(Tabelle434[[#This Row],[Key]],'3. Unique Results'!A:X,6,FALSE) -> IEEE Access | G11: =VLOOKUP(Tabelle434[[#This Row],[Key]],'3. Unique Results'!A:X,7,FALSE) | H11: =VLOOKUP(Tabelle434[[#This Row],[Key]],'3. Unique Results'!A:X,8,FALSE) | I11: =VLOOKUP(Tabelle434[[#This Row],[Key]],'3. Unique Results'!A:X,9,FALSE) -> 10.1109/ACCESS.2021.3111229 | J11: =VLOOKUP(Tabelle434[[#This Row],[Key]],'3. Unique Results'!A:X,10,FALSE) | K11: =VLOOKUP(Tabelle434[[#This Row],[Key]],'3. Unique Results'!A:X,11,FALSE) -> 2021 | L11: =VLOOKUP(Tabelle434[[#This Row],[Key]],'3. Unique Results'!A:X,12,FALSE) -> 44887.364 | M11: =VLOOKUP(Tabelle434[[#This Row],[Key]],'3. Unique Results'!A:X,13,FALSE) -> 44887.364 | N11: =VLOOKUP(Tabelle434[[#This Row],[Key]],'3. Unique Results'!A:X,14,FALSE) -> 0 | O11: =VLOOKUP(Tabelle434[[#This Row],[Key]],'3. Unique Results'!A:X,15,FALSE) -> 127973-127984 | P11: =VLOOKUP(Tabelle434[[#This Row],[Key]],'3. Unique Results'!A:X,16,FALSE) | Q11: =VLOOKUP(Tabelle434[[#This Row],[Key]],'3. Unique Results'!A:X,17,FALSE) -> 9 | R11: =VLOOKUP(Tabelle434[[#This Row],[Key]],'3. Unique Results'!A:X,18,FALSE) | S11: =VLOOKUP(Tabelle434[[#This Row],[Key]],'3. Unique Results'!A:X,19,FALSE) | T11: =VLOOKUP(Tabelle434[[#This Row],[Key]],'3. Unique Results'!A:X,20,FALSE) | U11: =VLOOKUP(Tabelle434[[#This Row],[Key]],'3. Unique Results'!A:X,21,FALSE) | V11: =VLOOKUP(Tabelle434[[#This Row],[Key]],'3. Unique Results'!A:X,22,FALSE) | W11: =VLOOKUP(Tabelle434[[#This Row],[Key]],'3. Unique Results'!A:X,23,FALSE)
A12: XQ6GQKI8 | B12: =VLOOKUP(Tabelle434[[#This Row],[Key]],'3. Unique Results'!A:X,2,FALSE) -> journalArticle | C12: =VLOOKUP(Tabelle434[[#This Row],[Key]],'3. Unique Results'!A:X,3,FALSE) -> 2021 | D12: =VLOOKUP(Tabelle434[[#This Row],[Key]],'3. Unique Results'!A:X,4,FALSE) -> Moin, Armin; Badii, Atta; Günnemann, Stephan | E12: =VLOOKUP(Tabelle434[[#This Row],[Key]],'3. Unique Results'!A:X,5,FALSE) -> A Model-Driven Engineering Approach to Machine Learning and Software Modeling | F12: =VLOOKUP(Tabelle434[[#This Row],[Key]],'3. Unique Results'!A:X,6,FALSE) -> CoRR | G12: =VLOOKUP(Tabelle434[[#This Row],[Key]],'3. Unique Results'!A:X,7,FALSE) | H12: =VLOOKUP(Tabelle434[[#This Row],[Key]],'3. Unique Results'!A:X,8,FALSE) | I12: =VLOOKUP(Tabelle434[[#This Row],[Key]],'3. Unique Results'!A:X,9,FALSE) | J12: =VLOOKUP(Tabelle434[[#This Row],[Key]],'3. Unique Results'!A:X,10,FALSE) -> https://arxiv.org/abs/2107.02689 | K12: =VLOOKUP(Tabelle434[[#This Row],[Key]],'3. Unique Results'!A:X,11,FALSE) -> 2021 | L12: =VLOOKUP(Tabelle434[[#This Row],[Key]],'3. Unique Results'!A:X,12,FALSE) -> 44887.364 | M12: =VLOOKUP(Tabelle434[[#This Row],[Key]],'3. Unique Results'!A:X,13,FALSE) -> 44887.364 | N12: =VLOOKUP(Tabelle434[[#This Row],[Key]],'3. Unique Results'!A:X,14,FALSE) -> 0 | O12: =VLOOKUP(Tabelle434[[#This Row],[Key]],'3. Unique Results'!A:X,15,FALSE) | P12: =VLOOKUP(Tabelle434[[#This Row],[Key]],'3. Unique Results'!A:X,16,FALSE) | Q12: =VLOOKUP(Tabelle434[[#This Row],[Key]],'3. Unique Results'!A:X,17,FALSE) -> abs/2107.02689 | R12: =VLOOKUP(Tabelle434[[#This Row],[Key]],'3. Unique Results'!A:X,18,FALSE) | S12: =VLOOKUP(Tabelle434[[#This Row],[Key]],'3. Unique Results'!A:X,19,FALSE) | T12: =VLOOKUP(Tabelle434[[#This Row],[Key]],'3. Unique Results'!A:X,20,FALSE) | U12: =VLOOKUP(Tabelle434[[#This Row],[Key]],'3. Unique Results'!A:X,21,FALSE) | V12: =VLOOKUP(Tabelle434[[#This Row],[Key]],'3. Unique Results'!A:X,22,FALSE) | W12: =VLOOKUP(Tabelle434[[#This Row],[Key]],'3. Unique Results'!A:X,23,FALSE)
A13: 8W7BSBQX | B13: =VLOOKUP(Tabelle434[[#This Row],[Key]],'3. Unique Results'!A:X,2,FALSE) -> journalArticle | C13: =VLOOKUP(Tabelle434[[#This Row],[Key]],'3. Unique Results'!A:X,3,FALSE) -> 2022 | D13: =VLOOKUP(Tabelle434[[#This Row],[Key]],'3. Unique Results'!A:X,4,FALSE) -> Morales, Sergio; Clarisó, Robert; Cabot, Jordi | E13: =VLOOKUP(Tabelle434[[#This Row],[Key]],'3. Unique Results'!A:X,5,FALSE) -> Towards a DSL for AI Engineering Process Modeling | F13: =VLOOKUP(Tabelle434[[#This Row],[Key]],'3. Unique Results'!A:X,6,FALSE) -> Product-Focused Software Process Improvement | G13: =VLOOKUP(Tabelle434[[#This Row],[Key]],'3. Unique Results'!A:X,7,FALSE) | H13: =VLOOKUP(Tabelle434[[#This Row],[Key]],'3. Unique Results'!A:X,8,FALSE) | I13: =VLOOKUP(Tabelle434[[#This Row],[Key]],'3. Unique Results'!A:X,9,FALSE) | J13: =VLOOKUP(Tabelle434[[#This Row],[Key]],'3. Unique Results'!A:X,10,FALSE) -> https://link.springer.com/10.1007/978-3-031-21388-5_4 | K13: =VLOOKUP(Tabelle434[[#This Row],[Key]],'3. Unique Results'!A:X,11,FALSE) -> 2022 | L13: =VLOOKUP(Tabelle434[[#This Row],[Key]],'3. Unique Results'!A:X,12,FALSE) -> 44887.364 | M13: =VLOOKUP(Tabelle434[[#This Row],[Key]],'3. Unique Results'!A:X,13,FALSE) -> 44887.364 | N13: =VLOOKUP(Tabelle434[[#This Row],[Key]],'3. Unique Results'!A:X,14,FALSE) -> 44886.598 | O13: =VLOOKUP(Tabelle434[[#This Row],[Key]],'3. Unique Results'!A:X,15,FALSE) -> 53-60 | P13: =VLOOKUP(Tabelle434[[#This Row],[Key]],'3. Unique Results'!A:X,16,FALSE) | Q13: =VLOOKUP(Tabelle434[[#This Row],[Key]],'3. Unique Results'!A:X,17,FALSE) -> 13709 | R13: =VLOOKUP(Tabelle434[[#This Row],[Key]],'3. Unique Results'!A:X,18,FALSE) | S13: =VLOOKUP(Tabelle434[[#This Row],[Key]],'3. Unique Results'!A:X,19,FALSE) | T13: =VLOOKUP(Tabelle434[[#This Row],[Key]],'3. Unique Results'!A:X,20,FALSE) | U13: =VLOOKUP(Tabelle434[[#This Row],[Key]],'3. Unique Results'!A:X,21,FALSE) | V13: =VLOOKUP(Tabelle434[[#This Row],[Key]],'3. Unique Results'!A:X,22,FALSE) -> en | W13: =VLOOKUP(Tabelle434[[#This Row],[Key]],'3. Unique Results'!A:X,23,FALSE) -> DOI.org (Crossref)
... A16: KP52PSST | B16: =VLOOKUP(Tabelle434[[#This Row],[Key]],'3. Unique Results'!A:X,2,FALSE) -> conferencePaper | C16: =VLOOKUP(Tabelle434[[#This Row],[Key]],'3. Unique Results'!A:X,3,FALSE) -> 2020 | D16: =VLOOKUP(Tabelle434[[#This Row],[Key]],'3. Unique Results'!A:X,4,FALSE) -> Zucker, Julian; d'Leeuwen, Myraeka | E16: =VLOOKUP(Tabelle434[[#This Row],[Key]],'3. Unique Results'!A:X,5,FALSE) -> Arbiter: A Domain-Specific Language for Ethical Machine Learning | F16: =VLOOKUP(Tabelle434[[#This Row],[Key]],'3. Unique Results'!A:X,6,FALSE) -> AIES '20: AAAI/ACM Conference on AI, Ethics, and Society, New York, NY, USA, February 7-8, 2020 | G16: =VLOOKUP(Tabelle434[[#This Row],[Key]],'3. Unique Results'!A:X,7,FALSE) | H16: =VLOOKUP(Tabelle434[[#This Row],[Key]],'3. Unique Results'!A:X,8,FALSE) | I16: =VLOOKUP(Tabelle434[[#This Row],[Key]],'3. Unique Results'!A:X,9,FALSE) -> 10.1145/3375627.3375858 | J16: =VLOOKUP(Tabelle434[[#This Row],[Key]],'3. Unique Results'!A:X,10,FALSE) -> https://doi.org/10.1145/3375627.3375858 | K16: =VLOOKUP(Tabelle434[[#This Row],[Key]],'3. Unique Results'!A:X,11,FALSE) -> 2020 | L16: =VLOOKUP(Tabelle434[[#This Row],[Key]],'3. Unique Results'!A:X,12,FALSE) -> 44887.364 | M16: =VLOOKUP(Tabelle434[[#This Row],[Key]],'3. Unique Results'!A:X,13,FALSE) -> 44887.364 | N16: =VLOOKUP(Tabelle434[[#This Row],[Key]],'3. Unique Results'!A:X,14,FALSE) -> 0 | O16: =VLOOKUP(Tabelle434[[#This Row],[Key]],'3. Unique Results'!A:X,15,FALSE) -> 421–425 | P16: =VLOOKUP(Tabelle434[[#This Row],[Key]],'3. Unique Results'!A:X,16,FALSE) | Q16: =VLOOKUP(Tabelle434[[#This Row],[Key]],'3. Unique Results'!A:X,17,FALSE) | R16: =VLOOKUP(Tabelle434[[#This Row],[Key]],'3. Unique Results'!A:X,18,FALSE) | S16: =VLOOKUP(Tabelle434[[#This Row],[Key]],'3. Unique Results'!A:X,19,FALSE) | T16: =VLOOKUP(Tabelle434[[#This Row],[Key]],'3. Unique Results'!A:X,20,FALSE) -> ACM | U16: =VLOOKUP(Tabelle434[[#This Row],[Key]],'3. Unique Results'!A:X,21,FALSE) | V16: =VLOOKUP(Tabelle434[[#This Row],[Key]],'3. Unique Results'!A:X,22,FALSE) | W16: =VLOOKUP(Tabelle434[[#This Row],[Key]],'3. Unique Results'!A:X,23,FALSE)

Sheet 6.1 Snowballing Results
A1: Key | B1: Item Type | C1: Publication Year | D1: Author | E1: Title | F1: Publication Title | G1: ISBN | H1: ISSN | I1: DOI | J1: Url | K1: Abstract Note | L1: Date | M1: Date Added | N1: Date Modified | O1: Access Date | P1: Pages | Q1: Num Pages | R1: Issue | S1: Volume | T1: Series | U1: Publisher | V1: Place | W1: Extra
A2: V3QBE3TK | B2: conferencePaper | C2: 2019 | D2: Kusmenko, Evgeny; Pavlitskaya, Svetlana; Rumpe, Bernhard; Stuber, Sebastian | E2: On the Engineering of AI-Powered Systems | F2: 2019 34th IEEE/ACM International Conference on Automated Software Engineering Workshop (ASEW) | G2: 978-1-72814-136-7 | I2: 10.1109/ASEW.2019.00042 | J2: https://ieeexplore.ieee.org/document/8967413/ | K2: More and more tasks become solvable using deep learning technology nowadays. Consequently, the amount of neural network code in software rises continuously. To make the new paradigm more accessible, frameworks, languages, and tools keep emerging. Although, the maturity of these tools is steadily increasing, we still lack appropriate domain speciﬁc languages and a high degree of automation when it comes to deep learning for productive systems. In this paper we present a multi-paradigm language family allowing the AI engineer to model and train deep neural networks as well as to integrate them into software architectures containing classical code. Using input and output layers as strictly typed interfaces enables a seamless embedding of neural networks into component-based models. The lifecycle of deep learning components can then be governed by a compiler accordingly, e.g. detecting when (re-)training is necessary or when network weights can be shared between different network instances. We provide a compelling case study, where we train an autonomous vehicle for the TORCS simulator. Furthermore, we discuss how the methodology automates the AI development process if neural networks are changed or added to the system. | L2: 2019-11 | M2: 44889.802 | N2: 44889.802 | O2: 2020-09-26 10:03:29 | P2: 126-133 | U2: IEEE | V2: San Diego, CA, USA | W2: 6
A3: AVJUP5V9 | B3: conferencePaper | C3: 2019 | D3: Kusmenko, Evgeny; Nickels, Sebastian; Pavlitskaya, Svetlana; Rumpe, Bernhard; Timmermanns, Thomas | E3: Modeling and Training of Neural Processing Systems | F3: 2019 ACM/IEEE 22nd International Conference on Model Driven Engineering Languages and Systems (MODELS) | I3: 10.1109/MODELS.2019.00012 | K3: The field of deep learning has become more and more pervasive in the last years as we have seen varieties of problems being solved using neural processing techniques. Image analysis and detection, control, speech recognition, translation are only a few prominent examples tackled successfully by neural networks. Thereby, the discipline imposes a completely new problem solving paradigm requiring a rethinking of classical software development methods. The high demand for deep learning technology has led to a large amount of competing frameworks mostly having a Python interface - a quasi standard in the community. Although, existing tools often provide great flexibility and high performance, they still lack to deliver a completely domain oriented problem view. Furthermore, using neural networks as reusable building blocks with clear interfaces in productive systems is still a challenge. In this work we propose a domain specific modeling methodology tackling design, training, and integration of deep neural networks. Thereby, we distinguish between three main modeling concerns: architecture, training, and data. We integrate our methodology in a component-based modeling toolchain allowing one to employ and reuse neural networks in large software architectures. | L3: 2019-09 | M3: 44889.823 | N3: 44889.823 | P3: 283-293
A4: Z6UVCL7I | B4: conferencePaper | C4: 2019 | D4: Gatto, Nicola; Kusmenko, Evgeny; Rumpe, Bernhard | E4: Modeling Deep Reinforcement Learning Based Architectures for Cyber-Physical Systems | F4: 2019 ACM/IEEE 22nd International Conference on Model Driven Engineering Languages and Systems Companion (MODELS-C) | I4: 10.1109/MODELS-C.2019.00033 | K4: Reinforcement learning is a sub-field of machine learning where an agent aims to learn a behavior or a policy maximizing a reward function by trial and error. The approach is particularly interesting for the design of autonomous cyber-physical systems such as self-driving cars. In this work we present a generative, domain-specific modeling framework for the design, training and integration of reinforcement learning systems. It consists of a neural network modeling language which is used to design the models to be trained, e.g. actor and critic networks, and a training language used to describe the training procedure and set the corresponding hyperparameters. The underlying component model allows the modeler to embed the trained networks in larger component & connector architectures. We illustrate our framework by the example of a self-driving racing car. | L4: 2019-09 | M4: 44889.824 | N4: 44889.824 | P4: 196-202
A5: 5GDZMXTA | B5: journalArticle | C5: 2016 | D5: Portugal, Ivens; Alencar, Paulo; Cowan, Donald | E5: A Survey on Domain-Specific Languages for Machine Learning in Big Data | I5: 10.48550/ARXIV.1602.07637 | J5: https://arxiv.org/abs/1602.07637 | K5: The amount of data generated in the modern society is increasing rapidly. New problems and novel approaches of data capture, storage, analysis and visualization are responsible for the emergence of the Big Data research field. Machine Learning algorithms can be used in Big Data to make better and more accurate inferences. However, because of the challenges Big Data imposes, these algorithms need to be adapted and optimized to specific applications. One important decision made by software engineers is the choice of the language that is used in the implementation of these algorithms. Therefore, this literature survey identifies and describes domain-specific languages and frameworks used for Machine Learning in Big Data. By doing this, software engineers can then make more informed choices and beginners have an overview of the main languages used in this domain. | L5: 2016 | M5: 44889.837 | N5: 44889.837 | O5: 2022-11-24 20:05:27 | W5: Publisher: arXiv Version Number: 2
A6: 63Y89P2Q | B6: journalArticle | C6: 2020 | D6: Meacham, Sofia; Pech, Vaclav; Nauck, Detlef | E6: Classification Algorithms Framework (CAF) to Enable Intelligent Systems Using JetBrains MPS Domain-Specific Languages Environment | F6: IEEE Access | H6: 2169-3536 | I6: 10.1109/ACCESS.2020.2966630 | J6: https://ieeexplore.ieee.org/document/8959196/ | L6: 2020 | M6: 44889.839 | N6: 44889.839 | O6: 2022-11-24 20:08:25 | P6: 14832-14840 | S6: 8
A7: VSVTKZXP | B7: journalArticle | C7: 2013 | D7: Bishop, Christopher M. | E7: Model-based machine learning | F7: Philosophical Transactions of the Royal Society A: Mathematical, Physical and Engineering Sciences | I7: 10.1098/rsta.2012.0222 | J7: https://royalsocietypublishing.org/doi/10.1098/rsta.2012.0222 | K7: Several decades of research in the field of machine learning have resulted in a multitude of different algorithms for solving a broad range of problems. To tackle a new application, a researcher typically tries to map their problem onto one of these existing methods, often influenced by their familiarity with specific algorithms and by the availability of corresponding software implementations. In this study, we describe an alternative methodology for applying machine learning, in which a bespoke solution is formulated for each new application. The solution is expressed through a compact modelling language, and the corresponding custom machine learning code is then generated automatically. This model-based approach offers several major advantages, including the opportunity to create highly tailored models for specific scenarios, as well as rapid prototyping and comparison of a range of alternative models. Furthermore, newcomers to the field of machine learning do not have to learn about the huge range of traditional methods, but instead can focus their attention on understanding a single modelling environment. In this study, we show how probabilistic graphical models, coupled with efficient inference algorithms, provide a very flexible foundation for model-based machine learning, and we outline a large-scale commercial application of this framework involving tens of millions of users. We also describe the concept of probabilistic programming as a powerful software environment for model-based machine learning, and we discuss a specific probabilistic programming language called Infer.NET, which has been widely used in practical applications. | L7: 2013-02-13 | M7: 44889.841 | N7: 44889.841 | O7: 2022-11-24 20:11:19 | P7: 20120222 | R7: 1984 | S7: 371 | W7: Publisher: Royal Society
A8: NW73NKWY | B8: conferencePaper | C8: 2022 | D8: Melchor, Fran; Rodriguez-Echeverria, Roberto; Conejero, José M.; Prieto, Álvaro E.; Gutiérrez, Juan D. | E8: A Model-Driven Approach for Systematic Reproducibility and Replicability of Data Science Projects | F8: Advanced Information Systems Engineering | G8: 978-3-031-07472-1 | I8: 10.1007/978-3-031-07472-1_9 | K8: In the last few years, there has been an important increase in the number of tools and approaches to define pipelines that allow the development of data science projects. They allow not only the pipeline definition but also the code generation needed to execute the project providing an easy way to carry out the projects even for non-expert users. However, there are still some challenges that these tools do not address yet, e.g. the possibility of executing pipelines defined by using different tools or execute them in different environments (reproducibility and replicability) or models validation and verification by identifying inconsistent operations (intentionality). In order to alleviate these problems, this paper presents a Model-Driven framework for the definition of data science pipelines independent of the particular execution platform and tools. The framework relies on the separation of the pipeline definition into two different modelling layers: conceptual, where the data scientist may specify all the data and models operations to be carried out by the pipeline; operational, where the data engineer may describe the execution environment details where the operations (defined in the conceptual part) will be implemented. Based on this abstract definition and layers separation, the approach allows: the usage of different tools improving, thus, process replicability; the automation of the process execution, enhancing process reproducibility; and the definition of model verification rules, providing intentionality restrictions. | L8: 2022 | M8: 44889.843 | N8: 44889.843 | P8: 147-163 | U8: Springer International Publishing | V8: Cham
A9: ANY24S8B | B9: conferencePaper | C9: 2019 | D9: Hartsell, Charles; Mahadevan, Nagabhushan; Ramakrishna, Shreyas; Dubey, Abhishek; Bapty, Theodore; Johnson, Taylor; Koutsoukos, Xenofon; Sztipanovits, Janos; Karsai, Gabor | E9: Model-based design for CPS with learning-enabled components | F9: Proceedings of the Workshop on Design Automation for CPS and IoT | G9: 978-1-4503-6699-1 | I9: 10.1145/3313151.3313166 | J9: https://doi.org/10.1145/3313151.3313166 | K9: Recent advances in machine learning led to the appearance of Learning-Enabled Components (LECs) in Cyber-Physical Systems. LECs are being evaluated and used for various, complex functions including perception and control. However, very little tool support is available for design automation in such systems. This paper introduces an integrated toolchain that supports the architectural modeling of CPS with LECs, but also has extensive support for the engineering and integration of LECs, including support for training data collection, LEC training, LEC evaluation and verification, and system software deployment. Additionally, the toolsuite supports the modeling and analysis of safety cases - a critical part of the engineering process for mission and safety critical systems. | L9: 2019-04-15 | M9: 44889.854 | N9: 44889.854 | O9: 2022-11-24 | P9: 1–9 | U9: Association for Computing Machinery | V9: New York, NY, USA
A10: L7QXGU8P | B10: journalArticle | C10: 2020 | D10: de la Vega, Alfonso; García-Saiz, Diego; Zorrilla, Marta; Sánchez, Pablo | E10: Lavoisier: A DSL for increasing the level of abstraction of data selection and formatting in data mining | F10: Journal of Computer Languages | H10: 25901184 | I10: 10.1016/j.cola.2020.100987 | J10: https://linkinghub.elsevier.com/retrieve/pii/S2590118420300472 | L10: 2020-10 | M10: 44889.854 | N10: 44889.854 | O10: 2022-11-24 20:30:27 | P10: 100987 | S10: 60
A11: YTXBX3EZ | B11: conferencePaper | C11: 2021 | D11: Atouani, Abdallah; Kirchhof, Jörg Christian; Kusmenko, Evgeny; Rumpe, Bernhard | E11: Artifact and reference models for generative machine learning frameworks and build systems | F11: Proceedings of the 20th ACM SIGPLAN International Conference on Generative Programming: Concepts and Experiences | G11: 978-1-4503-9112-2 | I11: 10.1145/3486609.3487199 | J11: https://doi.org/10.1145/3486609.3487199 | K11: Machine learning is a discipline which has become ubiquitous in the last few years. While the research of machine learning algorithms is very active and continues to reveal astonishing possibilities on a regular basis, the wide usage of these algorithms is shifting the research focus to the integration, maintenance, and evolution of AI-driven systems. Although there is a variety of machine learning frameworks on the market, there is little support for process automation and DevOps in machine learning-driven projects. In this paper, we discuss how metamodels can support the development of deep learning frameworks and help deal with the steadily increasing variety of learning algorithms. In particular, we present a deep learning-oriented artifact model which serves as a foundation for build automation and data management in iterative, machine learning-driven development processes. Furthermore, we show how schema and reference models can be used to structure and maintain a versatile deep learning framework. Feasibility is demonstrated on several state-of-the-art examples from the domains of image and natural language processing as well as decision making and autonomous driving. | L11: 2021-11-22 | M11: 44889.855 | N11: 44889.855 | O11: 2022-11-24 | P11: 55–68 | U11: Association for Computing Machinery | V11: New York, NY, USA
A12: T74GXRNC | B12: conferencePaper | C12: 2017 | D12: Zafar, Muhammad Nouman; Azam, Farooque; Rehman, Saad; Anwar, Muhammad Waseem | E12: A Systematic Review of Big Data Analytics Using Model Driven Engineering | F12: Proceedings of the 2017 International Conference on Cloud and Big Data Computing - ICCBDC 2017 | G12: 978-1-4503-5343-4 | I12: 10.1145/3141128.3141138 | J12: http://dl.acm.org/citation.cfm?doid=3141128.3141138 | L12: 2017 | M12: 44889.858 | N12: 44889.858 | O12: 2022-11-24 20:36:02 | P12: 1-5 | U12: ACM Press | V12: London, United Kingdom
A13: 8AJBF667 | B13: journalArticle | C13: 2009 | D13: Berthold, Michael R.; Cebron, Nicolas; Dill, Fabian; Gabriel, Thomas R.; Kötter, Tobias; Meinl, Thorsten; Ohl, Peter; Thiel, Kilian; Wiswedel, Bernd | E13: KNIME - the Konstanz information miner: version 2.0 and beyond | F13: ACM SIGKDD Explorations Newsletter | H13: 1931-0145 | I13: 10.1145/1656274.1656280 | J13: https://doi.org/10.1145/1656274.1656280 | K13: The Konstanz Information Miner is a modular environment, which enables easy visual assembly and interactive execution of a data pipeline. It is designed as a teaching, research and collaboration platform, which enables simple integration of new algorithms and tools as well as data manipulation or visualization methods in the form of new modules or nodes. In this paper we describe some of the design aspects of the underlying architecture, briey sketch how new nodes can be incorporated, and highlight some of the new features of version 2.0. | L13: 2009-11-16 | M13: 44890.341 | N13: 44890.341 | O13: 2022-11-25 08:10:54 | P13: 26–31 | R13: 1 | S13: 11
A14: 6NTZWCVK | B14: conferencePaper | C14: 2014 | D14: Rajbhoj, Asha; Kulkarni, Vinay; Bellarykar, Nikhil | E14: Early Experience with Model-Driven Development of MapReduce Based Big Data Application | F14: 2014 21st Asia-Pacific Software Engineering Conference | G14: 978-1-4799-7425-2 978-1-4799-7426-9 | I14: 10.1109/APSEC.2014.23 | J14: http://ieeexplore.ieee.org/document/7091296/ | L14: 2014-12 | M14: 44890.499 | N14: 44892.312 | O14: 2022-11-25 11:57:57 | P14: 94-97 | U14: IEEE | V14: Jeju, South Korea | W14: 11 citations (Semantic Scholar/DOI) [2022-11-27]
A15: CTCP4BER | B15: conferencePaper | C15: 2016 | D15: Guerriero, Michele; Tajfar, Saeed; Tamburri, Damian A.; Di Nitto, Elisabetta | E15: Towards a model-driven design tool for big data architectures | F15: Proceedings of the 2nd International Workshop on BIG Data Software Engineering - BIGDSE '16 | G15: 978-1-4503-4152-3 | I15: 10.1145/2896825.2896835 | J15: http://dl.acm.org/citation.cfm?doid=2896825.2896835 | L15: 2016 | M15: 44890.5 | N15: 44892.312 | O15: 2022-11-25 11:59:37 | P15: 37-43 | U15: ACM Press | V15: Austin, Texas | W15: 34 citations (Semantic Scholar/DOI) [2022-11-27]

Sheet 6.2 Snowballing Full-Text
A1: Key | B1: Item Type | C1: Publication Year | D1: Author | E1: Title | F1: Publication Title | G1: ISBN | H1: ISSN | I1: DOI | J1: Url | K1: Abstract Note | L1: Date | M1: Date Added | N1: Date Modified | O1: Access Date | P1: Pages | Q1: Num Pages | R1: Issue | S1: Volume | T1: Series | U1: Publisher | V1: Place | W1: Extra
A2: V3QBE3TK | B2: conferencePaper | C2: 2019 | D2: Kusmenko, Evgeny; Pavlitskaya, Svetlana; Rumpe, Bernhard; Stuber, Sebastian | E2: On the Engineering of AI-Powered Systems | F2: 2019 34th IEEE/ACM International Conference on Automated Software Engineering Workshop (ASEW) | G2: 978-1-72814-136-7 | I2: 10.1109/ASEW.2019.00042 | J2: https://ieeexplore.ieee.org/document/8967413/ | K2: More and more tasks become solvable using deep learning technology nowadays. Consequently, the amount of neural network code in software rises continuously. To make the new paradigm more accessible, frameworks, languages, and tools keep emerging. Although, the maturity of these tools is steadily increasing, we still lack appropriate domain speciﬁc languages and a high degree of automation when it comes to deep learning for productive systems. In this paper we present a multi-paradigm language family allowing the AI engineer to model and train deep neural networks as well as to integrate them into software architectures containing classical code. Using input and output layers as strictly typed interfaces enables a seamless embedding of neural networks into component-based models. The lifecycle of deep learning components can then be governed by a compiler accordingly, e.g. detecting when (re-)training is necessary or when network weights can be shared between different network instances. We provide a compelling case study, where we train an autonomous vehicle for the TORCS simulator. Furthermore, we discuss how the methodology automates the AI development process if neural networks are changed or added to the system. | L2: 2019-11 | M2: 44889.802 | N2: 44889.802 | O2: 2020-09-26 10:03:29 | P2: 126-133 | U2: IEEE | V2: San Diego, CA, USA | W2: 6
A3: AVJUP5V9 | B3: conferencePaper | C3: 2019 | D3: Kusmenko, Evgeny; Nickels, Sebastian; Pavlitskaya, Svetlana; Rumpe, Bernhard; Timmermanns, Thomas | E3: Modeling and Training of Neural Processing Systems | F3: 2019 ACM/IEEE 22nd International Conference on Model Driven Engineering Languages and Systems (MODELS) | I3: 10.1109/MODELS.2019.00012 | K3: The field of deep learning has become more and more pervasive in the last years as we have seen varieties of problems being solved using neural processing techniques. Image analysis and detection, control, speech recognition, translation are only a few prominent examples tackled successfully by neural networks. Thereby, the discipline imposes a completely new problem solving paradigm requiring a rethinking of classical software development methods. The high demand for deep learning technology has led to a large amount of competing frameworks mostly having a Python interface - a quasi standard in the community. Although, existing tools often provide great flexibility and high performance, they still lack to deliver a completely domain oriented problem view. Furthermore, using neural networks as reusable building blocks with clear interfaces in productive systems is still a challenge. In this work we propose a domain specific modeling methodology tackling design, training, and integration of deep neural networks. Thereby, we distinguish between three main modeling concerns: architecture, training, and data. We integrate our methodology in a component-based modeling toolchain allowing one to employ and reuse neural networks in large software architectures. | L3: 2019-09 | M3: 44889.823 | N3: 44889.823 | P3: 283-293
A4: Z6UVCL7I | B4: conferencePaper | C4: 2019 | D4: Gatto, Nicola; Kusmenko, Evgeny; Rumpe, Bernhard | E4: Modeling Deep Reinforcement Learning Based Architectures for Cyber-Physical Systems | F4: 2019 ACM/IEEE 22nd International Conference on Model Driven Engineering Languages and Systems Companion (MODELS-C) | I4: 10.1109/MODELS-C.2019.00033 | K4: Reinforcement learning is a sub-field of machine learning where an agent aims to learn a behavior or a policy maximizing a reward function by trial and error. The approach is particularly interesting for the design of autonomous cyber-physical systems such as self-driving cars. In this work we present a generative, domain-specific modeling framework for the design, training and integration of reinforcement learning systems. It consists of a neural network modeling language which is used to design the models to be trained, e.g. actor and critic networks, and a training language used to describe the training procedure and set the corresponding hyperparameters. The underlying component model allows the modeler to embed the trained networks in larger component & connector architectures. We illustrate our framework by the example of a self-driving racing car. | L4: 2019-09 | M4: 44889.824 | N4: 44889.824 | P4: 196-202
A5: NW73NKWY | B5: conferencePaper | C5: 2022 | D5: Melchor, Fran; Rodriguez-Echeverria, Roberto; Conejero, José M.; Prieto, Álvaro E.; Gutiérrez, Juan D. | E5: A Model-Driven Approach for Systematic Reproducibility and Replicability of Data Science Projects | F5: Advanced Information Systems Engineering | G5: 978-3-031-07472-1 | I5: 10.1007/978-3-031-07472-1_9 | K5: In the last few years, there has been an important increase in the number of tools and approaches to define pipelines that allow the development of data science projects. They allow not only the pipeline definition but also the code generation needed to execute the project providing an easy way to carry out the projects even for non-expert users. However, there are still some challenges that these tools do not address yet, e.g. the possibility of executing pipelines defined by using different tools or execute them in different environments (reproducibility and replicability) or models validation and verification by identifying inconsistent operations (intentionality). In order to alleviate these problems, this paper presents a Model-Driven framework for the definition of data science pipelines independent of the particular execution platform and tools. The framework relies on the separation of the pipeline definition into two different modelling layers: conceptual, where the data scientist may specify all the data and models operations to be carried out by the pipeline; operational, where the data engineer may describe the execution environment details where the operations (defined in the conceptual part) will be implemented. Based on this abstract definition and layers separation, the approach allows: the usage of different tools improving, thus, process replicability; the automation of the process execution, enhancing process reproducibility; and the definition of model verification rules, providing intentionality restrictions. | L5: 2022 | M5: 44889.843 | N5: 44889.843 | P5: 147-163 | U5: Springer International Publishing | V5: Cham
A6: ANY24S8B | B6: conferencePaper | C6: 2019 | D6: Hartsell, Charles; Mahadevan, Nagabhushan; Ramakrishna, Shreyas; Dubey, Abhishek; Bapty, Theodore; Johnson, Taylor; Koutsoukos, Xenofon; Sztipanovits, Janos; Karsai, Gabor | E6: Model-based design for CPS with learning-enabled components | F6: Proceedings of the Workshop on Design Automation for CPS and IoT | G6: 978-1-4503-6699-1 | I6: 10.1145/3313151.3313166 | J6: https://doi.org/10.1145/3313151.3313166 | K6: Recent advances in machine learning led to the appearance of Learning-Enabled Components (LECs) in Cyber-Physical Systems. LECs are being evaluated and used for various, complex functions including perception and control. However, very little tool support is available for design automation in such systems. This paper introduces an integrated toolchain that supports the architectural modeling of CPS with LECs, but also has extensive support for the engineering and integration of LECs, including support for training data collection, LEC training, LEC evaluation and verification, and system software deployment. Additionally, the toolsuite supports the modeling and analysis of safety cases - a critical part of the engineering process for mission and safety critical systems. | L6: 2019-04-15 | M6: 44889.854 | N6: 44889.854 | O6: 2022-11-24 | P6: 1–9 | U6: Association for Computing Machinery | V6: New York, NY, USA
A7: L7QXGU8P | B7: journalArticle | C7: 2020 | D7: de la Vega, Alfonso; García-Saiz, Diego; Zorrilla, Marta; Sánchez, Pablo | E7: Lavoisier: A DSL for increasing the level of abstraction of data selection and formatting in data mining | F7: Journal of Computer Languages | H7: 25901184 | I7: 10.1016/j.cola.2020.100987 | J7: https://linkinghub.elsevier.com/retrieve/pii/S2590118420300472 | L7: 2020-10 | M7: 44889.854 | N7: 44889.854 | O7: 2022-11-24 20:30:27 | P7: 100987 | S7: 60
C11: Duplicate

Sheet 7. Data-Extraction
D1: 1 | E1: 2 | F1: 3 | G1: 4 | H1: 5 | I1: 6 | J1: 7 | K1: 8 | L1: 9 | M1: 10 | N1: 11 | O1: 12 | P1: 13 | Q1: 14 | R1: 15 | S1: 16 | T1: 17 | U1: 18
D2: UCWWRPIQ | E2: BQTIAXTW | F2: UJPER7V8 | G2: 3QB88ANK | H2: L7QXGU8P | I2: HMQVEDXS | J2: SLULQZRF | K2: HNLKTP5J | L2: AVGA8TJW | M2: ANY24S8B | N2: 7SMEDRAN | O2: V3QBE3TK | P2: R9ALKAH3 | Q2: NW73NKWY | R2: XQ6GQKI8 | S2: 8W7BSBQX | T2: E77DCQEB | U2: KP52PSST
D3: =VLOOKUP(D2,'3. Unique Results'!$A:$X,4,FALSE) -> Al-Azzoni, Issam | E3: =VLOOKUP(E2,'3. Unique Results'!$A:$X,4,FALSE) -> Bhattacharjee, Anirban; Barve, Yogesh; Khare, Shweta; Bao, Shunxing; Kang, Zhuangwei; Gokhale, Aniruddha; Damiano, Thomas | F3: =VLOOKUP(F2,'3. Unique Results'!$A:$X,4,FALSE) -> Breuker, D. | G3: =VLOOKUP(G2,'3. Unique Results'!$A:$X,4,FALSE) -> Burnay, Corentin; Giunta, Benito | H3: de la Vega, Alfonso; García-Saiz, Diego; Zorrilla, Marta; Sánchez, Pablo | I3: =VLOOKUP(I2,'3. Unique Results'!$A:$X,4,FALSE) -> Dethlefs, Nina; Hawick, Ken | J3: =VLOOKUP(J2,'3. Unique Results'!$A:$X,4,FALSE) -> Giner-Miguelez, J.; Gómez, A.; Cabot, J. | K3: =VLOOKUP(K2,'3. Unique Results'!$A:$X,4,FALSE) -> Hartmann, Thomas; Moawad, Assaad; Fouquet, Francois; Traon, Yves Le | L3: =VLOOKUP(L2,'3. Unique Results'!$A:$X,4,FALSE) -> Hartmann, Thomas; Moawad, Assaad; Schockaert, Cedric; Fouquet, Francois; Le Traon, Yves | M3: Hartsell, Charles; Mahadevan, Nagabhushan; Ramakrishna, Shreyas; Dubey, Abhishek; Bapty, Theodore; Johnson, Taylor; Koutsoukos, Xenofon; Sztipanovits, Janos; Karsai, Gabor | N3: =VLOOKUP(N2,'3. Unique Results'!$A:$X,4,FALSE) -> Koseler, Kaan; McGraw, Kelsea; Stephan, Matthew | O3: Kusmenko, Evgeny; Pavlitskaya, Svetlana; Rumpe, Bernhard; Stuber, Sebastian | P3: =VLOOKUP(P2,'3. Unique Results'!$A:$X,4,FALSE) -> Meacham, Sofia; Pech, Vaclav; Nauck, Detlef | Q3: Melchor, Fran; Rodriguez-Echeverria, Roberto; Conejero, José M.; Prieto, Álvaro E.; Gutiérrez, Juan D. | R3: =VLOOKUP(R2,'3. Unique Results'!$A:$X,4,FALSE) -> Moin, Armin; Badii, Atta; Günnemann, Stephan | S3: =VLOOKUP(S2,'3. Unique Results'!$A:$X,4,FALSE) -> Morales, Sergio; Clarisó, Robert; Cabot, Jordi | T3: =VLOOKUP(T2,'3. Unique Results'!$A:$X,4,FALSE) -> Ries, Benoît; Guelfi, Nicolas; Jahic, Benjamin | U3: =VLOOKUP(U2,'3. Unique Results'!$A:$X,4,FALSE) -> Zucker, Julian; d'Leeuwen, Myraeka
A4: RQ | B4: Concern | D4: =VLOOKUP(D2,'3. Unique Results'!$A:$X,5,FALSE) -> Model Driven Approach for Neural Networks | E4: =VLOOKUP(E2,'3. Unique Results'!$A:$X,5,FALSE) -> STRATUM: A BigData-as-a-Service for Lifecycle Management of IoT Analytics Applications | F4: =VLOOKUP(F2,'3. Unique Results'!$A:$X,5,FALSE) -> Towards Model-Driven Engineering for Big Data Analytics–An Exploratory Analysis of Domain-Specific Languages for Machine Learning | G4: =VLOOKUP(G2,'3. Unique Results'!$A:$X,5,FALSE) -> Towards Integrated Model-Driven Engineering Approach to Business Intelligence | H4: Lavoisier: A DSL for increasing the level of abstraction of data selection and formatting in data mining | I4: =VLOOKUP(I2,'3. Unique Results'!$A:$X,5,FALSE) -> DEFIne: A Fluent Interface DSL for Deep Learning Applications | J4: =VLOOKUP(J2,'3. Unique Results'!$A:$X,5,FALSE) -> A domain-specific language for describing machine learning dataset | K4: =VLOOKUP(K2,'3. Unique Results'!$A:$X,5,FALSE) -> The next Evolution of MDE: A Seamless Integration of Machine Learning into Domain Modeling | L4: =VLOOKUP(L2,'3. Unique Results'!$A:$X,5,FALSE) -> Meta-Modelling Meta-Learning | M4: Model-based design for CPS with learning-enabled components | N4: =VLOOKUP(N2,'3. Unique Results'!$A:$X,5,FALSE) -> Realization of a Machine Learning Domain Specific Modeling Language: A Baseball Analytics Case Study | O4: On the Engineering of AI-Powered Systems | P4: =VLOOKUP(P2,'3. Unique Results'!$A:$X,5,FALSE) -> AdaptiveSystems: An Integrated Framework for Adaptive Systems Design and Development Using MPS JetBrains Domain-Specific Modeling Environment | Q4: A Model-Driven Approach for Systematic Reproducibility and Replicability of Data Science Projects | R4: =VLOOKUP(R2,'3. Unique Results'!$A:$X,5,FALSE) -> A Model-Driven Engineering Approach to Machine Learning and Software Modeling | S4: =VLOOKUP(S2,'3. Unique Results'!$A:$X,5,FALSE) -> Towards a DSL for AI Engineering Process Modeling | T4: =VLOOKUP(T2,'3. Unique Results'!$A:$X,5,FALSE) -> An MDE Method for Improving Deep Learning Dataset Requirements Engineering using Alloy and UML | U4: =VLOOKUP(U2,'3. Unique Results'!$A:$X,5,FALSE) -> Arbiter: A Domain-Specific Language for Ethical Machine Learning
C5: Type of Publication | D5: Technical Paper | E5: Technical Paper | F5: Exploratory Paper (Basis of Koseler) | G5: Exploratory Paper | H5: Technical Paper | I5: Technical Paper | J5: Technical Paper | K5: Technical Paper | L5: Exploratory Paper | M5: Technical Paper | N5: Empirical Paper | O5: Technical Paper | P5: Technical Paper | Q5: Technical Paper | R5: Technical Paper | S5: Exploratory Paper | T5: Technical Paper | U5: Technical Paper (maybe exploratory paper)
A6: RQ1 | B6: MDE | C6: Meta-Models | D6: Yes | E6: Yes | F6: No | G6: No | H6: Yes | I6: No | J6: Yes | K6: Yes | L6: Yes | M6: Yes | N6: Yes | O6: No | P6: No | Q6: Yes | R6: Yes | S6: Yes | T6: Yes | U6: No
C7: Abstract Syntax | D7: No | E7: Yes | F7: Yes | G7: No | H7: Yes | I7: No | J7: Yes | K7: Yes | L7: Yes | M7: Yes | N7: Yes | O7: Yes | P7: Yes | Q7: Yes | R7: Yes | S7: Yes | T7: No | U7: No
C8: Concrete Syntax | D8: Yes | E8: Yes | F8: No | G8: No | H8: Yes | I8: Yes | J8: Yes | K8: Yes | L8: Yes | M8: Yes | N8: Yes | O8: Yes | P8: Yes | Q8: No | R8: Yes | S8: Yes | T8: Yes | U8: Yes
C9: Arbitrary Constraints | D9: Yes | E9: Yes | F9: No | G9: No | H9: No | I9: No | J9: No | K9: No | L9: No | M9: Yes | N9: Yes | O9: No | P9: No | Q9: Yes | R9: No | S9: No | T9: Yes | U9: Yes
C10: Model Transformation | D10: Yes | E10: Yes | F10: No | G10: No | H10: Yes | I10: No | J10: No | K10: Yes | L10: Yes | M10: Yes | N10: Yes | O10: Yes | P10: Yes | Q10: No | R10: Yes | S10: No | T10: Yes | U10: No
A11: RQ2, RQ5 | B11: AI | C11: Requirements Modeling | D11: No | E11: No | F11: No | G11: No | H11: No | I11: No | J11: No | K11: No | L11: No | M11: Yes | N11: No | O11: No | P11: No | Q11: No | R11: No | S11: Yes | T11: Yes | U11: Yes
C12: Business Understanding | D12: No | E12: No | F12: No | G12: Yes | H12: No | I12: No | J12: No | K12: No | L12: No | M12: Yes | N12: No | O12: No | P12: No | Q12: No | R12: No | S12: Yes | T12: No | U12: No
C13: Data Understanding | D13: No | E13: No | F13: Yes | G13: Yes | H13: Yes | I13: No | J13: Yes | K13: Yes | L13: Yes | M13: No | N13: Yes | O13: No | P13: No | Q13: Yes | R13: No | S13: No | T13: Yes | U13: No
C14: Data Ingestion | D14: Yes | E14: Yes | F14: No | G14: No | H14: Yes | I14: Yes | J14: No | K14: No | L14: No | M14: Yes | N14: No | O14: Yes | P14: Yes | Q14: Yes | R14: Yes | S14: Yes | T14: No | U14: Yes
C15: Feature Preparation | D15: Yes | E15: Yes | F15: No | G15: No | H15: No | I15: Yes | J15: No | K15: No | L15: No | M15: No | N15: No | O15: No | P15: No | Q15: Yes | R15: Yes | S15: Yes | T15: No | U15: No
C16: Model Training | D16: Yes | E16: Yes | F16: Yes | G16: No | H16: No | I16: Yes | J16: No | K16: Yes | L16: Yes | M16: Yes | N16: Yes | O16: Yes | P16: Yes | Q16: Yes | R16: Yes | S16: Yes | T16: No | U16: No
C17: Metrics/Evaluation | D17: No | E17: Yes | F17: No | G17: No | H17: No | I17: Yes | J17: No | K17: No | L17: No | M17: Yes | N17: No | O17: Yes | P17: No | Q17: No | R17: Yes | S17: No | T17: No | U17: No
A18: RQ3 | B18: Others | C18: Type of Application | D18: Datasets (Diabetes) | E18: IoT/Industry | F18: Unknown | G18: Business Intelligence | H18: Datasets | I18: Datasets | J18: Human related data | K18: IoT | L18: Unknown | M18: IoT | N18: Sportanalytics | O18: CPS (Image) | P18: adaptive Virtual Learning Environment | Q18: Datasets | R18: IoT | S18: Unknown | T18: Datasets | U18: Fairness, Accountability and Transparency of Datasets
A19: RQ4 | C19: Frameworks (Methods & Tools) | D19: Eclipse Modeling Framework (EMF) | E19: WebGME | F19: None | G19: None | H19: Ecore; xtext | I19: Python (Fluent Interface language) | J19: Langium | K19: GreyCat | L19: GreyCat; Sirius Web | M19: WebGME; GSN; SEAM; ROSMOD; DeepForge | N19: Papyrus; Epsilon | O19: MontiCore | P19: Jetbrains MPS | Q19: Ecore-based; | R19: Papyrus; Xtext; ThingML | S19: Sirius Web | T19: Aloy; BPMN; Ecore; Jupyter Notebook; xtext | U19: Python; SQL
C20: Artifacts Available | D20: Yes | E20: Yes | F20: No | G20: No | H20: Yes | I20: No | J20: Yes | K20: Yes | L20: No | M20: yes | N20: yes | O20: Yes | Q20: Yes | R20: Yes | S20: Yes | T20: Yes | U20: Yes
